Workbook

Sheet Script Inventory
B2: SandBox
C3: AuthAPI | D3: =COUNTA(SBAuthAPI!E:E)-1 -> 26
C4: BankList | D4: =COUNTA(SBBankList!E:E)-1 -> 18
C5: CheckStatus | D5: =COUNTA(SBCheckStatus!E:E)-1 -> 60
C6: LFT | D6: =COUNTA(SBSendFunds!E:E)-1 -> 114
D7: =SUM(D3:D6) -> 218
B8: Test
C9: AuthAPI | D9: =COUNTA(PTTAuthAPI!E:E)-1 -> 27
C10: BankList | D10: =COUNTA(PTTBankList!E:E)-1 -> 19
C11: CheckStatus | D11: =COUNTA(PTTCheckStatus!E:E)-1 -> 59
C12: LFT | D12: =COUNTA(PTTSendFunds!E:E)-1 -> 230
D13: =SUM(D9:D12) -> 335
B14: Live
C15: AuthAPI | D15: =COUNTA(PTLAuthAPI!E:E)-1 -> 26
C16: BankList | D16: =COUNTA(PTLBankList!E:E)-1 -> 19
C17: CheckStatus | D17: =COUNTA(PTLCheckStatus!E:E)-1 -> 56
C18: LFT | D18: =COUNTA(PTLSendFunds!E:E)-1 -> 302
D19: =SUM(D15:D18) -> 403
C22: Overall Count | D22: =SUM(D7,D13,D19) -> 956

Sheet Legend
B2: Legend: | E2: Live
C3: Not Applicable | E3: hemPVxAxU8QC6QlJuS5GQoPiP0dFdBzP | F3: Client ID
C4: Valid Test Data Value | E4: pLRFPZKifoRD00dj761QToHciekWqbbh | F4: Client Secret
C5: Invalid Headers/Body | E5: KPEgf6fjIHDaT0HByFjWD49cQWdphJMM | F5: API Key
C6: Blocked TC | F6: Partner ID
C7: Undecided
C8: 200 OK But Transaction expected to Failed on Check Status | E8: Test
C9: Test Case can be confirmed using the previous test cases/ Related Test Case | E9: 3TaenF9h5d9FCEEIZRVPc4AxdFggPaxA | F9: Client ID
C10: Need to Add Cells for Additional parameters (body) | E10: wE4n0CYiVOdJ9m8EfKuMhxm0m4kOaUOr | F10: Client Secret
E11: K6y28Ks1TyrwjONU0PatZ6BhOWfTAuHo | F11: API Key
F12: Partner ID

Sheet SBAuthAPI
A1: # | B1: ExecutionFlag | C1: CORE | D1: TC_ID | E1: Description | F1: StepAction | G1: ExpectedResult | H1: ExpectedStatus | I1: ExpectedResponseDescription | J1: IN_EndPoint | K1: IN_HeadAccept | L1: IN_HeadClientID | M1: IN_HeadClientSecret | N1: IN_HeadPartnerID | O1: IN_HeadAPIKey | P1: IN_HeadContentType | Q1: IN_AccountNumber | R1: IN_Scope | S1: OUT_RequestHeaders | T1: OUT_RequestBody | U1: OUT_ResponseHeaders | V1: OUT_ResponseBody
A2: 1 | B2: Y | C2: Y | D2: TS-EB-SB-PRODUCTS-0102 | E2: TS-EB-SB-PRODUCTS-0102: Account Authentication via Access Token v1.0_Generate Account Access Token API_Verify Token generation for Client-Owned Account | F2: Send POST Request using Client-Owned Account | G2: Successful Request Status 200 OK Response Body contains: - access_token [Token is valid and usable] - token_type - expires_in -authId Request logged in API Portal DB | H2: 200 | J2: /auth/token/v1/generate | K2: application/json | L2: 1VjIqTcMCJ8tIv8bMpv9l9x01ebYQd88 | M2: cnfKqb1Q53rmlS8HifRZf7zvtGZOSlUQ | N2: 104234abc4 | O2: GsG5c0UhuhXUPj4XlY8G1kcjKioiFrqI | P2: application/json | Q2: 200061777902 | R2: send-funds.initiate
A3: 2 | B3: Y | C3: Y | D3: TS-EB-SB-PRODUCTS-0103_1 | E3: TS-EB-SB-PRODUCTS-0103_1: Account Authentication via Access Token v1.0_Generate Account Access Token API_Verify send request with missing mandatory parameters. | F3: Send POST Request with missing mandatory parameters | G3: Failed 400 (Bad Request) Error details for missing fields Response Body contains: - access_token [Token is valid and usable] - token_type - expires_in -authId | H3: 400 | I3: The scope provided is invalid or not recognized | J3: /auth/token/v1/generate | K3: application/json | L3: 1VjIqTcMCJ8tIv8bMpv9l9x01ebYQd88 | M3: cnfKqb1Q53rmlS8HifRZf7zvtGZOSlUQ | N3: 104234abc4 | O3: GsG5c0UhuhXUPj4XlY8G1kcjKioiFrqI | P3: application/json | Q3: 200061777902
A4: 3 | B4: Y | C4: Y | D4: TS-EB-SB-PRODUCTS-0103_2 | E4: TS-EB-SB-PRODUCTS-0103_2: Account Authentication via Access Token v1.0_Generate Account Access Token API_Verify send request with missing mandatory parameters. | F4: Send POST Request with missing mandatory parameters | G4: Failed 400 (Bad Request) Error details for missing fields | H4: 400 | I4: The accountNumber provided is invalid, not recognized, or not registered in Client Hub. | J4: /auth/token/v1/generate | K4: application/json | L4: 1VjIqTcMCJ8tIv8bMpv9l9x01ebYQd88 | M4: cnfKqb1Q53rmlS8HifRZf7zvtGZOSlUQ | N4: 104234abc4 | O4: GsG5c0UhuhXUPj4XlY8G1kcjKioiFrqI | P4: application/json | R4: send-funds.initiate
A5: 4 | B5: Y | C5: Y | D5: TS-EB-SB-PRODUCTS-0105 | E5: TS-EB-SB-PRODUCTS-0105: Account Authentication via Access Token v1.0_Generate Account Access Token API_Verify successful POST Authentication using Client Owned Account with ACTIVE status and with valid client-id, client-secret, and partner-id | F5: Send POST Request using valid ACTIVE Client Owned Account wiht valid client-credentials | G5: Successful Status 200 OK Response Body: within 300 ms. accessToken, tokenType: Bearer, expiresIn, authId Token is bound to the exact account, | H5: 200 | J5: /auth/token/v1/generate | K5: application/json | L5: 1VjIqTcMCJ8tIv8bMpv9l9x01ebYQd88 | M5: cnfKqb1Q53rmlS8HifRZf7zvtGZOSlUQ | N5: 104234abc4 | O5: GsG5c0UhuhXUPj4XlY8G1kcjKioiFrqI | P5: application/json | Q5: 200061777902 | R5: send-funds.initiate
A6: 5 | B6: Y | C6: Y | D6: TS-EB-SB-PRODUCTS-0107 | E6: TS-EB-SB-PRODUCTS-0107: Account Authentication via Access Token v1.0_Generate Account Access Token API_Verify authentication token is usable in the next account-based API call within the expiry window | F6: Send POST Request using valid ACTIVE Client Owned Account with valid client-credentials using same authentication token | G6: Token generated is usable in the nexy account-based transactional API call within expiry (3600s) | H6: 200 | J6: /auth/token/v1/generate | K6: application/json | L6: 1VjIqTcMCJ8tIv8bMpv9l9x01ebYQd88 | M6: cnfKqb1Q53rmlS8HifRZf7zvtGZOSlUQ | N6: 104234abc4 | O6: GsG5c0UhuhXUPj4XlY8G1kcjKioiFrqI | P6: application/json | Q6: 200061777902 | R6: send-funds.initiate
A7: 6 | B7: Y | C7: Y | D7: TS-EB-SB-PRODUCTS-0108_1 | E7: TS-EB-SB-PRODUCTS-0108_1: Account Authentication via Access Token v1.0_Generate Account Access Token API_Verify POST request using Invalid client credentials | F7: Send POST Request using valid ACTIVE Client Owned Account with invalid client-credentials | G7: Failed/ Rejected Request 401 Unauthorized No token generated, authid, redirectUrl are returned Invalid credential attempts are rejected within 300 ms. | H7: 401 | I7: Invalid OAuth2 request parameters | J7: /auth/token/v1/generate | K7: application/json | L7: 1VjIqTcMCJ8tIv8bMpv9i9x01ebYQd32 | M7: cnfKqb1Q53rmlS8HifRZf7zvtGZOSlUQ | N7: 104234abc4 | O7: GsG5c0UhuhXUPj4XlY8G1kcjKioiFrqI | P7: application/json | Q7: 200061777902 | R7: send-funds.initiate
A8: 7 | B8: Y | C8: Y | D8: TS-EB-SB-PRODUCTS-0108_2 | E8: TS-EB-SB-PRODUCTS-0108_2: Account Authentication via Access Token v1.0_Generate Account Access Token API_Verify POST request using Invalid client credentials | F8: Send POST Request using valid ACTIVE Client Owned Account with invalid client-credentials | G8: Failed/ Rejected Request 401 Unauthorized No token generated, authid, redirectUrl are returned Invalid credential attempts are rejected within 300 ms. | H8: 401 | I8: Invalid OAuth2 request parameters | J8: /auth/token/v1/generate | K8: application/json | L8: 1VjIqTcMCJ8tIv8bMpv9l9x01ebYQd88 | M8: cnfKqj1Q53rmlS8HifRZf7zvtGZOSlUW | N8: 104234abc4 | O8: GsG5c0UhuhXUPj4XlY8G1kcjKioiFrqI | P8: application/json | Q8: 200061777902 | R8: send-funds.initiate
A9: 8 | B9: Y | C9: Y | D9: TS-EB-SB-PRODUCTS-0108_3 | E9: TS-EB-SB-PRODUCTS-0108_3: Account Authentication via Access Token v1.0_Generate Account Access Token API_Verify POST request using Invalid client credentials | F9: Send POST Request using valid ACTIVE Client Owned Account with invalid client-credentials | G9: Failed/ Rejected Request 401 Unauthorized No token generated, authid, redirectUrl are returned Invalid credential attempts are rejected within 300 ms. | H9: 401 | I9: Invalid OAuth2 request parameters | J9: /auth/token/v1/generate | K9: application/json | M9: cnfKqb1Q53rmlS8HifRZf7zvtGZOSlUQ | N9: 104234abc4 | O9: GsG5c0UhuhXUPj4XlY8G1kcjKioiFrqI | P9: application/json | Q9: 200061777902 | R9: send-funds.initiate
A10: 9 | B10: Y | C10: Y | D10: TS-EB-SB-PRODUCTS-0108_4 | E10: TS-EB-SB-PRODUCTS-0108_4: Account Authentication via Access Token v1.0_Generate Account Access Token API_Verify POST request using Invalid client credentials | F10: Send POST Request using valid ACTIVE Client Owned Account with invalid client-credentials | G10: Failed/ Rejected Request 401 Unauthorized No token generated, authid, redirectUrl are returned Invalid credential attempts are rejected within 300 ms. | H10: 401 | I10: Invalid OAuth2 request parameters | J10: /auth/token/v1/generate | K10: application/json | L10: 1VjIqTcMCJ8tIv8bMpv9l9x01ebYQd88 | N10: 104234abc4 | O10: GsG5c0UhuhXUPj4XlY8G1kcjKioiFrqI | P10: application/json | Q10: 200061777902 | R10: send-funds.initiate
A11: 10 | B11: Y | C11: Y | D11: TS-EB-SB-PRODUCTS-0109 | E11: TS-EB-SB-PRODUCTS-0109: Account Authentication via Access Token v1.0_Generate Account Access Token API_Verify if POST request with Invalid Client credentials is logged in API Portal Database | F11: Send POST Request using valid ACTIVE Client Owned Account with invalid client-credentials. Validate DB | G11: Security event is logged in the API Portal Database. | H11: 200 | J11: /auth/token/v1/generate | K11: application/json | L11: 1VjIqTcMCJ8tIv8bMpv9l9x01ebYQd88 | M11: cnfKqb1Q53rmlS8HifRZf7zvtGZOSlUQ | N11: 104234abc4 | O11: GsG5c0UhuhXUPj4XlY8G1kcjKioiFrqI | P11: application/json | Q11: 200061777902 | R11: send-funds.initiate
A12: 11 | B12: Y | C12: Y | D12: TS-EB-SB-PRODUCTS-0110_1 | E12: TS-EB-SB-PRODUCTS-0110_1: Account Authentication via Access Token v1.0_Generate Account Access Token API_Verify Send Request using Invalid Account Number | F12: Send POST Request using Invalid Client Owned Account with valid client-credentials. | G12: Failed / Rejected Request 400 Bad Request - error code invalid_account - clear errorDescription. No token or redirectUrl is issued. Core banking validation completes and rejects within 300 ms. | H12: 400 | I12: The accountNumber provided is invalid, not recognized, or not registered in Client Hub. | J12: /auth/token/v1/generate | K12: application/json | L12: 1VjIqTcMCJ8tIv8bMpv9l9x01ebYQd88 | M12: cnfKqb1Q53rmlS8HifRZf7zvtGZOSlUQ | N12: 104234abc4 | O12: GsG5c0UhuhXUPj4XlY8G1kcjKioiFrqI | P12: application/json | Q12: 200061977902 | R12: send-funds.initiate
A13: 12 | B13: Y | C13: Y | D13: TS-EB-SB-PRODUCTS-0110_2 | E13: TS-EB-SB-PRODUCTS-0110_2: Account Authentication via Access Token v1.0_Generate Account Access Token API_Verify Send Request using Invalid Account Number | F13: Send POST Request using Invalid Client Owned Account with valid client-credentials. | G13: Failed / Rejected Request 400 Bad Request - error code invalid_account - clear errorDescription. No token or redirectUrl is issued. Core banking validation completes and rejects within 300 ms. | H13: 400 | I13: The accountNumber provided is invalid, not recognized, or not registered in Client Hub. | J13: /auth/token/v1/generate | K13: application/json | L13: 1VjIqTcMCJ8tIv8bMpv9l9x01ebYQd88 | M13: cnfKqb1Q53rmlS8HifRZf7zvtGZOSlUQ | N13: 104234abc4 | O13: GsG5c0UhuhXUPj4XlY8G1kcjKioiFrqI | P13: application/json | R13: send-funds.initiate
A14: 13 | B14: Y | C14: Y | D14: TS-EB-SB-PRODUCTS-0111 | E14: TS-EB-SB-PRODUCTS-0111: Account Authentication via Access Token v1.0_Generate Account Access Token API_Verify Send Request using Inactive Account Number | F14: Send POST Request using INACTIVE Client Owned Account with valid client-credentials. | G14: Failed / Rejected Request 400 Bad Request - error code account_inactive - clear errorDescription. No token or redirectUrl is issued. Core banking validation completes and rejects within 300 ms. | H14: 400 | I14: The accountNumber provided is invalid, not recognized, or not registered in Client Hub. | J14: /auth/token/v1/generate | K14: application/json | L14: 1VjIqTcMCJ8tIv8bMpv9l9x01ebYQd88 | M14: cnfKqb1Q53rmlS8HifRZf7zvtGZOSlUQ | N14: 104234abc4 | O14: GsG5c0UhuhXUPj4XlY8G1kcjKioiFrqI | P14: application/json | Q14: 200098777902 | R14: send-funds.initiate
A15: 14 | B15: Y | C15: Y | D15: TS-EB-SB-PRODUCTS-0112 | E15: TS-EB-SB-PRODUCTS-0112: Account Authentication via Access Token v1.0_Generate Account Access Token API_Verify Send Request using Not Existing Account Number | F15: Send POST Request using NOT EXISTING Client Owned Account with valid client-credentials. | G15: Failed / Rejected Request 400 Bad Request - error code invalid_account - clear errorDescription. No token or redirectUrl is issued. Core banking validation completes and rejects within 300 ms. | H15: 400 | I15: The accountNumber provided is invalid, not recognized, or not registered in Client Hub. | J15: /auth/token/v1/generate | K15: application/json | L15: 1VjIqTcMCJ8tIv8bMpv9l9x01ebYQd88 | M15: cnfKqb1Q53rmlS8HifRZf7zvtGZOSlUQ | N15: 104234abc4 | O15: GsG5c0UhuhXUPj4XlY8G1kcjKioiFrqI | P15: application/json | Q15: 200081579910 | R15: send-funds.initiate
A16: 15 | B16: Y | C16: Y | D16: TS-EB-SB-PRODUCTS-0113 | E16: TS-EB-SB-PRODUCTS-0113: Account Authentication via Access Token v1.0_Generate Account Access Token API_Verify Send Request using Malformed Account Number | F16: Send POST Request using MALFORMED Client Owned Account with valid client-credentials. | G16: Failed / Rejected Request 400 Bad Request - error code invalid_account - clear errorDescription. No token or redirectUrl is issued. Core banking validation completes and rejects within 300 ms. | H16: 400 | I16: The accountNumber provided is invalid, not recognized, or not registered in Client Hub. | J16: /auth/token/v1/generate | K16: application/json | L16: 1VjIqTcMCJ8tIv8bMpv9l9x01ebYQd88 | M16: cnfKqb1Q53rmlS8HifRZf7zvtGZOSlUQ | N16: 104234abc4 | O16: GsG5c0UhuhXUPj4XlY8G1kcjKioiFrqI | P16: application/json | Q16: 20006IU77902 | R16: send-funds.initiate
A17: 16 | B17: Y | C17: Y | D17: TS-EB-SB-PRODUCTS-0114 | E17: TS-EB-SB-PRODUCTS-0114: Account Authentication via Access Token v1.0_Generate Account Access Token API_Validate POST Request using Valid values in Scope | F17: Send POST Request using Valid Scope value with valid client-credentials. | G17: Successful Status 200 OK - Valid scope indicated in Request Body Parameters contains [send-funds.initiate, receive-funds.generate, manage-funds.balance] (subscribed capabilities) | H17: 200 | J17: /auth/token/v1/generate | K17: application/json | L17: 1VjIqTcMCJ8tIv8bMpv9l9x01ebYQd88 | M17: cnfKqb1Q53rmlS8HifRZf7zvtGZOSlUQ | N17: 104234abc4 | O17: GsG5c0UhuhXUPj4XlY8G1kcjKioiFrqI | P17: application/json | Q17: 200061777902 | R17: send-funds.initiate
A18: 17 | B18: Y | C18: Y | D18: TS-EB-SB-PRODUCTS-0115 | E18: TS-EB-SB-PRODUCTS-0115: Account Authentication via Access Token v1.0_Generate Account Access Token API_Validate POST Request using Invalid values in Scope | F18: Send POST Request using Invalid Scope value with valid client-credentials. | G18: Failed / Rejected Request 400 Bad Request -invalid_scope with clear errorDescription. contains unknown or disallowed values [send-funds.initiate, , manage-funds.balance] (not subscribed capabilities) | H18: 400 | I18: The scope provided is invalid or not recognized | J18: /auth/token/v1/generate | K18: application/json | L18: 1VjIqTcMCJ8tIv8bMpv9l9x01ebYQd88 | M18: cnfKqb1Q53rmlS8HifRZf7zvtGZOSlUQ | N18: 104234abc4 | O18: GsG5c0UhuhXUPj4XlY8G1kcjKioiFrqI | P18: application/json | Q18: 200061777902 | R18: send-funds.invalid
A19: 18 | B19: N | C19: N | D19: TS-EB-SB-PRODUCTS-0001 | E19: TS-EB-SB-PRODUCTS-0001: Account Authentication via Access Token v1.0_Generate Account Access Token API_Verify Successful API call with Valid Account Access Token | F19: Send POST Request using Valid Account Access Token | G19: Successful Status 200 OK API request successfully processed Ownership and consent verified Token validation executes in p99 latency < 30 ms. | H19: 200 | J19: /auth/token/v1/generate | K19: application/json | L19: 1VjIqTcMCJ8tIv8bMpv9l9x01ebYQd88 | M19: cnfKqb1Q53rmlS8HifRZf7zvtGZOSlUQ | N19: 1042346954 | O19: GsG5c0UhuhXUPj4XlY8G1kcjKioiFrqI | P19: application/json | Q19: 200061777902 | R19: send-funds.initiate
A20: 19 | B20: N | C20: N | D20: TS-EB-SB-PRODUCTS-0002 | E20: TS-EB-SB-PRODUCTS-0002: Account Authentication via Access Token v1.0_Generate Account Access Token API_Verify API Call using Expired Account Access Token | F20: Send POST Request using Expired Account Access Token | G20: Failed/Rejected Status 401 Unauthorized - clear error message. -Token validation executes in p99 latency < 30 ms. | H20: 401 | J20: /auth/token/v1/generate | K20: application/json | L20: 1VjIqTcMCJ8tIv8bMpv9l9x01ebYQd88 | M20: cnfKqb1Q53rmlS8HifRZf7zvtGZOSlUQ | N20: 1042346954 | O20: GsG5c0UhuhXUPj4XlY8G1kcjKioiFrqI | P20: application/json | Q20: 200061777902 | R20: send-funds.initiate
A21: 20 | B21: N | C21: N | D21: TS-EB-SB-PRODUCTS-0003 | E21: TS-EB-SB-PRODUCTS-0003: Account Authentication via Access Token v1.0_Generate Account Access Token API_Verify API Call using Exceeding / FewerAccount Access Token | F21: Send POST Request using Exceeding/Fewer Account Access Token | G21: Failed/Rejected Status 401 Unauthorized - clear error message. - Token validation executes in p99 latency < 30 ms. | H21: 401 | J21: /auth/token/v1/generate | K21: application/json | L21: 1VjIqTcMCJ8tIv8bMpv9l9x01ebYQd88 | M21: cnfKqb1Q53rmlS8HifRZf7zvtGZOSlUQ | N21: 1042346954 | O21: GsG5c0UhuhXUPj4XlY8G1kcjKioiFrqI | P21: application/json | Q21: 200061777902 | R21: send-funds.initiate
A22: 21 | B22: N | C22: N | D22: TS-EB-SB-PRODUCTS-0004 | E22: TS-EB-SB-PRODUCTS-0004: Account Authentication via Access Token v1.0_Generate Account Access Token API_Verify API Call without Valid Account Access Token | F22: Send POST Request without VALID Account Access Token | G22: Failed/Rejected Status 401 Unauthorized - clear error message. - Token validation executes in p99 latency < 30 ms. | H22: 401 | J22: /auth/token/v1/generate | K22: application/json | L22: 1VjIqTcMCJ8tIv8bMpv9l9x01ebYQd88 | M22: cnfKqb1Q53rmlS8HifRZf7zvtGZOSlUQ | N22: 1042346954 | O22: GsG5c0UhuhXUPj4XlY8G1kcjKioiFrqI | P22: application/json | Q22: 200061777902 | R22: send-funds.initiate
A23: 22 | B23: N | C23: N | D23: TS-EB-SB-PRODUCTS-0005 | E23: TS-EB-SB-PRODUCTS-0005: Account Authentication via Access Token v1.0_Generate Account Access Token API_Verify API Call using malformed Account Access Token | F23: Send POST Request using Malformed Account Access Token | G23: Failed/Rejected Status 401 Unauthorized - clear error message. - Token validation executes in p99 latency < 30 ms. | H23: 401 | J23: /auth/token/v1/generate | K23: application/json | L23: 1VjIqTcMCJ8tIv8bMpv9l9x01ebYQd88 | M23: cnfKqb1Q53rmlS8HifRZf7zvtGZOSlUQ | N23: 1042346954 | O23: GsG5c0UhuhXUPj4XlY8G1kcjKioiFrqI | P23: application/json | Q23: 200061777902 | R23: send-funds.initiate
A24: 23 | B24: N | C24: N | D24: TS-EB-SB-PRODUCTS-0006 | E24: TS-EB-SB-PRODUCTS-0006: Account Authentication via Access Token v1.0_Generate Account Access Token API_Verify API Call using Token used with different client credentials | F24: Send POST Request using Valid Account Access Token but different client credentials | G24: Failed/Rejected Status 401 Unauthorized - clear error message. Error: Token does not match client credentials - Token validation executes in p99 latency < 30 ms. | H24: 401 | J24: /auth/token/v1/generate | K24: application/json | L24: 1VjIqTcMCJ8tIv8bMpv9l9x01ebYQd89 | M24: cnfKqb1Q53rmlS8HifRZf7zvtGZOSlUI | N24: 1042346954 | O24: GsG5c0UhuhXUPj4XlY8G1kcjKioiFrqI | P24: application/json | Q24: 200061777902 | R24: send-funds.initiate
A25: 24 | B25: N | C25: N | D25: TS-EB-SB-PRODUCTS-0007 | E25: TS-EB-SB-PRODUCTS-0007: Account Authentication via Access Token v1.0_Generate Account Access Token API_Token used with different Partner-ID | F25: Send POST Request using Valid Account Access Token but different Partner-ID | G25: Failed/Rejected Status 401 Unauthorized - clear error message. Enforcement failure due to Partner-ID mismatch - Token validation executes in p99 latency < 30 ms. | H25: 401 | J25: /auth/token/v1/generate | K25: application/json | L25: 1VjIqTcMCJ8tIv8bMpv9l9x01ebYQd88 | M25: cnfKqb1Q53rmlS8HifRZf7zvtGZOSlUQ | N25: 1042346954 | O25: GsG5c0UhuhXUPj4XlY8G1kcjKioiFrqI | P25: application/json | Q25: 200061777902 | R25: send-funds.initiate
A26: 25 | B26: N | C26: N | D26: TS-EB-SB-PRODUCTS-0104 | E26: TS-EB-SB-PRODUCTS-0104: Account Authentication via Access Token v1.0_Generate Account Access Token API_Verify send request from an IP not whitelisted for the application. | F26: Send POST Request using Not Whitelisted IP | G26: Failed Request 403 (Forbidden) No token generated | H26: 403 | J26: /auth/token/v1/generate | K26: application/json | L26: 1VjIqTcMCJ8tIv8bMpv9l9x01ebYQd88 | M26: cnfKqb1Q53rmlS8HifRZf7zvtGZOSlUQ | N26: 1042346954 | O26: GsG5c0UhuhXUPj4XlY8G1kcjKioiFrqI | P26: application/json | Q26: 200061777902 | R26: send-funds.initiate
A27: 26 | B27: N | C27: N | D27: TS-EB-SB-PRODUCTS-0106 | E27: TS-EB-SB-PRODUCTS-0106: Account Authentication via Access Token v1.0_Generate Account Access Token API_Verify status in Database of successful Client Owned Account Authentication | F27: Send POST Request using valid ACTIVE Client Owned Account with valid client-credentials. Validate DB | G27: Status in DB is COMPLETED | H27: 200 | J27: /auth/token/v1/generate | K27: application/json | L27: 1VjIqTcMCJ8tIv8bMpv9l9x01ebYQd88 | M27: cnfKqb1Q53rmlS8HifRZf7zvtGZOSlUQ | N27: 1042346954 | O27: GsG5c0UhuhXUPj4XlY8G1kcjKioiFrqI | P27: application/json | Q27: 200061777902 | R27: send-funds.initiate

Sheet SBBankList
A1: # | B1: ExecutionFlag | C1: CORE | D1: TC_ID | E1: Description | F1: StepAction | G1: ExpectedResult | H1: ExpectedStatus | I1: ExpectedResponseDescription | J1: IN_EndPoint | K1: IN_ParamChannel | L1: IN_HeadPartnerID | M1: IN_HeadAPIKey | N1: IN_HeadCorrelationID | O1: OUT_RequestHeaders | P1: OUT_RequestBody | Q1: OUT_ResponseHeaders | R1: OUT_ResponseBody
A2: 1 | B2: =C2 -> Y | C2: Y | D2: TS-EB-SB-PRODUCTS-0088 | E2: TS-EB-SB-PRODUCTS-0088: Send Funds via Local Fund Transfer v1.0 _Get Supported Banks and Wallets API_Verify successful GET request of Get Supported Banks and Wallets API | F2: Send GET Request of Get Supported Banks and Wallets API | G2: Status HTTP 200 OK Response Body: Complete and accurate list of Supported Receiving Financial Institutions (banks and e‑wallets) available for disbursements under the Send Funds via Local Fund Transfer product. { "data": [ { "bankName": "Alipay / Lazada Wallet", "pesonet": { "status": false, "brstn": "" }, "instapay": { "status": true, "brstn": "7021" }, "enable": true }, { "bankName": "Zybi Tech Inc. / JuanCash", "pesonet": { "status": true, "brstn": "18080012" }, "instapay": { "status": true, "brstn": "7012" }, "enable": true } ] } Institutioin Entries: Institution name, enablement flag, and supported settlement rails with corresponding Bank Identification Codes (BICs) where applicable. | H2: 200 | J2: /send-funds/localft/v1/list/institutions | L2: 104234abc4 | M2: GsG5c0UhuhXUPj4XlY8G1kcjKioiFrqI | N2: application/json
A3: 2 | B3: =C3 -> Y | C3: Y | D3: TS-EB-SB-PRODUCTS-0089 | E3: TS-EB-SB-PRODUCTS-0089: Send Funds via Local Fund Transfer v1.0 _Get Supported Banks and Wallets API_Verify when Optional field "Transfer Network" (channel) is not provided to filter Financial Institutions | F3: Send GET Request of Get Supported Banks and Wallets API when channel is empty | G3: When list channel parameter is not provided, the API returns institutions across all supported transfer networks channel: Intrabank, Instapay, PESONet) Sample Response Body: "data": [ { "bankName": "Alipay / Lazada Wallet", "pesonet": { "status": false, "brstn": "" }, "instapay": { "status": true, "brstn": "7021" }, "enable": true }, { "bankName": "Zybi Tech Inc. / JuanCash", "pesonet": { "status": true, "brstn": "18080012" }, "instapay": { "status": true, "brstn": "7012" }, "enable": true } ] } | H3: 200 | J3: /send-funds/localft/v1/list/institutions | L3: 104234abc4 | M3: GsG5c0UhuhXUPj4XlY8G1kcjKioiFrqI | N3: application/json
A4: 3 | B4: =C4 -> Y | C4: Y | D4: TS-EB-SB-PRODUCTS-0090 | E4: TS-EB-SB-PRODUCTS-0090: Send Funds via Local Fund Transfer v1.0 _Get Supported Banks and Wallets API_Verify when the “Transfer Network” (channel) is set to Instapay, the API returns only Financial Institutions that support Instapay transfers | F4: Send GET Request of Get Supported Banks and Wallets API when channel = InstaPay | G4: When list channel parameter is provided, the API returns only Financial institutions that support the Intrabank Transfer Network channel: Instapay "data": [ { "bankName": "Alipay / Lazada Wallet", "pesonet": { "status": false, "brstn": "" }, "instapay": { "status": true, "brstn": "7021" }, "enable": true }, { "bankName": "Zybi Tech Inc. / JuanCash", "pesonet": { "status": true, "brstn": "18080012" }, "instapay": { "status": true, "brstn": "7012" }, "enable": true } ] } | H4: 200 | J4: ="/send-funds/localft/v1/list/institutions?channel="&K4 -> /send-funds/localft/v1/list/institutions?channel=Instapay | K4: Instapay | L4: 104234abc4 | M4: GsG5c0UhuhXUPj4XlY8G1kcjKioiFrqI | N4: application/json
A5: 4 | B5: =C5 -> Y | C5: Y | D5: TS-EB-SB-PRODUCTS-0091 | E5: TS-EB-SB-PRODUCTS-0091: Send Funds via Local Fund Transfer v1.0 _Get Supported Banks and Wallets API_Verify when the “Transfer Network” (channel) is set to PESONet, the API returns only Financial Institutions that support PESONet transfers | F5: Send GET Request of Get Supported Banks and Wallets API when channel = PESONet | G5: When list channel parameter is provided, the API returns only Financial institutions that support the PESONet Transfer Network channel: PESONet "data": [ { "bankName": "Zybi Tech Inc. / JuanCash", "pesonet": { "status": true, "brstn": "18080012" }, "instapay": { "status": true, "brstn": "7012" }, "enable": true } ] } | H5: 200 | J5: ="/send-funds/localft/v1/list/institutions?channel="&K5 -> /send-funds/localft/v1/list/institutions?channel=PESONET | K5: PESONET | L5: 104234abc4 | M5: GsG5c0UhuhXUPj4XlY8G1kcjKioiFrqI | N5: application/json
A6: 5 | B6: =C6 -> Y | C6: Y | D6: TS-EB-SB-PRODUCTS-0092 | E6: TS-EB-SB-PRODUCTS-0092: Send Funds via Local Fund Transfer v1.0 _Get Supported Banks and Wallets API_Verify when the “Transfer Network” (channel) is set to specific and API returns only Financial Institutions that support both transfers | F6: Send GET Request of Get Supported Banks and Wallets API when channel is set to specific and API returns only Financial Institutions that support both transfers | G6: The API should display both enable for both transfers (Ex: pesonet and instapay) Sample Response Body: "data": [ { "bankName": "Zybi Tech Inc. / JuanCash", "pesonet": { "status": true, "brstn": "18080012" }, "instapay": { "status": true, "brstn": "7012" }, "enable": true } ] } | H6: 200 | J6: /send-funds/localft/v1/list/institutions | L6: 104234abc4 | M6: GsG5c0UhuhXUPj4XlY8G1kcjKioiFrqI | N6: application/json
A7: 6 | B7: =C7 -> Y | C7: Y | D7: TS-EB-SB-PRODUCTS-0093 | E7: TS-EB-SB-PRODUCTS-0093: Send Funds via Local Fund Transfer v1.0 _Get Supported Banks and Wallets API_Verify failed GET request when an unsupported channel value is provided | F7: Send GET Request of Get Supported Banks and Wallets API when channel is set to unsupported channel | G7: HTTP 400 Bad Request Clear error message indicating invalid or unsupported channel value (e.g., channel=ABC) (responseDescription) | H7: 400 | I7: Invalid Channel. The Channel provided is invalid. | J7: ="/send-funds/localft/v1/list/institutions?channel="&K7 -> /send-funds/localft/v1/list/institutions?channel=Test | K7: Test | L7: 104234abc4 | M7: GsG5c0UhuhXUPj4XlY8G1kcjKioiFrqI | N7: application/json
A8: 7 | B8: =C8 -> Y | C8: Y | D8: TS-EB-SB-PRODUCTS-0094 | E8: TS-EB-SB-PRODUCTS-0094: Send Funds via Local Fund Transfer v1.0_Get Supported Banks and Wallets API_Verify failed GET request when api-key is null/missing | F8: Send GET Request of Get Supported Banks and Wallets API but api k-key is not provided/missing | G8: HTTP 401 Unauthorized Clear authentication error message (responseDescription) | H8: 401 | I8: Invalid API key. The API key provided was not found. | J8: /send-funds/localft/v1/list/institutions | L8: 104234abc4 | N8: application/json
A9: 8 | B9: =C9 -> Y | C9: Y | D9: TS-EB-SB-PRODUCTS-0095 | E9: TS-EB-SB-PRODUCTS-0095: Send Funds via Local Fund Transfer v1.0_Get Supported Banks and Wallets API_Verify failed GET request when partnerID is null/missing | F9: Send GET Request of Get Supported Banks and Wallets API but partnerId is not provided/missing | G9: HTTP 401 Unauthorized Clear authentication error message (responseDescription) | H9: 401 | I9: The partner ID provided is invalid, not recognized, or not registered in Client Hub. | J9: /send-funds/localft/v1/list/institutions | M9: GsG5c0UhuhXUPj4XlY8G1kcjKioiFrqI | N9: application/json
A10: 9 | B10: =C10 -> Y | C10: Y | D10: TS-EB-SB-PRODUCTS-0096 | E10: TS-EB-SB-PRODUCTS-0096: Send Funds via Local Fund Transfer v1.0_Get Supported Banks and Wallets API_Verify failed GET request when api-key is incorrect | F10: Send GET Request of Get Supported Banks and Wallets API but api-key is incorrect or not existing | G10: HTTP 401 Unauthorized Clear authentication error message (responseDescription) | H10: 401 | I10: Invalid API key. The API key provided was not found. | J10: /send-funds/localft/v1/list/institutions | L10: 104234abc4 | M10: GsG5c0UhuhXUPj4XliKG1kcjKioiT5qI | N10: application/json
A11: 10 | B11: =C11 -> Y | C11: Y | D11: TS-EB-SB-PRODUCTS-0097 | E11: TS-EB-SB-PRODUCTS-0097: Send Funds via Local Fund Transfer v1.0_Get Supported Banks and Wallets API_Verify failed GET request when partnerid is incorrect | F11: Send GET Request of Get Supported Banks and Wallets API but partnerId is incorrect or not existing | G11: HTTP 401 Unauthorized Clear authentication error message (responseDescription) | H11: 401 | I11: The partner ID provided is invalid, not recognized, or not registered in Client Hub. | J11: /send-funds/localft/v1/list/institutions | L11: 1042346054 | M11: GsG5c0UhuhXUPj4XlY8G1kcjKioiFrqI | N11: application/json
A12: 12 | B12: =C12 -> Y | C12: Y | D12: TS-EB-SB-PRODUCTS-0099 | E12: TS-EB-SB-PRODUCTS-0099: Send Funds via Local Fund Transfer v1.0_Get Supported Banks and Wallets API_Verify disabled institutions are clearly indicated and not misrepresented as available | F12: Send GET Request of Get Supported Banks and Wallets API | G12: Disabled institutions are marked correctly They are not shown as valid disbursement destinations | H12: 200 | J12: /send-funds/localft/v1/list/institutions | L12: 104234abc4 | M12: GsG5c0UhuhXUPj4XlY8G1kcjKioiFrqI | N12: application/json
A13: 13 | B13: =C13 -> Y | C13: Y | D13: TS-EB-SB-PRODUCTS-0100 | E13: TS-EB-SB-PRODUCTS-0100: Send Funds via Local Fund Transfer v1.0_Get Supported Banks and Wallets API_Verify response processsing time of successful GET request of Get Supported Banks and Wallets API | F13: Send Successful GET Request of Get Supported Banks and Wallets API. Check processing time. | G13: 200 OK response within ≤ 1 second (1000 ms) for 95% of calls. | H13: 200 | J13: /send-funds/localft/v1/list/institutions | L13: 104234abc4 | M13: GsG5c0UhuhXUPj4XlY8G1kcjKioiFrqI | N13: application/json
A14: 14 | B14: =C14 -> Y | C14: Y | D14: TS-EB-SB-PRODUCTS-0101_1 | E14: TS-EB-SB-PRODUCTS-0101_1: Send Funds via Local Fund Transfer v1.0_Get Supported Banks and Wallets API_Verify response processsing time of failed GET request of Get Supported Banks and Wallets API | F14: Send GET Request of Get Supported Banks and Wallets API when channel is set to unsupported channel | G14: 400 status with descriptive error message within ≤ 1 second | H14: 400 | I14: Invalid Channel. The Channel provided is invalid. | J14: ="/send-funds/localft/v1/list/institutions?channel="&K14 -> /send-funds/localft/v1/list/institutions?channel=Test | K14: Test | L14: 104234abc4 | M14: GsG5c0UhuhXUPj4XlY8G1kcjKioiFrqI | N14: application/json
A15: 15 | B15: =C15 -> Y | C15: Y | D15: TS-EB-SB-PRODUCTS-0101_2 | E15: TS-EB-SB-PRODUCTS-0101_2: Send Funds via Local Fund Transfer v1.0_Get Supported Banks and Wallets API_Verify response processsing time of failed GET request of Get Supported Banks and Wallets API | F15: Send GET Request of Get Supported Banks and Wallets API but api k-key is not provided/missing | G15: 401 status with descriptive error message within ≤ 1 second | H15: 401 | I15: Invalid API key. The API key provided was not found. | J15: /send-funds/localft/v1/list/institutions | L15: 104234abc4 | N15: application/json
A16: 16 | B16: =C16 -> Y | C16: Y | D16: TS-EB-SB-PRODUCTS-0101_3 | E16: TS-EB-SB-PRODUCTS-0101_3: Send Funds via Local Fund Transfer v1.0_Get Supported Banks and Wallets API_Verify response processsing time of failed GET request of Get Supported Banks and Wallets API | F16: Send GET Request of Get Supported Banks and Wallets API but partnerId is not provided/missing | G16: 401 status with descriptive error message within ≤ 1 second | H16: 401 | I16: The partner ID provided is invalid, not recognized, or not registered in Client Hub. | J16: /send-funds/localft/v1/list/institutions | M16: GsG5c0UhuhXUPj4XlY8G1kcjKioiFrqI | N16: application/json
A17: 17 | B17: =C17 -> Y | C17: Y | D17: TS-EB-SB-PRODUCTS-0101_4 | E17: TS-EB-SB-PRODUCTS-0101_4: Send Funds via Local Fund Transfer v1.0_Get Supported Banks and Wallets API_Verify response processsing time of failed GET request of Get Supported Banks and Wallets API | F17: Send GET Request of Get Supported Banks and Wallets API but api-key is incorrect or not existing | G17: 401 status with descriptive error message within ≤ 1 second | H17: 401 | I17: Invalid API key. The API key provided was not found. | J17: /send-funds/localft/v1/list/institutions | L17: 104234abc4 | M17: GsG5c0UhuhXUPj4XliKG1kcjKioiT5qI | N17: application/json
A18: 18 | B18: =C18 -> Y | C18: Y | D18: TS-EB-SB-PRODUCTS-0101_5 | E18: TS-EB-SB-PRODUCTS-0101_5: Send Funds via Local Fund Transfer v1.0_Get Supported Banks and Wallets API_Verify response processsing time of failed GET request of Get Supported Banks and Wallets API | F18: Send GET Request of Get Supported Banks and Wallets API but partnerId is incorrect or not existing | G18: 401 status with descriptive error message within ≤ 1 second | H18: 401 | I18: The partner ID provided is invalid, not recognized, or not registered in Client Hub. | J18: /send-funds/localft/v1/list/institutions | L18: 1042346054 | M18: GsG5c0UhuhXUPj4XlY8G1kcjKioiFrqI | N18: application/json
A19: 19 | B19: =C19 -> N | C19: N | D19: TS-EB-SB-PRODUCTS-0098 | E19: TS-EB-SB-PRODUCTS-0098: Send Funds via Local Fund Transfer v1.0_Get Supported Banks and Wallets API_Verify failed GET request when application is not subscribed to the API product | F19: Send GET Request of Get Supported Banks and Wallets API but application is not subscribed to API Product | G19: HTTP 403 Forbidden Clear subscription or authorization error message (responseDescription) | H19: 403 | J19: /send-funds/localft/v1/list/institutions | L19: 1042346954 | M19: GsG5c0UhuhXUPj4XlY8G1kcjKioiFrqI | N19: application/json

Sheet SBCheckStatus
A1: # | B1: ExecutionFlag | C1: CORE | D1: TC_ID | E1: Description | F1: StepAction | G1: ExpectedResult | H1: ExpectedStatus | I1: ExpectedResponseDescription | J1: IN_EndPoint | K1: IN_ParamAPITxnID | L1: IN_ParamAPITxnRef | M1: IN_ParamIdempotencyKey | N1: IN_HeadPartnerID | O1: IN_HeadAPIKey | P1: IN_HeadContentType | Q1: OUT_RequestHeaders | R1: OUT_RequestBody | S1: OUT_ResponseHeaders | T1: OUT_ResponseBody
A2: 1 | B2: =C2 -> Y | C2: Y | D2: TS-EB-PRODUCTS-0205 | E2: TS-EB-PRODUCTS-0205: Send Funds via Local Fund Transfer v1.0 _Check Local Funds Transfer Details and Status API_Verify failed GET request of Local Fund Transfer (Transaction Details) upon providing Exceeding to 23 digits of API-Txn-Ref via Intrabank | F2: Send GET Request of Check Local Fund Transfer Details and Status API using exceeding to 23-digits Transaction ID (API-Txn-Ref) via Intrabank | G2: The API returns an error message as the transaction details of provided transaction reference is persistent 23-digit transaction reference Status: 400 Bad RequeststatusDescription | H2: 400 | I2: Query parameter apiTxnRef must be a 23-character alphanumeric string. | J2: /send-funds/localft/v1/status | L2: 111111854000000000000628 | N2: 104234abc4 | O2: GsG5c0UhuhXUPj4XlY8G1kcjKioiFrqI | P2: application/json
A3: 2 | B3: =C3 -> Y | C3: Y | D3: TS-EB-PRODUCTS-0206 | E3: TS-EB-PRODUCTS-0206: Send Funds via Local Fund Transfer v1.0 _Check Local Funds Transfer Details and Status API_Verify failed GET request of Local Fund Transfer (Transaction Details) upon providing fewer than 23 digits of API-Txn-Ref via Intrabank | F3: Send GET Request of Check Local Fund Transfer Details and Status API using fewer than 23-digits Transaction ID (API-Txn-Ref) via Intrabank | G3: The API returns an error message as the transaction details of provided transaction reference is persistent 23-digit transaction reference Status: 400 Bad RequeststatusDescription | H3: 400 | I3: Query parameter apiTxnRef must be a 23-character alphanumeric string. | J3: /send-funds/localft/v1/status | L3: 1111118540000000000006 | N3: 104234abc4 | O3: GsG5c0UhuhXUPj4XlY8G1kcjKioiFrqI | P3: application/json
A4: 3 | B4: =C4 -> Y | C4: Y | D4: TS-EB-PRODUCTS-0286 | E4: TS-EB-PRODUCTS-0286: Send Funds via Local Fund Transfer v1.0 _Check Local Funds Transfer Details and Status API_Verify failed GET request of Local Fund Transfer (Transaction Details) upon providing Exceeding to 23 digits of API-Txn-Ref via InstaPay | F4: Send GET Request of Check Local Fund Transfer Details and Status API using exceeding to 23-digits Transaction Ref (API-Txn-Ref) via InstaPay | G4: The API returns an error message as the transaction details of provided transaction reference is persistent 23-digit transaction reference Status: 400 Bad Request statusDescription | H4: 400 | I4: Query parameter apiTxnRef must be a 23-character alphanumeric string. | J4: /send-funds/localft/v1/status | L4: 111111773000000000000625 | N4: 104234abc4 | O4: GsG5c0UhuhXUPj4XlY8G1kcjKioiFrqI | P4: application/json
A5: 4 | B5: =C5 -> Y | C5: Y | D5: TS-EB-PRODUCTS-0287 | E5: TS-EB-PRODUCTS-0287: Send Funds via Local Fund Transfer v1.0 _Check Local Funds Transfer Details and Status API_Verify failed GET request of Local Fund Transfer (Transaction Details) upon providing Exceeding to 23 digits of API-Txn-Ref via PESONet | F5: Send GET Request of Check Local Fund Transfer Details and Status API using exceeding to 23-digits Transaction ID (API-Txn-Ref) via PESONet | G5: The API returns an error message as the transaction details of provided transaction reference is persistent 23-digit transaction reference Status: 400 Bad Request statusDescription | H5: 400 | I5: Query parameter apiTxnRef must be a 23-character alphanumeric string. | J5: /send-funds/localft/v1/status | L5: 1111117730000000000006 | N5: 104234abc4 | O5: GsG5c0UhuhXUPj4XlY8G1kcjKioiFrqI | P5: application/json
A6: 5 | B6: =C6 -> Y | C6: Y | D6: TS-EB-PRODUCTS-0288 | E6: TS-EB-PRODUCTS-0288: Send Funds via Local Fund Transfer v1.0 _Check Local Funds Transfer Details and Status API_Verify failed GET request of Local Fund Transfer (Transaction Details) upon providing fewer than 23 digits of API-Txn-Ref via InstaPay | F6: Send GET Request of Check Local Fund Transfer Details and Status API using fewer than 23-digits Transaction Ref (API-Txn-Ref) via InstaPay | G6: The API returns an error message as the transaction details of provided transaction reference is persistent 23-digit transaction reference Status: 400 Bad Request statusDescription | H6: 400 | I6: Query parameter apiTxnRef must be a 23-character alphanumeric string. | J6: /send-funds/localft/v1/status | L6: 1111117750000000000006289 | N6: 104234abc4 | O6: GsG5c0UhuhXUPj4XlY8G1kcjKioiFrqI | P6: application/json
A7: 6 | B7: =C7 -> Y | C7: Y | D7: TS-EB-PRODUCTS-0289 | E7: TS-EB-PRODUCTS-0289: Send Funds via Local Fund Transfer v1.0 _Check Local Funds Transfer Details and Status API_Verify failed GET request of Local Fund Transfer (Transaction Details) upon providing fewer than 23 digits of API-Txn-Ref via PESONet | F7: Send GET Request of Check Local Fund Transfer Details and Status API using fewer than 23-digits Transaction Ref (API-Txn-Ref) via PESONet | G7: The API returns an error message as the transaction details of provided transaction reference is persistent 23-digit transaction reference Status: 400 Bad Request statusDescription | H7: 400 | I7: Query parameter apiTxnRef must be a 23-character alphanumeric string. | J7: /send-funds/localft/v1/status | L7: 111111775000000000000 | N7: 104234abc4 | O7: GsG5c0UhuhXUPj4XlY8G1kcjKioiFrqI | P7: application/json
A8: 7 | B8: =C8 -> Y | C8: Y | D8: TS-EB-PRODUCTS-0187 | E8: TS-EB-PRODUCTS-0187: Send Funds via Local Fund Transfer v1.0 _Check Local Funds Transfer Details and Status API_Verify successful GET request of Check Local Fund Transfer Details and Status API for Intrabank | F8: Send GET Request of Check Local Fund Transfer Details and Status API | G8: Status HTTP 200 OK [within ≤ 1 second (1000 ms)] Response Body: apiTxnIdapiTxnRef ewbCoreReferencestatus = always "RECEIVED"responseCoderesponseDescriptioncreatedTimestampupdatedTimestamp | H8: 200 | J8: /send-funds/localft/v1/status | L8: 11111185400000000000062 | N8: 104234abc4 | O8: GsG5c0UhuhXUPj4XlY8G1kcjKioiFrqI | P8: application/json
A9: 8 | B9: =C9 -> Y | C9: Y | D9: TS-EB-PRODUCTS-0192 | E9: TS-EB-PRODUCTS-0192: Send Funds via Local Fund Transfer v1.0 _Check Local Funds Transfer Details and Status API_VVerify failed GET request of Check Local Fund Transfer Details and Status API due to invalid partner-id parameters via Intrabank transfer | F9: Send GET Request of Check Local Fund Transfer Details and Status API using invalid partner-id parameter for Intrabank Transfer | G9: responseCode (Status HTTP 401 Unauthorized[within ≤ 1 second (1000 ms)]}and responseDescription - must be included in API Portal Database | H9: 401 | I9: The partner ID provided is invalid, not recognized, or not registered in Client Hub. | J9: /send-funds/localft/v1/status | L9: 11111185400000000000062 | N9: 1042346950 | O9: GsG5c0UhuhXUPj4XlY8G1kcjKioiFrqI | P9: application/json
A10: 9 | B10: =C10 -> Y | C10: Y | D10: TS-EB-PRODUCTS-0195_2 | E10: TS-EB-PRODUCTS-0195_2: Send Funds via Local Fund Transfer v1.0 _Check Local Funds Transfer Details and Status API_Verify Check Local Fund Transfer Details and Status API when transaction is not yet in its final status (COMPLETED/FAILED) | F10: Send GET Request of Check Local Fund Transfer Details and Status API when created transaction is not yet in final status (COMPLETE/FAILED) | G10: API should trigger a status check with the core/downstream systems when invoked | H10: 200 | J10: /send-funds/localft/v1/status | K10: 223 | N10: 104234abc4 | O10: GsG5c0UhuhXUPj4XlY8G1kcjKioiFrqI | P10: application/json
A11: 10 | B11: =C11 -> Y | C11: Y | D11: TS-EB-PRODUCTS-0195_3 | E11: TS-EB-PRODUCTS-0195_3: Send Funds via Local Fund Transfer v1.0 _Check Local Funds Transfer Details and Status API_Verify Check Local Fund Transfer Details and Status API when transaction is not yet in its final status (COMPLETED/FAILED) | F11: Send GET Request of Check Local Fund Transfer Details and Status API when created transaction is not yet in final status (COMPLETE/FAILED) | G11: API should trigger a status check with the core/downstream systems when invoked | H11: 200 | J11: /send-funds/localft/v1/status | K11: 113 | N11: 104234abc4 | O11: GsG5c0UhuhXUPj4XlY8G1kcjKioiFrqI | P11: application/json
A12: 11 | B12: =C12 -> Y | C12: Y | D12: TS-EB-PRODUCTS-0196 | E12: TS-EB-PRODUCTS-0196: Send Funds via Local Fund Transfer v1.0 _Check Local Funds Transfer Details and Status API_Verify successful retrieval of local funds transfer details using a valid idempotency key Intrabank | F12: Send GET Request of Check Local Fund Transfer Details and Status API using valid idempotency-key via Intrabank | G12: API returns 200 OK statusFull transaction details and latest status are returned Response Body: apiTxnIdapiTxnRef ewbCoreReferencestatus = always "RECEIVED"responseCoderesponseDescriptioncreatedTimestampupdatedTimestamp | H12: 200 | J12: /send-funds/localft/v1/status | M12: 3300000000000 | N12: 104234abc4 | O12: GsG5c0UhuhXUPj4XlY8G1kcjKioiFrqI | P12: application/json
A13: 12 | B13: =C13 -> Y | C13: Y | D13: TS-EB-PRODUCTS-0197 | E13: TS-EB-PRODUCTS-0197: Send Funds via Local Fund Transfer v1.0 _Check Local Funds Transfer Details and Status API_Verify failed retrieval of local funds transfer details using a non‑existing idempotency key via Intrabank | F13: Send GET Request of Check Local Fund Transfer Details and Status API using not existing idempotency-key via Intabank | G13: Error response is returned 404 Not Found / 400 Bad RequestTransaction details are not found responseCoderesponseDescription | H13: 400 | I13: Transaction not found for the provided idempotencyKey | J13: /send-funds/localft/v1/status | M13: 5500000000000 | N13: 104234abc4 | O13: GsG5c0UhuhXUPj4XlY8G1kcjKioiFrqI | P13: application/json
A14: 13 | B14: =C14 -> Y | C14: Y | D14: TS-EB-PRODUCTS-0198 | E14: TS-EB-PRODUCTS-0198: Send Funds via Local Fund Transfer v1.0 _Check Local Funds Transfer Details and Status API_Verify failed retrieval of local funds transfer details using an invalid idempotency key format via Intrabank | F14: Send GET Request of Check Local Fund Transfer Details and Status API using invalid idempotency-key format via Intrabank | G14: Error response is returned 404 Not Found / 400 Bad RequestTransaction details are not found responseCoderesponseDescription | H14: 400 | I14: Transaction not found for the provided idempotencyKey | J14: /send-funds/localft/v1/status | M14: 5500000000000 | N14: 104234abc4 | O14: GsG5c0UhuhXUPj4XlY8G1kcjKioiFrqI | P14: application/json
A15: 14 | B15: =C15 -> Y | C15: Y | D15: TS-EB-PRODUCTS-0200 | E15: TS-EB-PRODUCTS-0200: Send Funds via Local Fund Transfer v1.0 _Check Local Funds Transfer Details and Status API_Verify successful GET request of Local Fund Transfer (Transaction Details) upon providing Valid API-Txn-ID via Intrabank | F15: Send GET Request of Check Local Fund Transfer Details and Status API using Valid Transaction ID (API-Txn-ID) via Intrabank | G15: Status HTTP 200 OK [within ≤ 1 second (1000 ms)] Response Body: apiTxnIdapiTxnRef ewbCoreReferencestatus = always "RECEIVED"responseCoderesponseDescriptioncreatedTimestampupdatedTimestamp | H15: 200 | J15: /send-funds/localft/v1/status | K15: 330 | N15: 104234abc4 | O15: GsG5c0UhuhXUPj4XlY8G1kcjKioiFrqI | P15: application/json
A16: 15 | B16: =C16 -> Y | C16: Y | D16: TS-EB-PRODUCTS-0201 | E16: TS-EB-PRODUCTS-0201: Send Funds via Local Fund Transfer v1.0 _Check Local Funds Transfer Details and Status API_Verify failed GET request of Local Fund Transfer (Transaction Details) upon providing Invalid format API-Txn-ID via Intrabank | F16: Send GET Request of Check Local Fund Transfer Details and Status API using Invalid Format Transaction ID (API-Txn-ID) via Intrabank | G16: The API returns an error message: Status 400 Bad Request / 404 Not FoundstatusDescription | H16: 400 | I16: Transaction not found for the provided apiTxnId | J16: /send-funds/localft/v1/status | K16: 550 | N16: 104234abc4 | O16: GsG5c0UhuhXUPj4XlY8G1kcjKioiFrqI | P16: application/json
A17: 16 | B17: =C17 -> Y | C17: Y | D17: TS-EB-PRODUCTS-0202 | E17: TS-EB-PRODUCTS-0202: Send Funds via Local Fund Transfer v1.0 _Check Local Funds Transfer Details and Status API_Verify failed GET request of Local Fund Transfer (Transaction Details) upon providing Not Existing API-Txn-ID via Intrabank | F17: Send GET Request of Check Local Fund Transfer Details and Status API using Not Existing Transaction ID (API-Txn-ID) via Intrabank | G17: The API returns an error message: Status 400 Bad RequeststatusDescription | H17: 400 | I17: Transaction not found for the provided apiTxnId | J17: /send-funds/localft/v1/status | K17: 550 | N17: 104234abc4 | O17: GsG5c0UhuhXUPj4XlY8G1kcjKioiFrqI | P17: application/json
A18: 17 | B18: =C18 -> Y | C18: Y | D18: TS-EB-PRODUCTS-0203 | E18: TS-EB-PRODUCTS-0203: Send Funds via Local Fund Transfer v1.0 _Check Local Funds Transfer Details and Status API_Verify successful GET request of Local Fund Transfer (Transaction Details) upon providing valid API-Txn-Ref via Intrabank | F18: Send GET Request of Check Local Fund Transfer Details and Status API using Valid Transaction ID (API-Txn-Ref) | G18: Status HTTP 200 OK [within ≤ 1 second (1000 ms)] Response Body: apiTxnIdapiTxnRef ewbCoreReferencestatus = always "RECEIVED"responseCoderesponseDescriptioncreatedTimestampupdatedTimestamp | H18: 200 | J18: /send-funds/localft/v1/status | L18: 11111185400000000000062 | N18: 104234abc4 | O18: GsG5c0UhuhXUPj4XlY8G1kcjKioiFrqI | P18: application/json
A19: 18 | B19: =C19 -> Y | C19: Y | D19: TS-EB-PRODUCTS-0204 | E19: TS-EB-PRODUCTS-0204: Send Funds via Local Fund Transfer v1.0 _Check Local Funds Transfer Details and Status API_Verify failed GET request of Local Fund Transfer (Transaction Details) upon providing Not Existing API-Txn-Ref via Intrabank | F19: Send GET Request of Check Local Fund Transfer Details and Status API using Not Existing Transaction ID (API-Txn-Ref) via Intrabank | G19: The API returns an error message as the transaction details of provided transaction reference is not existing. Status: 400 Bad RequeststatusDescription | H19: 400 | I19: Transaction not found for the provided apiTxnRef | J19: /send-funds/localft/v1/status | L19: 11111177400000000000062 | N19: 104234abc4 | O19: GsG5c0UhuhXUPj4XlY8G1kcjKioiFrqI | P19: application/json
A20: 19 | B20: =C20 -> Y | C20: Y | D20: TS-EB-PRODUCTS-0207 | E20: TS-EB-PRODUCTS-0207: Send Funds via Local Fund Transfer v1.0 _Check Local Funds Transfer Details and Status API_Verify failed GET request of Local Fund Transfer (Transaction Details) upon not providing API-Txn-Ref (Blank) via Intrabank | F20: Send GET Request of Check Local Fund Transfer Details and Status API using blank/empty Transaction ID (API-Txn-Ref) via Intrabank | G20: The API returns an error message as the transaction reference is not given but the query parameter is present. Status: 400 Bad RequeststatusDescription | H20: 400 | I20: Exactly one of idempotencyKey, apiTxnId, or apiTxnRef must be provided | J20: /send-funds/localft/v1/status | N20: 104234abc4 | O20: GsG5c0UhuhXUPj4XlY8G1kcjKioiFrqI | P20: application/json
A21: 20 | B21: =C21 -> Y | C21: Y | D21: TS-EB-PRODUCTS-0262 | E21: TS-EB-PRODUCTS-0262: Send Funds via Local Fund Transfer v1.0 _Check Local Funds Transfer Details and Status API_Verify successful GET request of Check Local Fund Transfer Details and Status API for PESONet | F21: Send GET Request of Check Local Fund Transfer Details and Status API of InstaPay transaction | G21: Status HTTP 200 OK [within ≤ 1 second (1000 ms)] Response Body: apiTxnId apiTxnRef ewbCoreReference externalRailreference (InstaPay) status = always "RECEIVED" responseCode responseDescription createdTimestamp updatedTimestamp | H21: 200 | J21: /send-funds/localft/v1/status | L21: 11111177300000000000062 | N21: 104234abc4 | O21: GsG5c0UhuhXUPj4XlY8G1kcjKioiFrqI | P21: application/json
A22: 21 | B22: =C22 -> Y | C22: Y | D22: TS-EB-PRODUCTS-0263 | E22: TS-EB-PRODUCTS-0263: Send Funds via Local Fund Transfer v1.0 _Check Local Funds Transfer Details and Status API_Verify successful GET request of Check Local Fund Transfer Details and Status API for PESONet | F22: Send GET Request of Check Local Fund Transfer Details and Status API of PESONet transaction | G22: Status HTTP 200 OK [within ≤ 1 second (1000 ms)] Response Body: apiTxnId apiTxnRef ewbCoreReference externalRailreference (PESONet) status = always "RECEIVED" responseCode responseDescription createdTimestamp updatedTimestamp | H22: 200 | J22: /send-funds/localft/v1/status | L22: 11111177500000000000062 | N22: 104234abc4 | O22: GsG5c0UhuhXUPj4XlY8G1kcjKioiFrqI | P22: application/json
A23: 22 | B23: =C23 -> Y | C23: Y | D23: TS-EB-PRODUCTS-0264 | E23: TS-EB-PRODUCTS-0264: Send Funds via Local Fund Transfer v1.0 _Check Local Funds Transfer Details and Status API_Verify failed GET request of Check Local Fund Transfer Details and Status API due to invalid partner-id parameters via InstaPay transfer | F23: Send GET Request of Check Local Fund Transfer Details and Status API using invalid partner-id parameter for InstaPay Transfer | G23: responseCode (Status HTTP 401 Unauthorized/403 Forbidden Error [within ≤ 1 second (1000 ms)]}and responseDescription - must be included in API Portal Database | H23: 401 | I23: The partner ID provided is invalid, not recognized, or not registered in Client Hub. | J23: /send-funds/localft/v1/status | L23: 11111177300000000000062 | N23: 1042346054 | O23: GsG5c0UhuhXUPj4XlY8G1kcjKioiFrqI | P23: application/json
A24: 23 | B24: =C24 -> Y | C24: Y | D24: TS-EB-PRODUCTS-0265 | E24: TS-EB-PRODUCTS-0265: Send Funds via Local Fund Transfer v1.0 _Check Local Funds Transfer Details and Status API_Verify failed GET request of Check Local Fund Transfer Details and Status API due to invalid partner-id parameters via PESONet transfer | F24: Send GET Request of Check Local Fund Transfer Details and Status API using invalid partner-id parameter for PESONet Transfer | G24: responseCode (Status HTTP 401 Unauthorized[within ≤ 1 second (1000 ms)]}and responseDescription - must be included in API Portal Database | H24: 401 | I24: The partner ID provided is invalid, not recognized, or not registered in Client Hub. | J24: /send-funds/localft/v1/status | L24: 11111177500000000000062 | N24: 1042346054 | O24: GsG5c0UhuhXUPj4XlY8G1kcjKioiFrqI | P24: application/json
A25: 24 | B25: =C25 -> Y | C25: Y | D25: TS-EB-PRODUCTS-0270 | E25: TS-EB-PRODUCTS-0270: Send Funds via Local Fund Transfer v1.0 _Check Local Funds Transfer Details and Status API_Verify successful retrieval of local funds transfer details using a valid idempotency key InstaPay | F25: Send GET Request of Check Local Fund Transfer Details and Status API using valid idempotency-key via InstaPay | G25: API returns 200 OK status Full transaction details and latest status are returned Response Body: apiTxnId apiTxnRef ewbCoreReference externalRailReference (InstaPay) status = always "RECEIVED" responseCode responseDescription createdTimestamp updatedTimestamp | H25: 200 | J25: /send-funds/localft/v1/status | M25: 1100000000000 | N25: 104234abc4 | O25: GsG5c0UhuhXUPj4XlY8G1kcjKioiFrqI | P25: application/json
A26: 25 | B26: =C26 -> Y | C26: Y | D26: TS-EB-PRODUCTS-0271 | E26: TS-EB-PRODUCTS-0271: Send Funds via Local Fund Transfer v1.0 _Check Local Funds Transfer Details and Status API_Verify successful retrieval of local funds transfer details using a valid idempotency key PESONet | F26: Send GET Request of Check Local Fund Transfer Details and Status API using valid idempotency-key via PESONet | G26: API returns 200 OK status Full transaction details and latest status are returned Response Body: apiTxnId apiTxnRef ewbCoreReference externelRailReference (PESONet) status = always "RECEIVED" responseCode responseDescription createdTimestamp updatedTimestamp | H26: 200 | J26: /send-funds/localft/v1/status | M26: 2200000000000 | N26: 104234abc4 | O26: GsG5c0UhuhXUPj4XlY8G1kcjKioiFrqI | P26: application/json
A27: 26 | B27: =C27 -> Y | C27: Y | D27: TS-EB-PRODUCTS-0272 | E27: TS-EB-PRODUCTS-0272: Send Funds via Local Fund Transfer v1.0 _Check Local Funds Transfer Details and Status API_Verify failed retrieval of local funds transfer details using a non‑existent idempotency key via InstaPay | F27: Send GET Request of Check Local Fund Transfer Details and Status API using not existing idempotency-key via InstaPay | G27: Error response is returned 404 Not Found / 400 Bad Request Transaction details are not found responseCode responseDescription | H27: 400 | I27: Transaction not found for the provided idempotencyKey | J27: /send-funds/localft/v1/status | M27: 5500000000000 | N27: 104234abc4 | O27: GsG5c0UhuhXUPj4XlY8G1kcjKioiFrqI | P27: application/json
A28: 27 | B28: =C28 -> Y | C28: Y | D28: TS-EB-PRODUCTS-0273 | E28: TS-EB-PRODUCTS-0273: Send Funds via Local Fund Transfer v1.0 _Check Local Funds Transfer Details and Status API_Verify failed retrieval of local funds transfer details using a non‑existent idempotency key via PESONet | F28: Send GET Request of Check Local Fund Transfer Details and Status API using not existing idempotency-key via PESONet | G28: Error response is returned 404 Not Found / 400 Bad Request Transaction details are not found responseCode responseDescription | H28: 400 | I28: Transaction not found for the provided idempotencyKey | J28: /send-funds/localft/v1/status | M28: 5500000000000 | N28: 104234abc4 | O28: GsG5c0UhuhXUPj4XlY8G1kcjKioiFrqI | P28: application/json
A29: 28 | B29: =C29 -> Y | C29: Y | D29: TS-EB-PRODUCTS-0274 | E29: TS-EB-PRODUCTS-0274: Send Funds via Local Fund Transfer v1.0 _Check Local Funds Transfer Details and Status API_Verify failed retrieval of local funds transfer details using an invalid idempotency key format via instaPay | F29: Send GET Request of Check Local Fund Transfer Details and Status API using invalid idempotency-key format via InstaPay | G29: Error response is returned 404 Not Found / 400 Bad Request Transaction details are not found responseCode responseDescription | H29: 400 | I29: Transaction not found for the provided idempotencyKey | J29: /send-funds/localft/v1/status | M29: 5500000000O00 | N29: 104234abc4 | O29: GsG5c0UhuhXUPj4XlY8G1kcjKioiFrqI | P29: application/json
A30: 29 | B30: =C30 -> Y | C30: Y | D30: TS-EB-PRODUCTS-0275 | E30: TS-EB-PRODUCTS-0275: Send Funds via Local Fund Transfer v1.0 _Check Local Funds Transfer Details and Status API_Verify failed retrieval of local funds transfer details using an invalid idempotency key format via PESONet | F30: Send GET Request of Check Local Fund Transfer Details and Status API using invalid idempotency-key format via PESONEt | G30: Error response is returned 404 Not Found / 400 Bad Request Transaction details are not found responseCode responseDescription | H30: 400 | I30: Transaction not found for the provided idempotencyKey | J30: /send-funds/localft/v1/status | M30: 400000P000000 | N30: 104234abc4 | O30: GsG5c0UhuhXUPj4XlY8G1kcjKioiFrqI | P30: application/json
A31: 30 | B31: =C31 -> Y | C31: Y | D31: TS-EB-PRODUCTS-0278 | E31: TS-EB-PRODUCTS-0278: Send Funds via Local Fund Transfer v1.0 _Check Local Funds Transfer Details and Status API_Verify failed GET request of Local Fund Transfer (Transaction Details) upon providing Invalid format API-Txn-ID via InstaPay | F31: Send GET Request of Check Local Fund Transfer Details and Status API using Invalid Format Transaction ID (API-Txn-ID) via InstaPay | G31: The API returns an error message: Status 400 Bad Request statusDescription | H31: 400 | I31: Transaction not found for the provided apiTxnId | J31: /send-funds/localft/v1/status | K31: 550 | N31: 104234abc4 | O31: GsG5c0UhuhXUPj4XlY8G1kcjKioiFrqI | P31: application/json
A32: 31 | B32: =C32 -> Y | C32: Y | D32: TS-EB-PRODUCTS-0279 | E32: TS-EB-PRODUCTS-0279: Send Funds via Local Fund Transfer v1.0 _Check Local Funds Transfer Details and Status API_Verify failed GET request of Local Fund Transfer (Transaction Details) upon providing Invalid format API-Txn-ID via PESONet | F32: Send GET Request of Check Local Fund Transfer Details and Status API using Invalid Format Transaction ID (API-Txn-ID) via PESONet | G32: The API returns an error message: Status 400 Bad Request statusDescription | H32: 400 | I32: Transaction not found for the provided apiTxnId | J32: /send-funds/localft/v1/status | K32: 550 | N32: 104234abc4 | O32: GsG5c0UhuhXUPj4XlY8G1kcjKioiFrqI | P32: application/json
A33: 32 | B33: =C33 -> Y | C33: Y | D33: TS-EB-PRODUCTS-0280 | E33: TS-EB-PRODUCTS-0280: Send Funds via Local Fund Transfer v1.0 _Check Local Funds Transfer Details and Status API_Verify failed GET request of Local Fund Transfer (Transaction Details) upon providing Not Existing API-Txn-ID via InstaPay | F33: Send GET Request of Check Local Fund Transfer Details and Status API using Not Existing Transaction ID (API-Txn-ID) via InstaPay | G33: The API returns an error message: Status 400 Bad Request statusDescription | H33: 400 | I33: Transaction not found for the provided apiTxnId | J33: /send-funds/localft/v1/status | K33: 550 | N33: 104234abc4 | O33: GsG5c0UhuhXUPj4XlY8G1kcjKioiFrqI | P33: application/json
A34: 33 | B34: =C34 -> Y | C34: Y | D34: TS-EB-PRODUCTS-0281 | E34: TS-EB-PRODUCTS-0281: Send Funds via Local Fund Transfer v1.0 _Check Local Funds Transfer Details and Status API_Verify failed GET request of Local Fund Transfer (Transaction Details) upon providing Not Existing API-Txn-ID via PESONet | F34: Send GET Request of Check Local Fund Transfer Details and Status API using Not Existing Transaction ID (API-Txn-ID) via PESONet | G34: The API returns an error message: Status 400 Bad Request statusDescription | H34: 400 | I34: Transaction not found for the provided apiTxnId | J34: /send-funds/localft/v1/status | K34: 550 | N34: 104234abc4 | O34: GsG5c0UhuhXUPj4XlY8G1kcjKioiFrqI | P34: application/json
A35: 34 | B35: =C35 -> Y | C35: Y | D35: TS-EB-PRODUCTS-0284 | E35: TS-EB-PRODUCTS-0284: Send Funds via Local Fund Transfer v1.0 _Check Local Funds Transfer Details and Status API_Verify failed GET request of Local Fund Transfer (Transaction Details) upon providing Not Existing API-Txn-Ref via InstaPay | F35: Send GET Request of Check Local Fund Transfer Details and Status API using Not Existing Transaction Ref (API-Txn-Ref) via InstaPay | G35: The API returns an error message as the transaction details of provided transaction reference is not existing. Status: 400 Bad Request statusDescription | H35: 400 | I35: Transaction not found for the provided apiTxnRef | J35: /send-funds/localft/v1/status | L35: 11111177400000000000062 | N35: 104234abc4 | O35: GsG5c0UhuhXUPj4XlY8G1kcjKioiFrqI | P35: application/json
A36: 35 | B36: =C36 -> Y | C36: Y | D36: TS-EB-PRODUCTS-0285 | E36: TS-EB-PRODUCTS-0285: Send Funds via Local Fund Transfer v1.0 _Check Local Funds Transfer Details and Status API_Verify failed GET request of Local Fund Transfer (Transaction Details) upon providing Not Existing API-Txn-Ref via PESONet | F36: Send GET Request of Check Local Fund Transfer Details and Status API using Not Existing Transaction Ref (API-Txn-Ref) via PESONet | G36: The API returns an error message as the transaction details of provided transaction reference is not existing. Status: 400 Bad Request statusDescription | H36: 400 | I36: Transaction not found for the provided apiTxnRef | J36: /send-funds/localft/v1/status | L36: 11111177400000000000062 | N36: 104234abc4 | O36: GsG5c0UhuhXUPj4XlY8G1kcjKioiFrqI | P36: application/json
A37: 36 | B37: =C37 -> Y | C37: Y | D37: TS-EB-PRODUCTS-0290 | E37: TS-EB-PRODUCTS-0290: Send Funds via Local Fund Transfer v1.0 _Check Local Funds Transfer Details and Status API_Verify failed GET request of Local Fund Transfer (Transaction Details) upon not providing API-Txn-Ref (Blank) via InstaPay | F37: Send GET Request of Check Local Fund Transfer Details and Status API using blank/empty Transaction Ref (API-Txn-Ref) via InstaPay | G37: The API returns an error message as the transaction reference is not given but the query parameter is present. Status: 400 Bad Request statusDescription | H37: 400 | I37: Exactly one of idempotencyKey, apiTxnId, or apiTxnRef must be provided | J37: /send-funds/localft/v1/status | N37: 104234abc4 | O37: GsG5c0UhuhXUPj4XlY8G1kcjKioiFrqI | P37: application/json
A38: 37 | B38: =C38 -> Y | C38: Y | D38: TS-EB-PRODUCTS-0291 | E38: TS-EB-PRODUCTS-0291: Send Funds via Local Fund Transfer v1.0 _Check Local Funds Transfer Details and Status API_Verify failed GET request of Local Fund Transfer (Transaction Details) upon not providing API-Txn-Ref (Blank) via PESONet | F38: Send GET Request of Check Local Fund Transfer Details and Status API using blank/empty Transaction Ref (API-Txn-Ref) via PESONet | G38: The API returns an error message as the transaction reference is not given but the query parameter is present. Status: 400 Bad Request statusDescription | H38: 400 | I38: Exactly one of idempotencyKey, apiTxnId, or apiTxnRef must be provided | J38: /send-funds/localft/v1/status | N38: 104234abc4 | O38: GsG5c0UhuhXUPj4XlY8G1kcjKioiFrqI | P38: application/json
A39: 38 | B39: =C39 -> Y | C39: Y | D39: TS-EB-PRODUCTS-0188 | E39: TS-EB-PRODUCTS-0188: Send Funds via Local Fund Transfer v1.0 _Check Local Funds Transfer Details and Status API_Verify successful GET request of Check Local Fund Transfer Details and Status API but failed transaction due to Inactive receiving EWB Account | F39: Send GET Request of Check Local Fund Transfer Details and Status API when transaction is failed due to Inactive Receiving EWB Account | G39: HTTP Code = 200 STATUS = FAILED_REJECTEDResponse Code = 403 Response Description = The transaction was rejected by the payment rail. This usually means there is an issue with the target bank account.Transaction Handling = No action needed since this is already the final state - must be included in API Portal Database | H39: 200 | J39: /send-funds/localft/v1/status | L39: 11111185450000000000062 | N39: 104234abc4 | O39: GsG5c0UhuhXUPj4XlY8G1kcjKioiFrqI | P39: application/json
A40: 39 | B40: =C40 -> Y | C40: Y | D40: TS-EB-PRODUCTS-0189 | E40: TS-EB-PRODUCTS-0189: Send Funds via Local Fund Transfer v1.0 _Check Local Funds Transfer Details and Status API_Verify successful GET request of Check Local Fund Transfer Details and Status API but failed transaction due to rejection by Instapay | F40: Send GET Request of Check Local Fund Transfer Details and Status API when transaction is failed due to Rejection by Instapay | G40: HTTP Code = 200 STATUS = FAILED_REJECTEDResponse Code = The rejection code from the Payment RailResponse Description = The transaction was rejected by the payment rail. This usually means there is an issue with the target bank or wallet account.Transaction Handling = No action needed since this is already the final state - must be included in API Portal Database | H40: 200 | J40: /send-funds/localft/v1/status | L40: 11111177320000000000062 | N40: 104234abc4 | O40: GsG5c0UhuhXUPj4XlY8G1kcjKioiFrqI | P40: application/json
A41: 40 | B41: =C41 -> Y | C41: Y | D41: TS-EB-PRODUCTS-0191 | E41: TS-EB-PRODUCTS-0191: Send Funds via Local Fund Transfer v1.0 _Check Local Funds Transfer Details and Status API_Verify successful GET request of Check Local Fund Transfer Details and Status API but failed transaction due to rejection by Receiving Bank/eWa | F41: Send GET Request of Check Local Fund Transfer Details and Status API when transaction is failed due to Rejection by receiving Bank/eWallet | G41: HTTP Code = 200 STATUS = FAILED_REJECTEDResponse Code = 403 Response Description = The transaction was rejected by the payment rail. This usually means there is an issue with the target bank account.Transaction Handling = No action needed since this is already the final state - must be included in API Portal Database | H41: 200 | J41: /send-funds/localft/v1/status | L41: 11111185440000000000062 | N41: 104234abc4 | O41: GsG5c0UhuhXUPj4XlY8G1kcjKioiFrqI | P41: application/json
A42: 41 | B42: =C42 -> Y | C42: Y | D42: TS-EB-PRODUCTS-0193 | E42: TS-EB-PRODUCTS-0193: Send Funds via Local Fund Transfer v1.0 _Check Local Funds Transfer Details and Status API_Verify failed GET request of Check Local Fund Transfer Details and Status API due to invalid client-credentials parameters via Intrabank | F42: Send GET Request of Check Local Fund Transfer Details and Status API using invalid client-credentials parameter via Intrabank transfer | G42: responseCode (Status HTTP 400 Bad Request / 403 Forbidden [within ≤ 1 second (1000 ms)]}and responseDescription - must be included in API Portal Database | H42: 200 | J42: /send-funds/localft/v1/status | L42: 11111185400000000000062 | N42: 104234abc4 | O42: GsG5c0UhuhXUPj4XlY8G1kcjKioiFrqI | P42: application/json
A43: 42 | B43: =C43 -> Y | C43: Y | D43: TS-EB-PRODUCTS-0208 | E43: TS-EB-PRODUCTS-0208: Send Funds via Local Fund Transfer v1.0 _Check Local Funds Transfer Details and Status API_Verify successful GET request of Local Fund Transfer (Transaction Details) upon providing Application ID linked with Partner ID via Intrabank | F43: Send GET Request of Check Local Fund Transfer Details and Status API using valid Application ID linked with Partner ID via Intrabank | G43: The API Portal that passes the ownership validation request using Application ID linked with Partner ID should dispplay the Transaction Details matches: apiTxnId apiTxnRef ewbCoreReference externalRailReference(if available) Status 200 OK statusDescription timestamps | H43: 200 | J43: /send-funds/localft/v1/status | L43: 11111185400000000000062 | N43: 104234abc4 | O43: GsG5c0UhuhXUPj4XlY8G1kcjKioiFrqI | P43: application/json
A44: 43 | B44: =C44 -> Y | C44: Y | D44: TS-EB-PRODUCTS-0210 | E44: TS-EB-PRODUCTS-0210: Send Funds via Local Fund Transfer v1.0 _Check Local Funds Transfer Details and Status API_Verify the latest reconciled status of Transaction existing | F44: Send GET Request of Check Local Fund Transfer Details and Status API. Check mismatch statuses | G44: Status returned is latest reconciled status with no mismatches Backend reconciliation runs continuously via automated jobs, executing every 5 minutes for real‑time rails and according to scheduled cut‑offs for batch rails, ensuring the API Portal Database always reflects the current state of EWB Core and payment rails. All transaction data and references are kept strictly consistent across all systems, with zero tolerance for floating, pending, unknown, or mismatched statuses at any time. | H44: 200 | J44: /send-funds/localft/v1/status | L44: 11111185400000000000062 | N44: 104234abc4 | O44: GsG5c0UhuhXUPj4XlY8G1kcjKioiFrqI | P44: application/json
A45: 44 | B45: =C45 -> Y | C45: Y | D45: TS-EB-PRODUCTS-0266 | E45: TS-EB-PRODUCTS-0266: Send Funds via Local Fund Transfer v1.0 _Check Local Funds Transfer Details and Status API_Verify failed GET request of Check Local Fund Transfer Details and Status API due to invalid client-credentials parameters via InstaPay | F45: Send GET Request of Check Local Fund Transfer Details and Status API using invalid client-credentials parameter via InstaPay | G45: responseCode (Status HTTP 401 Unauthorized[within ≤ 1 second (1000 ms)]}and responseDescription - must be included in API Portal Database | H45: 200 | J45: /send-funds/localft/v1/status | L45: 11111177300000000000062 | N45: 104234abc4 | O45: GsG5c0UhuhXUPj4XlY8G1kcjKioiFrqI | P45: application/json
A46: 45 | B46: =C46 -> Y | C46: Y | D46: TS-EB-PRODUCTS-0267 | E46: TS-EB-PRODUCTS-0267: Send Funds via Local Fund Transfer v1.0 _Check Local Funds Transfer Details and Status API_Verify failed GET request of Check Local Fund Transfer Details and Status API due to invalid client-credentials parameters via PESONet | F46: Send GET Request of Check Local Fund Transfer Details and Status API using invalid client-credentials parameter via PESONet | G46: responseCode (Status HTTP 401 Unauthorized[within ≤ 1 second (1000 ms)]}and responseDescription - must be included in API Portal Database | H46: 200 | J46: /send-funds/localft/v1/status | L46: 11111177500000000000062 | N46: 104234abc4 | O46: GsG5c0UhuhXUPj4XlY8G1kcjKioiFrqI | P46: application/json
A47: 46 | B47: =C47 -> Y | C47: Y | D47: TS-EB-PRODUCTS-0276 | E47: TS-EB-PRODUCTS-0276: Send Funds via Local Fund Transfer v1.0 _Check Local Funds Transfer Details and Status API_Verify successful GET request of Local Fund Transfer (Transaction Details) upon providing Valid API-Txn-ID via InstaPay | F47: Send GET Request of Check Local Fund Transfer Details and Status API using Valid Transaction ID (API-Txn-ID) via InstaPay | G47: Status HTTP 200 OK [within ≤ 1 second (1000 ms)] Response Body: apiTxnId apiTxnRef ewbCoreReference externalRailReference(InstaPay) status = "COMPLETED/FAILED" responseCode responseDescription createdTimestamp updatedTimestamp | H47: 200 | J47: /send-funds/localft/v1/status | K47: 110 | N47: 104234abc4 | O47: GsG5c0UhuhXUPj4XlY8G1kcjKioiFrqI | P47: application/json
A48: 47 | B48: =C48 -> Y | C48: Y | D48: TS-EB-PRODUCTS-0277 | E48: TS-EB-PRODUCTS-0277: Send Funds via Local Fund Transfer v1.0 _Check Local Funds Transfer Details and Status API_Verify successful GET request of Local Fund Transfer (Transaction Details) upon providing Valid API-Txn-ID via PESONet | F48: Send GET Request of Check Local Fund Transfer Details and Status API using Valid Transaction ID (API-Txn-ID) via PESONet | G48: Status HTTP 200 OK [within ≤ 1 second (1000 ms)] Response Body: apiTxnId apiTxnRef ewbCoreReference externalRailReference(PESONet) status = COMPLETE/FAILED responseCode responseDescription createdTimestamp updatedTimestamp | H48: 200 | J48: /send-funds/localft/v1/status | K48: 220 | N48: 104234abc4 | O48: GsG5c0UhuhXUPj4XlY8G1kcjKioiFrqI | P48: application/json
A49: 48 | B49: =C49 -> Y | C49: Y | D49: TS-EB-PRODUCTS-0282 | E49: TS-EB-PRODUCTS-0282: Send Funds via Local Fund Transfer v1.0 _Check Local Funds Transfer Details and Status API_Verify successful GET request of Local Fund Transfer (Transaction Details) upon providing valid API-Txn-Ref via InstaPay | F49: Send GET Request of Check Local Fund Transfer Details and Status API using Valid Transaction ID (API-Txn-Ref) via InstaPay | G49: Status HTTP 200 OK [within ≤ 1 second (1000 ms)] Response Body: apiTxnId apiTxnRef ewbCoreReference externalRailReference (InstaPay) status = "COMPLETED/FAILED" responseCode responseDescription createdTimestamp updatedTimestamp | H49: 200 | J49: /send-funds/localft/v1/status | L49: 11111177300000000000062 | N49: 104234abc4 | O49: GsG5c0UhuhXUPj4XlY8G1kcjKioiFrqI | P49: application/json
A50: 49 | B50: =C50 -> Y | C50: Y | D50: TS-EB-PRODUCTS-0283 | E50: TS-EB-PRODUCTS-0283: Send Funds via Local Fund Transfer v1.0 _Check Local Funds Transfer Details and Status API_Verify successful GET request of Local Fund Transfer (Transaction Details) upon providing valid API-Txn-Ref via PESONet | F50: Send GET Request of Check Local Fund Transfer Details and Status API using Valid Transaction ID (API-Txn-Ref) via PESONet | G50: Status HTTP 200 OK [within ≤ 1 second (1000 ms)] Response Body: apiTxnId apiTxnRef ewbCoreReference externalRailReference (PESONet) status = COMPLETE/FAILED responseCode responseDescription createdTimestamp updatedTimestamp | H50: 200 | J50: /send-funds/localft/v1/status | L50: 11111177500000000000062 | N50: 104234abc4 | O50: GsG5c0UhuhXUPj4XlY8G1kcjKioiFrqI | P50: application/json
A51: 50 | B51: =C51 -> Y | C51: Y | D51: TS-EB-PRODUCTS-0292 | E51: TS-EB-PRODUCTS-0292: Send Funds via Local Fund Transfer v1.0 _Check Local Funds Transfer Details and Status API_Verify successful GET request of Local Fund Transfer (Transaction Details) upon providing Application ID linked with Partner ID via InstaPay | F51: Send GET Request of Check Local Fund Transfer Details and Status API using valid Application ID linked with Partner ID via InstaPay | G51: The API Portal that passes the ownership validation request using Application ID linked with Partner ID should dispplay the Transaction Details matches: HTTP 200 OK Status Response Body: apiTxnId apiTxnRef ewbCoreReference externalRailReference (InstaPay) status = "COMPLETE/FAILED" responseCode responseDescription createdTimestamp updatedTimestamp | H51: 200 | J51: /send-funds/localft/v1/status | L51: 11111177300000000000062 | N51: 104234abc4 | O51: GsG5c0UhuhXUPj4XlY8G1kcjKioiFrqI | P51: application/json
A52: 51 | B52: =C52 -> Y | C52: Y | D52: TS-EB-PRODUCTS-0293 | E52: TS-EB-PRODUCTS-0293: Send Funds via Local Fund Transfer v1.0 _Check Local Funds Transfer Details and Status API_Verify successful GET request of Local Fund Transfer (Transaction Details) upon providing Application ID linked with Partner ID via PESONet | F52: Send GET Request of Check Local Fund Transfer Details and Status API using valid Application ID linked with Partner ID via PESONet | G52: The API Portal that passes the ownership validation request using Application ID linked with Partner ID should dispplay the Transaction Details matches: HTTP 200 OK Status Response Body: apiTxnId apiTxnRef ewbCoreReference externalRailReference (PESONet) status = "COMPLETE/FAILED" responseCode responseDescription createdTimestamp updatedTimestamp | H52: 200 | J52: /send-funds/localft/v1/status | L52: 11111177500000000000062 | N52: 104234abc4 | O52: GsG5c0UhuhXUPj4XlY8G1kcjKioiFrqI | P52: application/json
A53: 52 | B53: =C53 -> N | C53: N | D53: TS-EB-PRODUCTS-0336 | E53: TS-EB-PRODUCTS-0336: Send Funds via Local Fund Transfer v1.0 _Check Local Funds Transfer Details and Status API_Verify API Response upon using 2-3 parameters | F53: Send failed GET Request of Check Local Fund Transfer Details and Status API | G53: 1. The api returns 400 Bad Request 2. Sample Request URL.: https://proxy-apim-external-test.eastwestbanker.com/test/send-funds/localft/v1/status?apiTxnId=351&apiTxnRef=0D84887734626740593296V 3. Sample Response Body { "status": "400", "errors": [ { "errorCode": "INVALID_ARGUMENT", "errorDescription": "Exactly one of idempotencyKey, apiTxnId, or apiTxnRef must be provided" } ], "authId": "auth-48c6926e-799d-4cb8-b81f-11b20bf2b18b", "responseCode": "400", "responseDescription": "Exactly one of idempotencyKey, apiTxnId, or apiTxnRef must be provided" } | H53: 400 | I53: Exactly one of idempotencyKey, apiTxnId, or apiTxnRef must be provided | J53: /send-funds/localft/v1/status | N53: 104234abc4 | O53: GsG5c0UhuhXUPj4XlY8G1kcjKioiFrqI | P53: application/json
A54: 53 | B54: N | C54: N | D54: TS-EB-PRODUCTS-0194 | E54: TS-EB-PRODUCTS-0194: Send Funds via Local Fund Transfer v1.0 _Check Local Funds Transfer Details and Status API_Verify failed GET request of Check Local Fund Transfer Details and Status API due to wrong scope or ownership via Intrabank | F54: Send GET Request of Check Local Fund Transfer Details and Status API using wrong scope or ownership via Intrabank | G54: responseCode (Status HTTP 403 Forbidden [within ≤ 1 second (1000 ms)]}and responseDescription - must be included in API Portal Database | H54: 401 | J54: /send-funds/localft/v1/status | L54: 46249877312345168969213 | N54: 1042346954 | O54: GsG5c0UhuhXUPj4XlY8G1kcjKioiFrqI | P54: application/json
A55: 54 | B55: N | C55: N | D55: TS-EB-PRODUCTS-0199 | E55: TS-EB-PRODUCTS-0199: Send Funds via Local Fund Transfer v1.0 _Check Local Funds Transfer Details and Status API_Verify failed retrieval of local funds transfer details due to ownership validation failure | F55: Send GET Request of Check Local Fund Transfer Details and Status API when set parameter has failed the testing for account ownership | G55: API returns 403 Forbidden Transaction details are not exposed | H55: 400/401/403 | J55: /send-funds/localft/v1/status | M55: 5500000000000 | N55: 1042346954 | O55: GsG5c0UhuhXUPj4XlY8G1kcjKioiFrqI | P55: application/json
A56: 55 | B56: N | C56: N | D56: TS-EB-PRODUCTS-0209 | E56: TS-EB-PRODUCTS-0209: Send Funds via Local Fund Transfer v1.0 _Check Local Funds Transfer Details and Status API_Verify failed GET request of upon providing Application ID linked with Partner ID but didn't pass the ownership validation via Intrabank | F56: Send GET Request of Check Local Fund Transfer Details and Status API using valid Application ID linked with Partner ID but doesn't match during ownership validation via Intrabank | G56: Status 403 Forbidden is returned with clear error message.
A57: 56 | B57: N | C57: N | D57: TS-EB-PRODUCTS-0268 | E57: TS-EB-PRODUCTS-0268: Send Funds via Local Fund Transfer v1.0 _Check Local Funds Transfer Details and Status API_Verify failed GET request of Check Local Fund Transfer Details and Status API due to wrong scope or ownership via InstaPay | F57: Send GET Request of Check Local Fund Transfer Details and Status API using wrong scope or ownership via InstaPay | G57: responseCode (Status HTTP 403 Forbidden [within ≤ 1 second (1000 ms)]}and responseDescription - must be included in API Portal Database | J57: /send-funds/localft/v1/status | N57: 1042346954 | O57: GsG5c0UhuhXUPj4XlY8G1kcjKioiFrqI | P57: application/json
A58: 57 | B58: N | C58: N | D58: TS-EB-PRODUCTS-0269 | E58: TS-EB-PRODUCTS-0269: Send Funds via Local Fund Transfer v1.0 _Check Local Funds Transfer Details and Status API_Verify failed GET request of Check Local Fund Transfer Details and Status API due to wrong scope or ownership via PESONet | F58: Send GET Request of Check Local Fund Transfer Details and Status API using wrong scope or ownership via PESONet | G58: responseCode (Status HTTP 403 Forbidden [within ≤ 1 second (1000 ms)]}and responseDescription - must be included in API Portal Database | J58: /send-funds/localft/v1/status | N58: 1042346954 | O58: GsG5c0UhuhXUPj4XlY8G1kcjKioiFrqI | P58: application/json
A59: 58 | B59: N | C59: N | D59: TS-EB-PRODUCTS-0294 | E59: TS-EB-PRODUCTS-0294: Send Funds via Local Fund Transfer v1.0 _Check Local Funds Transfer Details and Status API_Verify failed GET request of upon providing Application ID linked with Partner ID but didn't pass the ownership validation via InstaPay | F59: Send GET Request of Check Local Fund Transfer Details and Status API using valid Application ID linked with Partner ID but doesn't match during ownership validation via InstaPay | G59: Status 403 Forbidden is returned with clear error message. | J59: /send-funds/localft/v1/status | N59: 1042346954 | O59: GsG5c0UhuhXUPj4XlY8G1kcjKioiFrqI | P59: application/json
A60: 59 | B60: N | C60: N | D60: TS-EB-PRODUCTS-0295 | E60: TS-EB-PRODUCTS-0295: Send Funds via Local Fund Transfer v1.0 _Check Local Funds Transfer Details and Status API_Verify failed GET request of upon providing Application ID linked with Partner ID but didn't pass the ownership validation via PESONet | F60: Send GET Request of Check Local Fund Transfer Details and Status API using valid Application ID linked with Partner ID but doesn't match during ownership validation via PESONet | G60: Status 403 Forbidden is returned with clear error message. | J60: /send-funds/localft/v1/status | N60: 1042346954 | O60: GsG5c0UhuhXUPj4XlY8G1kcjKioiFrqI | P60: application/json
A61: 60 | B61: N | C61: N | D61: TS-EB-PRODUCTS-0351 | E61: TS-EB-PRODUCTS-0351: Send Funds via Local Fund Transfer v1.0 _Check Local Funds Transfer Details and Status API_Verify Instapay transaction status upon using incorrect swiftCode (bankCode) | F61: Send GET Request of transaction with incorrect swiftCode (bankCode) | G61: { "apiTxnId": 201, "apiTxnRef": "FT3DNQA1GJ261NC6NC4636U", "channel": "INSTAPAY", "ewbCoreReference": null, "externalRailReference": null, "externalRailCode": "404", "transferAmount": 7.00, "transferCurrency": "PHP", "responseCode": "404", "status": "FAILED", "responseDescription": "Unable to retrieve swift code. [E0001: ]", "createdTimestamp": 1781061302.605000000, "completedTimestamp": null, "updatedTimestamp": 1781090102.564000000 } | J61: /send-funds/localft/v1/status | N61: 1042346954 | O61: GsG5c0UhuhXUPj4XlY8G1kcjKioiFrqI | P61: application/json

Sheet SBSendFunds
A1: # | B1: ExecutionFlag | C1: CORE | D1: TC_ID | E1: Description | F1: StepAction | G1: ExpectedResult | H1: ExpectedStatus | I1: ExpectedResponseDescription | J1: IN_EndPointBearer | K1: IN_EndPoint | L1: IN_HeadAccept | M1: IN_HeadClientSecret | N1: IN_HeadClientID | O1: IN_HeadPartnerID | P1: IN_HeadAPIKey | Q1: IN_HeadCorrelationID | R1: IN_HeadContentType | S1: IN_NonGeneratedToken | T1: IN_Channel | U1: IN_Scope | V1: IN_SourceAccountNumber | W1: IN_UltimateSenderName | X1: IN_BankCode | Y1: IN_TargetAccountNumber | Z1: IN_UltimateBeneficiaryName | AA1: IN_Amount | AB1: IN_IPAddress | AC1: IN_GeoLatitude | AD1: IN_GeoLongitude | AE1: IN_DeviceId | AF1: IN_UserAgent | AG1: IN_Country | AH1: IN_ApplicationType | AI1: IN_IPCity | AJ1: OUT_TxnID | AK1: OUT_TxnRef | AL1: OUT_RequestHeaders | AM1: OUT_RequestBody | AN1: OUT_ResponseHeaders | AO1: OUT_ResponseBody
A2: 1 | B2: Y | C2: Y | D2: TS-EB-SB-PRODUCTS-0008 | E2: TS-EB-SB-PRODUCTS-0008-Verify Successful initiation of a Local funds transfer via Intrabank (EWB to EWB) | F2: Send POST Request of Send Funds via Local Fund Transfer via EWB to EWB | G2: DB Initial Status = RECEIVED with (full 13-digit idempotency-key stored (with 48-hour TTL for duplicate checks) apiTxnId, apiTxnRef, ewbCoreReference, externalRailReference (if available), status(RECEIVED), statusDescription, and createdTimestamp. EWB API PORTAL Status = COMPLETED Response Code = 200 Response Description = The transaction has been successfully received and credited. Transaction Handling = No action needed since this is already the final state apiTxnRef is correctly constructed (Application-ID + Product-ID + Idempotency-Key + wildcard) and propagated to EWB Core Banking System, payment rails, logs, reconciliation files, and audit trails. | H2: 200 | J2: /auth/token/v1/generate | K2: /send-funds/localft/v1/initiate | L2: application/json | M2: cnfKqb1Q53rmlS8HifRZf7zvtGZOSlUQ | N2: 1VjIqTcMCJ8tIv8bMpv9l9x01ebYQd88 | O2: 104234abc4 | P2: GsG5c0UhuhXUPj4XlY8G1kcjKioiFrqI | Q2: 924fdda7-26f7-414b-ac56-9214ff796881 | R2: application/json | T2: INTRABANK | U2: send-funds.initiate | V2: 200061777902 | W2: Lorence Ecle | X2: EWBCPHMMXXX | Y2: 200061812368 | Z2: Pao Casipe | AA2: 1 | AB2: 203.0.113.42 | AC2: 14.599500 | AD2: 120.984200 | AE2: device-abc123 | AF2: AcmePayrollApp/2.1 | AG2: Philippines | AH2: Desktop | AI2: Mandaluyong
A3: 2 | B3: Y | C3: Y | D3: TS-EB-SB-PRODUCTS-0009 | E3: TS-EB-SB-PRODUCTS-0009-Verify Successful initiation of a Local funds transfer via Intrabank (EWB to EWRB) | F3: Send POST Request of Send Funds via Local Fund Transfer via EWB to EWRB | G3: DB Initial Status = RECEIVED with (full 13-digit idempotency-key stored (with 48-hour TTL for duplicate checks) apiTxnId, apiTxnRef, ewbCoreReference, externalRailReference (if available), status(RECEIVED), statusDescription, and createdTimestamp. EWB API PORTAL Status = COMPLETED Response Code = 200 Response Description = The transaction has been successfully received and credited. Transaction Handling = No action needed since this is already the final state apiTxnRef is correctly constructed (Application-ID + Product-ID + Idempotency-Key + wildcard) and propagated to EWB Core Banking System, payment rails, logs, reconciliation files, and audit trails. | H3: 200 | J3: /auth/token/v1/generate | K3: /send-funds/localft/v1/initiate | L3: application/json | M3: cnfKqb1Q53rmlS8HifRZf7zvtGZOSlUQ | N3: 1VjIqTcMCJ8tIv8bMpv9l9x01ebYQd88 | O3: 104234abc4 | P3: GsG5c0UhuhXUPj4XlY8G1kcjKioiFrqI | Q3: 924fdda7-26f7-414b-ac56-9214ff796881 | R3: application/json | T3: INTRABANK | U3: send-funds.initiate | V3: 200061777902 | W3: Lorence Ecle | X3: EAWRPHM2XXX | Y3: 500027172598 | Z3: Pao Casipe | AA3: 1 | AB3: 203.0.113.42 | AC3: 14.599500 | AD3: 120.984200 | AE3: device-abc123 | AF3: AcmePayrollApp/2.1 | AG3: Philippines | AH3: Desktop | AI3: Mandaluyong
A4: 3 | B4: Y | C4: Y | D4: TS-EB-SB-PRODUCTS-0010 | E4: TS-EB-SB-PRODUCTS-0010-Verify Successful initiation of a local funds transfer via InstaPay | F4: Send POST Request of Send Funds via Local Fund Transfer via EWB to InstaPay | G4: DB Initial Status = RECEIVED with (full 13-digit idempotency-key stored (with 48-hour TTL for duplicate checks) apiTxnId, apiTxnRef, ewbCoreReference, externalRailReference (if available), status (RECEIVED), statusDescription, and createdTimestamp. EWB API PORTAL Status = COMPLETED Response Code = 200 Response Description = The transaction has been successfully received by the receiving bank/wallet. Transaction Handling = No action needed since this is already the final state apiTxnRef is correctly constructed (Application-ID + Product-ID + Idempotency-Key + wildcard) and propagated to EWB Core Banking System, payment rails, logs, reconciliation files, and audit trails. | H4: 200 | J4: /auth/token/v1/generate | K4: /send-funds/localft/v1/initiate | L4: application/json | M4: cnfKqb1Q53rmlS8HifRZf7zvtGZOSlUQ | N4: 1VjIqTcMCJ8tIv8bMpv9l9x01ebYQd88 | O4: 104234abc4 | P4: GsG5c0UhuhXUPj4XlY8G1kcjKioiFrqI | Q4: 924fdda7-26f7-414b-ac56-9214ff796881 | R4: application/json | T4: INSTAPAY | U4: send-funds.initiate | V4: 200061777902 | W4: Lorence Ecle | X4: CUOBPHM2XXX | Y4: 001080000029 | Z4: Pao Casipe | AA4: 1 | AB4: 203.0.113.42 | AC4: 14.599500 | AD4: 120.984200 | AE4: device-abc123 | AF4: AcmePayrollApp/2.1 | AG4: Philippines | AH4: Desktop | AI4: Mandaluyong
A5: 4 | B5: Y | C5: Y | D5: TS-EB-SB-PRODUCTS-0011 | E5: TS-EB-SB-PRODUCTS-0011-Verify Successful initiation of a local funds transfer via PESONet | F5: Send POST Request of Send Funds via Local Fund Transfer via EWB to PESONet | G5: DB Initial Status = RECEIVED with (full 13-digit idempotency-key stored (with 48-hour TTL for duplicate checks) apiTxnId, apiTxnRef, ewbCoreReference, externalRailReference (if available), status (RECIEVED), statusDescription, and createdTimestamp. EWB API PORTAL Status = COMPLETED Response Code = 200 Response Description = The transaction has been successfully received by the receiving bank/wallet. Transaction Handling = No action needed since this is already the final state apiTxnRef is correctly constructed (Application-ID + Product-ID + Idempotency-Key + wildcard) and propagated to EWB Core Banking System, payment rails, logs, reconciliation files, and audit trails. | H5: 200 | J5: /auth/token/v1/generate | K5: /send-funds/localft/v1/initiate | L5: application/json | M5: cnfKqb1Q53rmlS8HifRZf7zvtGZOSlUQ | N5: 1VjIqTcMCJ8tIv8bMpv9l9x01ebYQd88 | O5: 104234abc4 | P5: GsG5c0UhuhXUPj4XlY8G1kcjKioiFrqI | Q5: 924fdda7-26f7-414b-ac56-9214ff796881 | R5: application/json | T5: PESONET | U5: send-funds.initiate | V5: 200061777902 | W5: Lorence Ecle | X5: CUOBPHM2XXX | Y5: 001080000029 | Z5: Pao Casipe | AA5: 1 | AB5: 203.0.113.42 | AC5: 14.599500 | AD5: 120.984200 | AE5: device-abc123 | AF5: AcmePayrollApp/2.1 | AG5: Philippines | AH5: Desktop | AI5: Mandaluyong
A6: 5 | B6: Y | C6: Y | D6: TS-EB-SB-PRODUCTS-0012_1 | E6: TS-EB-SB-PRODUCTS-0012_1-Transfer with No Amount | F6: Send POST Request of Send Funds via Local Fund Transfer using No Amount | G6: Failed Status 400 Bad Request | H6: 400 | I6: Amount must be a plain decimal number (no scientific notation or letters). | J6: /auth/token/v1/generate | K6: /send-funds/localft/v1/initiate | L6: application/json | M6: cnfKqb1Q53rmlS8HifRZf7zvtGZOSlUQ | N6: 1VjIqTcMCJ8tIv8bMpv9l9x01ebYQd88 | O6: 104234abc4 | P6: GsG5c0UhuhXUPj4XlY8G1kcjKioiFrqI | Q6: 924fdda7-26f7-414b-ac56-9214ff796881 | R6: application/json | T6: INTRABANK | U6: send-funds.initiate | V6: 200061777902 | W6: Lorence Ecle | X6: EWBCPHMMXXX | Y6: 200061812368 | Z6: Pao Casipe | AB6: 203.0.113.42 | AC6: 14.599500 | AD6: 120.984200 | AE6: device-abc123 | AF6: AcmePayrollApp/2.1 | AG6: Philippines | AH6: Desktop | AI6: Mandaluyong
A7: 6 | B7: Y | C7: Y | D7: TS-EB-SB-PRODUCTS-0012_2 | E7: TS-EB-SB-PRODUCTS-0012_2-Transfer with No Amount | F7: Send POST Request of Send Funds via Local Fund Transfer using No Amount | G7: Failed Status 400 Bad Request | H7: 400 | I7: Amount must be a plain decimal number (no scientific notation or letters). | J7: /auth/token/v1/generate | K7: /send-funds/localft/v1/initiate | L7: application/json | M7: cnfKqb1Q53rmlS8HifRZf7zvtGZOSlUQ | N7: 1VjIqTcMCJ8tIv8bMpv9l9x01ebYQd88 | O7: 104234abc4 | P7: GsG5c0UhuhXUPj4XlY8G1kcjKioiFrqI | Q7: 924fdda7-26f7-414b-ac56-9214ff796881 | R7: application/json | T7: INTRABANK | U7: send-funds.initiate | V7: 200061777902 | W7: Lorence Ecle | X7: EAWRPHM2XXX | Y7: 500027172598 | Z7: Pao Casipe | AB7: 203.0.113.42 | AC7: 14.599500 | AD7: 120.984200 | AE7: device-abc123 | AF7: AcmePayrollApp/2.1 | AG7: Philippines | AH7: Desktop | AI7: Mandaluyong
A8: 7 | B8: Y | C8: Y | D8: TS-EB-SB-PRODUCTS-0012_3 | E8: TS-EB-SB-PRODUCTS-0012_3-Transfer with No Amount | F8: Send POST Request of Send Funds via Local Fund Transfer using No Amount | G8: Failed Status 400 Bad Request | H8: 400 | I8: Amount must be a plain decimal number (no scientific notation or letters). | J8: /auth/token/v1/generate | K8: /send-funds/localft/v1/initiate | L8: application/json | M8: cnfKqb1Q53rmlS8HifRZf7zvtGZOSlUQ | N8: 1VjIqTcMCJ8tIv8bMpv9l9x01ebYQd88 | O8: 104234abc4 | P8: GsG5c0UhuhXUPj4XlY8G1kcjKioiFrqI | Q8: 924fdda7-26f7-414b-ac56-9214ff796881 | R8: application/json | T8: INSTAPAY | U8: send-funds.initiate | V8: 200061777902 | W8: Lorence Ecle | X8: CUOBPHM2XXX | Y8: 001080000029 | Z8: Pao Casipe | AB8: 203.0.113.42 | AC8: 14.599500 | AD8: 120.984200 | AE8: device-abc123 | AF8: AcmePayrollApp/2.1 | AG8: Philippines | AH8: Desktop | AI8: Mandaluyong
A9: 8 | B9: Y | C9: Y | D9: TS-EB-SB-PRODUCTS-0012_4 | E9: TS-EB-SB-PRODUCTS-0012_4-Transfer with No Amount | F9: Send POST Request of Send Funds via Local Fund Transfer using No Amount | G9: Failed Status 400 Bad Request | H9: 400 | I9: Amount must be a plain decimal number (no scientific notation or letters). | J9: /auth/token/v1/generate | K9: /send-funds/localft/v1/initiate | L9: application/json | M9: cnfKqb1Q53rmlS8HifRZf7zvtGZOSlUQ | N9: 1VjIqTcMCJ8tIv8bMpv9l9x01ebYQd88 | O9: 104234abc4 | P9: GsG5c0UhuhXUPj4XlY8G1kcjKioiFrqI | Q9: 924fdda7-26f7-414b-ac56-9214ff796881 | R9: application/json | T9: PESONET | U9: send-funds.initiate | V9: 200061777902 | W9: Lorence Ecle | X9: CUOBPHM2XXX | Y9: 001080000029 | Z9: Pao Casipe | AB9: 203.0.113.42 | AC9: 14.599500 | AD9: 120.984200 | AE9: device-abc123 | AF9: AcmePayrollApp/2.1 | AG9: Philippines | AH9: Desktop | AI9: Mandaluyong
A10: 9 | B10: =C10 -> N | C10: N | D10: TS-EB-SB-PRODUCTS-0013_1 | E10: TS-EB-SB-PRODUCTS-0013_1-Verify if Missing Access Token is use in Local Fund Transfer | F10: Send POST Request of Send Funds via Local Fund Transfer without/missing Access Token | G10: Failed Status 401 Unauthorized | H10: 401 | I10: Missing required parameter: Authorization | J10: /auth/token/v1/generate | K10: /send-funds/localft/v1/initiate | L10: application/json | M10: cnfKqb1Q53rmlS8HifRZf7zvtGZOSlUQ | N10: 1VjIqTcMCJ8tIv8bMpv9l9x01ebYQd88 | O10: 104234abc4 | P10: GsG5c0UhuhXUPj4XlY8G1kcjKioiFrqI | Q10: 924fdda7-26f7-414b-ac56-9214ff796881 | R10: application/json | T10: INTRABANK | U10: send-funds.initiate | V10: 200061777902 | W10: Lorence Ecle | X10: EWBCPHMMXXX | Y10: 200061812368 | Z10: Pao Casipe | AA10: 1 | AB10: 203.0.113.42 | AC10: 14.599500 | AD10: 120.984200 | AE10: device-abc123 | AF10: AcmePayrollApp/2.1 | AG10: Philippines | AH10: Desktop | AI10: Mandaluyong
A11: 10 | B11: =C11 -> N | C11: N | D11: TS-EB-SB-PRODUCTS-0013_2 | E11: TS-EB-SB-PRODUCTS-0013_2-Verify if Missing Access Token is use in Local Fund Transfer | F11: Send POST Request of Send Funds via Local Fund Transfer without/missing Access Token | G11: Failed Status 401 Unauthorized | H11: 401 | I11: Missing required parameter: Authorization | J11: /auth/token/v1/generate | K11: /send-funds/localft/v1/initiate | L11: application/json | M11: cnfKqb1Q53rmlS8HifRZf7zvtGZOSlUQ | N11: 1VjIqTcMCJ8tIv8bMpv9l9x01ebYQd88 | O11: 104234abc4 | P11: GsG5c0UhuhXUPj4XlY8G1kcjKioiFrqI | Q11: 924fdda7-26f7-414b-ac56-9214ff796881 | R11: application/json | T11: INTRABANK | U11: send-funds.initiate | V11: 200061777902 | W11: Lorence Ecle | X11: EAWRPHM2XXX | Y11: 500027172598 | Z11: Pao Casipe | AA11: 1 | AB11: 203.0.113.42 | AC11: 14.599500 | AD11: 120.984200 | AE11: device-abc123 | AF11: AcmePayrollApp/2.1 | AG11: Philippines | AH11: Desktop | AI11: Mandaluyong
A12: 11 | B12: =C12 -> N | C12: N | D12: TS-EB-SB-PRODUCTS-0013_3 | E12: TS-EB-SB-PRODUCTS-0013_3-Verify if Missing Access Token is use in Local Fund Transfer | F12: Send POST Request of Send Funds via Local Fund Transfer without/missing Access Token | G12: Failed Status 401 Unauthorized | H12: 401 | I12: Missing required parameter: Authorization | J12: /auth/token/v1/generate | K12: /send-funds/localft/v1/initiate | L12: application/json | M12: cnfKqb1Q53rmlS8HifRZf7zvtGZOSlUQ | N12: 1VjIqTcMCJ8tIv8bMpv9l9x01ebYQd88 | O12: 104234abc4 | P12: GsG5c0UhuhXUPj4XlY8G1kcjKioiFrqI | Q12: 924fdda7-26f7-414b-ac56-9214ff796881 | R12: application/json | T12: INSTAPAY | U12: send-funds.initiate | V12: 200061777902 | W12: Lorence Ecle | X12: CUOBPHM2XXX | Y12: 001080000029 | Z12: Pao Casipe | AA12: 1 | AB12: 203.0.113.42 | AC12: 14.599500 | AD12: 120.984200 | AE12: device-abc123 | AF12: AcmePayrollApp/2.1 | AG12: Philippines | AH12: Desktop | AI12: Mandaluyong
A13: 12 | B13: =C13 -> N | C13: N | D13: TS-EB-SB-PRODUCTS-0013_4 | E13: TS-EB-SB-PRODUCTS-0013_4-Verify if Missing Access Token is use in Local Fund Transfer | F13: Send POST Request of Send Funds via Local Fund Transfer without/missing Access Token | G13: Failed Status 401 Unauthorized | H13: 401 | I13: Missing required parameter: Authorization | J13: /auth/token/v1/generate | K13: /send-funds/localft/v1/initiate | L13: application/json | M13: cnfKqb1Q53rmlS8HifRZf7zvtGZOSlUQ | N13: 1VjIqTcMCJ8tIv8bMpv9l9x01ebYQd88 | O13: 104234abc4 | P13: GsG5c0UhuhXUPj4XlY8G1kcjKioiFrqI | Q13: 924fdda7-26f7-414b-ac56-9214ff796881 | R13: application/json | T13: PESONET | U13: send-funds.initiate | V13: 200061777902 | W13: Lorence Ecle | X13: CUOBPHM2XXX | Y13: 001080000029 | Z13: Pao Casipe | AA13: 1 | AB13: 203.0.113.42 | AC13: 14.599500 | AD13: 120.984200 | AE13: device-abc123 | AF13: AcmePayrollApp/2.1 | AG13: Philippines | AH13: Desktop | AI13: Mandaluyong
A14: 13 | B14: =C14 -> N | C14: N | D14: TS-EB-SB-PRODUCTS-0014 | E14: TS-EB-SB-PRODUCTS-0014-Verify Local Fund Transfer if Source Account is Not Registered as Client Owned Account - Source Account via EWB to EWB | F14: Send POST Request of Send Funds via Local Fund Transfer via EWB to EWB using Not Registered as Client Owned Account - Source Account | G14: DB Initial Status = RECEIVED with (full 13-digit idempotency-key stored (with 48-hour TTL for duplicate checks) apiTxnId, apiTxnRef, ewbCoreReference, externalRailReference (if available, Instapay/PESONet applicable), status(PENDING), statusDescription, and createdTimestamp. apiTxnRef is correctly constructed (Application-ID + Product-ID + Idempotency-Key + wildcard) and propagated to EWB Core Banking System, payment rails, logs, reconciliation files, and audit trails. | H14: 400 | I14: Account not found for accountNumber=200061777909 and partnerId=104234abc4 | J14: /auth/token/v1/generate | K14: /send-funds/localft/v1/initiate | L14: application/json | M14: cnfKqb1Q53rmlS8HifRZf7zvtGZOSlUQ | N14: 1VjIqTcMCJ8tIv8bMpv9l9x01ebYQd88 | O14: 104234abc4 | P14: GsG5c0UhuhXUPj4XlY8G1kcjKioiFrqI | Q14: 924fdda7-26f7-414b-ac56-9214ff796881 | R14: application/json | S14: luyoBItdetZbLfAJ3F1kvLfZgl1UAEY2 | T14: INTRABANK | U14: send-funds.initiate | V14: 200061777909 | W14: Lorence Ecle | X14: EWBCPHMMXXX | Y14: 200061812368 | Z14: Pao Casipe | AA14: 1 | AB14: 203.0.113.42 | AC14: 14.599500 | AD14: 120.984200 | AE14: device-abc123 | AF14: AcmePayrollApp/2.1 | AG14: Philippines | AH14: Desktop | AI14: Mandaluyong
A15: 14 | B15: =C15 -> N | C15: N | D15: TS-EB-SB-PRODUCTS-0015 | E15: TS-EB-SB-PRODUCTS-0015-Verify Local Fund Transfer if Source Account is Not Registered as Client Owned Account - Source Account via EWB to EWRB | F15: Send POST Request of Send Funds via Local Fund Transfer via EWB to EWRB using Not Registered as Client Owned Account - Source Account | G15: DB Initial Status = RECEIVED with (full 13-digit idempotency-key stored (with 48-hour TTL for duplicate checks) apiTxnId, apiTxnRef, ewbCoreReference, externalRailReference (if available, Instapay/PESONet applicable), status (PENDING), statusDescription, and createdTimestamp. apiTxnRef is correctly constructed (Application-ID + Product-ID + Idempotency-Key + wildcard) and propagated to EWB Core Banking System, payment rails, logs, reconciliation files, and audit trails. | H15: 400 | I15: Account not found for accountNumber=200061777909 and partnerId=104234abc4 | J15: /auth/token/v1/generate | K15: /send-funds/localft/v1/initiate | L15: application/json | M15: cnfKqb1Q53rmlS8HifRZf7zvtGZOSlUQ | N15: 1VjIqTcMCJ8tIv8bMpv9l9x01ebYQd88 | O15: 104234abc4 | P15: GsG5c0UhuhXUPj4XlY8G1kcjKioiFrqI | Q15: 924fdda7-26f7-414b-ac56-9214ff796881 | R15: application/json | S15: luyoBItdetZbLfAJ3F1kvLfZgl1UAEY2 | T15: INTRABANK | U15: send-funds.initiate | V15: 200061777909 | W15: Lorence Ecle | X15: EAWRPHM2XXX | Y15: 500027172598 | Z15: Pao Casipe | AA15: 1 | AB15: 203.0.113.42 | AC15: 14.599500 | AD15: 120.984200 | AE15: device-abc123 | AF15: AcmePayrollApp/2.1 | AG15: Philippines | AH15: Desktop | AI15: Mandaluyong
A16: 15 | B16: =C16 -> N | C16: N | D16: TS-EB-SB-PRODUCTS-0016 | E16: TS-EB-SB-PRODUCTS-0016-Verify Local Fund Transfer if Source Account is Not Registered as Client Owned Account - Source Account via EWB to InstaPay | F16: Send POST Request of Send Funds via Local Fund Transfer via EWB to InstaPay using Not Registered as Client Owned Account - Source Account | G16: DB Initial Status = RECEIVED with (full 13-digit idempotency-key stored (with 48-hour TTL for duplicate checks) apiTxnId, apiTxnRef, ewbCoreReference, externalRailReference (if available, Instapay/PESONet applicable), status (PENDING), statusDescription, and createdTimestamp. apiTxnRef is correctly constructed (Application-ID + Product-ID + Idempotency-Key + wildcard) and propagated to EWB Core Banking System, payment rails, logs, reconciliation files, and audit trails. | H16: 400 | I16: Account not found for accountNumber=200061777909 and partnerId=104234abc4 | J16: /auth/token/v1/generate | K16: /send-funds/localft/v1/initiate | L16: application/json | M16: cnfKqb1Q53rmlS8HifRZf7zvtGZOSlUQ | N16: 1VjIqTcMCJ8tIv8bMpv9l9x01ebYQd88 | O16: 104234abc4 | P16: GsG5c0UhuhXUPj4XlY8G1kcjKioiFrqI | Q16: 924fdda7-26f7-414b-ac56-9214ff796881 | R16: application/json | S16: luyoBItdetZbLfAJ3F1kvLfZgl1UAEY2 | T16: INSTAPAY | U16: send-funds.initiate | V16: 200061777909 | W16: Lorence Ecle | X16: CUOBPHM2XXX | Y16: 001080000029 | Z16: Pao Casipe | AA16: 1 | AB16: 203.0.113.42 | AC16: 14.599500 | AD16: 120.984200 | AE16: device-abc123 | AF16: AcmePayrollApp/2.1 | AG16: Philippines | AH16: Desktop | AI16: Mandaluyong
A17: 16 | B17: =C17 -> N | C17: N | D17: TS-EB-SB-PRODUCTS-0017 | E17: TS-EB-SB-PRODUCTS-0017-Verify Local Fund Transfer if Source Account is Not Registered as Client Owned Account - Source Account via EWB to PESONet | F17: Send POST Request of Send Funds via Local Fund Transfer via EWB to PESOnet using Not Registered as Client Owned Account - Source Account | G17: DB Initial Status = RECEIVED with (full 13-digit idempotency-key stored (with 48-hour TTL for duplicate checks) apiTxnId, apiTxnRef, ewbCoreReference, externalRailReference (if available, Instapay/PESONet applicable), status (PENDING), statusDescription, and createdTimestamp. apiTxnRef is correctly constructed (Application-ID + Product-ID + Idempotency-Key + wildcard) and propagated to EWB Core Banking System, payment rails, logs, reconciliation files, and audit trails. | H17: 400 | I17: Account not found for accountNumber=200061777909 and partnerId=104234abc4 | J17: /auth/token/v1/generate | K17: /send-funds/localft/v1/initiate | L17: application/json | M17: cnfKqb1Q53rmlS8HifRZf7zvtGZOSlUQ | N17: 1VjIqTcMCJ8tIv8bMpv9l9x01ebYQd88 | O17: 104234abc4 | P17: GsG5c0UhuhXUPj4XlY8G1kcjKioiFrqI | Q17: 924fdda7-26f7-414b-ac56-9214ff796881 | R17: application/json | S17: luyoBItdetZbLfAJ3F1kvLfZgl1UAEY2 | T17: PESONET | U17: send-funds.initiate | V17: 200061777909 | W17: Lorence Ecle | X17: CUOBPHM2XXX | Y17: 001080000029 | Z17: Pao Casipe | AA17: 1 | AB17: 203.0.113.42 | AC17: 14.599500 | AD17: 120.984200 | AE17: device-abc123 | AF17: AcmePayrollApp/2.1 | AG17: Philippines | AH17: Desktop | AI17: Mandaluyong
A18: 17 | B18: =C18 -> N | C18: N | D18: TS-EB-SB-PRODUCTS-0018 | E18: TS-EB-SB-PRODUCTS-0018-Verify Initiation of Local Funds Transfer with Non-Existing Source Account via EWB to EWB | F18: Send POST Request of Send Funds via Local Fund Transfer via EWB to EWB using Not Existing Source Account | G18: DB Initial Status = RECEIVED with (full 13-digit idempotency-key stored (with 48-hour TTL for duplicate checks) apiTxnId, apiTxnRef, ewbCoreReference, externalRailReference (if available, Instapay/PESONet applicable), status(PENDING), statusDescription, and createdTimestamp. apiTxnRef is correctly constructed (Application-ID + Product-ID + Idempotency-Key + wildcard) and propagated to EWB Core Banking System, payment rails, logs, reconciliation files, and audit trails. | H18: 400 | I18: Account not found for accountNumber=200061778909 and partnerId=104234abc4 | J18: /auth/token/v1/generate | K18: /send-funds/localft/v1/initiate | L18: application/json | M18: cnfKqb1Q53rmlS8HifRZf7zvtGZOSlUQ | N18: 1VjIqTcMCJ8tIv8bMpv9l9x01ebYQd88 | O18: 104234abc4 | P18: GsG5c0UhuhXUPj4XlY8G1kcjKioiFrqI | Q18: 924fdda7-26f7-414b-ac56-9214ff796881 | R18: application/json | S18: luyoBItdetZbLfAJ3F1kvLfZgl1UAEY2 | T18: INTRABANK | U18: send-funds.initiate | V18: 200061777909 | W18: Lorence Ecle | X18: EWBCPHMMXXX | Y18: 200061812368 | Z18: Pao Casipe | AA18: 1 | AB18: 203.0.113.42 | AC18: 14.599500 | AD18: 120.984200 | AE18: device-abc123 | AF18: AcmePayrollApp/2.1 | AG18: Philippines | AH18: Desktop | AI18: Mandaluyong
A19: 18 | B19: =C19 -> N | C19: N | D19: TS-EB-SB-PRODUCTS-0019 | E19: TS-EB-SB-PRODUCTS-0019-Verify Initiation of Local Funds Transfer with Non-Existing Source Account via EWB to EWRB | F19: Send POST Request of Send Funds via Local Fund Transfer via EWB to EWRB using Not Existing Source Account | G19: DB Initial Status = RECEIVED with (full 13-digit idempotency-key stored (with 48-hour TTL for duplicate checks) apiTxnId, apiTxnRef, ewbCoreReference, externalRailReference (if available, Instapay/PESONet applicable), status(PENDING), statusDescription, and createdTimestamp. apiTxnRef is correctly constructed (Application-ID + Product-ID + Idempotency-Key + wildcard) and propagated to EWB Core Banking System, payment rails, logs, reconciliation files, and audit trails. | H19: 400 | I19: Account not found for accountNumber=200061778909 and partnerId=104234abc4 | J19: /auth/token/v1/generate | K19: /send-funds/localft/v1/initiate | L19: application/json | M19: cnfKqb1Q53rmlS8HifRZf7zvtGZOSlUQ | N19: 1VjIqTcMCJ8tIv8bMpv9l9x01ebYQd88 | O19: 104234abc4 | P19: GsG5c0UhuhXUPj4XlY8G1kcjKioiFrqI | Q19: 924fdda7-26f7-414b-ac56-9214ff796881 | R19: application/json | S19: luyoBItdetZbLfAJ3F1kvLfZgl1UAEY2 | T19: INTRABANK | U19: send-funds.initiate | V19: 200061777909 | W19: Lorence Ecle | X19: EAWRPHM2XXX | Y19: 500027172598 | Z19: Pao Casipe | AA19: 1 | AB19: 203.0.113.42 | AC19: 14.599500 | AD19: 120.984200 | AE19: device-abc123 | AF19: AcmePayrollApp/2.1 | AG19: Philippines | AH19: Desktop | AI19: Mandaluyong
A20: 19 | B20: =C20 -> N | C20: N | D20: TS-EB-SB-PRODUCTS-0020 | E20: TS-EB-SB-PRODUCTS-0020-Verify Initiation of Local Funds Transfer with Non-Existing Source Account via EWB to InstaPay | F20: Send POST Request of Send Funds via Local Fund Transfer via EWB to InstaPay using Not Existing Source Account | G20: DB Initial Status = RECEIVED with (full 13-digit idempotency-key stored (with 48-hour TTL for duplicate checks) apiTxnId, apiTxnRef, ewbCoreReference, externalRailReference (if available, Instapay/PESONet applicable), status(PENDING), statusDescription, and createdTimestamp. apiTxnRef is correctly constructed (Application-ID + Product-ID + Idempotency-Key + wildcard) and propagated to EWB Core Banking System, payment rails, logs, reconciliation files, and audit trails. | H20: 400 | I20: Account not found for accountNumber=200061778909 and partnerId=104234abc4 | J20: /auth/token/v1/generate | K20: /send-funds/localft/v1/initiate | L20: application/json | M20: cnfKqb1Q53rmlS8HifRZf7zvtGZOSlUQ | N20: 1VjIqTcMCJ8tIv8bMpv9l9x01ebYQd88 | O20: 104234abc4 | P20: GsG5c0UhuhXUPj4XlY8G1kcjKioiFrqI | Q20: 924fdda7-26f7-414b-ac56-9214ff796881 | R20: application/json | S20: luyoBItdetZbLfAJ3F1kvLfZgl1UAEY2 | T20: INSTAPAY | U20: send-funds.initiate | V20: 200061777909 | W20: Lorence Ecle | X20: CUOBPHM2XXX | Y20: 001080000029 | Z20: Pao Casipe | AA20: 1 | AB20: 203.0.113.42 | AC20: 14.599500 | AD20: 120.984200 | AE20: device-abc123 | AF20: AcmePayrollApp/2.1 | AG20: Philippines | AH20: Desktop | AI20: Mandaluyong
A21: 20 | B21: =C21 -> N | C21: N | D21: TS-EB-SB-PRODUCTS-0021 | E21: TS-EB-SB-PRODUCTS-0021-Verify Initiation of Local Funds Transfer with Non-Existing Source Account via EWB to PESONet | F21: Send POST Request of Send Funds via Local Fund Transfer via EWB to PESONet using Not Existing Source Account | G21: DB Initial Status = RECEIVED with (full 13-digit idempotency-key stored (with 48-hour TTL for duplicate checks) apiTxnId, apiTxnRef, ewbCoreReference, externalRailReference (if available, Instapay/PESONet applicable), status(PENDING), statusDescription, and createdTimestamp. apiTxnRef is correctly constructed (Application-ID + Product-ID + Idempotency-Key + wildcard) and propagated to EWB Core Banking System, payment rails, logs, reconciliation files, and audit trails. | H21: 400 | I21: Account not found for accountNumber=200061778909 and partnerId=104234abc4 | J21: /auth/token/v1/generate | K21: /send-funds/localft/v1/initiate | L21: application/json | M21: cnfKqb1Q53rmlS8HifRZf7zvtGZOSlUQ | N21: 1VjIqTcMCJ8tIv8bMpv9l9x01ebYQd88 | O21: 104234abc4 | P21: GsG5c0UhuhXUPj4XlY8G1kcjKioiFrqI | Q21: 924fdda7-26f7-414b-ac56-9214ff796881 | R21: application/json | S21: luyoBItdetZbLfAJ3F1kvLfZgl1UAEY2 | T21: PESONET | U21: send-funds.initiate | V21: 200061777909 | W21: Lorence Ecle | X21: CUOBPHM2XXX | Y21: 001080000029 | Z21: Pao Casipe | AA21: 1 | AB21: 203.0.113.42 | AC21: 14.599500 | AD21: 120.984200 | AE21: device-abc123 | AF21: AcmePayrollApp/2.1 | AG21: Philippines | AH21: Desktop | AI21: Mandaluyong
A22: 21 | B22: =C22 -> N | C22: N | D22: TS-EB-SB-PRODUCTS-0022 | E22: TS-EB-SB-PRODUCTS-0022: Send Funds via Local Fund Transfer v1.0_Initiate Local Funds Transfer API_Verify Initiation of Local Funds Transfer via EWB to EWB with Blank Source Account Number | F22: Send POST Request of Send Funds via Local Fund Transfer via EWB to EWB using Blank Source Account Number | G22: Status: FAILED responseCode: 400 Bad Request responseDescription | H22: 400 | I22: Missing required parameter: sourceAccountNumber | J22: /auth/token/v1/generate | K22: /send-funds/localft/v1/initiate | L22: application/json | M22: cnfKqb1Q53rmlS8HifRZf7zvtGZOSlUQ | N22: 1VjIqTcMCJ8tIv8bMpv9l9x01ebYQd88 | O22: 104234abc4 | P22: GsG5c0UhuhXUPj4XlY8G1kcjKioiFrqI | Q22: 924fdda7-26f7-414b-ac56-9214ff796881 | R22: application/json | T22: INTRABANK | U22: send-funds.initiate | W22: Lorence Ecle | X22: EWBCPHMMXXX | Y22: 200061812368 | Z22: Pao Casipe | AA22: 1 | AB22: 203.0.113.42 | AC22: 14.599500 | AD22: 120.984200 | AE22: device-abc123 | AF22: AcmePayrollApp/2.1 | AG22: Philippines | AH22: Desktop | AI22: Mandaluyong
A23: 22 | B23: =C23 -> N | C23: N | D23: TS-EB-SB-PRODUCTS-0023 | E23: TS-EB-SB-PRODUCTS-0005: Account Authentication via Access Token v1.0_Generate Account Access Token API_Verify API Call using malformed Account Access Token | F23: Send POST Request of Send Funds via Local Fund Transfer via EWB to EWRB using Blank Source Account Number | G23: Status: FAILED responseCode: 400 Bad Request responseDescription | H23: 400 | I23: Missing required parameter: sourceAccountNumber | J23: /auth/token/v1/generate | K23: /send-funds/localft/v1/initiate | L23: application/json | M23: cnfKqb1Q53rmlS8HifRZf7zvtGZOSlUQ | N23: 1VjIqTcMCJ8tIv8bMpv9l9x01ebYQd88 | O23: 104234abc4 | P23: GsG5c0UhuhXUPj4XlY8G1kcjKioiFrqI | Q23: 924fdda7-26f7-414b-ac56-9214ff796881 | R23: application/json | T23: INTRABANK | U23: send-funds.initiate | W23: Lorence Ecle | X23: EAWRPHM2XXX | Y23: 500027172598 | Z23: Pao Casipe | AA23: 1 | AB23: 203.0.113.42 | AC23: 14.599500 | AD23: 120.984200 | AE23: device-abc123 | AF23: AcmePayrollApp/2.1 | AG23: Philippines | AH23: Desktop | AI23: Mandaluyong
A24: 23 | B24: =C24 -> N | C24: N | D24: TS-EB-SB-PRODUCTS-0024 | E24: TS-EB-SB-PRODUCTS-0024: Send Funds via Local Fund Transfer v1.0_Initiate Local Funds Transfer API_Verify Initiation of Local Funds Transfer via EWB to Instapay with Blank Source Account Number | F24: Send POST Request of Send Funds via Local Fund Transfer via EWB to InstaPay using Blank Source Account Number | G24: Status: FAILED responseCode: 400 Bad Request responseDescription | H24: 400 | I24: Missing required parameter: sourceAccountNumber | J24: /auth/token/v1/generate | K24: /send-funds/localft/v1/initiate | L24: application/json | M24: cnfKqb1Q53rmlS8HifRZf7zvtGZOSlUQ | N24: 1VjIqTcMCJ8tIv8bMpv9l9x01ebYQd88 | O24: 104234abc4 | P24: GsG5c0UhuhXUPj4XlY8G1kcjKioiFrqI | Q24: 924fdda7-26f7-414b-ac56-9214ff796881 | R24: application/json | T24: INSTAPAY | U24: send-funds.initiate | W24: Lorence Ecle | X24: CUOBPHM2XXX | Y24: 001080000029 | Z24: Pao Casipe | AA24: 1 | AB24: 203.0.113.42 | AC24: 14.599500 | AD24: 120.984200 | AE24: device-abc123 | AF24: AcmePayrollApp/2.1 | AG24: Philippines | AH24: Desktop | AI24: Mandaluyong
A25: 24 | B25: =C25 -> N | C25: N | D25: TS-EB-SB-PRODUCTS-0025 | E25: TS-EB-SB-PRODUCTS-0025: Send Funds via Local Fund Transfer v1.0_Initiate Local Funds Transfer API_Verify Initiation of Local Funds Transfer via EWB to PESONet with Blank Source Account Number | F25: Send POST Request of Send Funds via Local Fund Transfer via EWB to PEOSNet using Blank Source Account Number | G25: Status: FAILED responseCode: 400 Bad Request responseDescription | H25: 400 | I25: Missing required parameter: sourceAccountNumber | J25: /auth/token/v1/generate | K25: /send-funds/localft/v1/initiate | L25: application/json | M25: cnfKqb1Q53rmlS8HifRZf7zvtGZOSlUQ | N25: 1VjIqTcMCJ8tIv8bMpv9l9x01ebYQd88 | O25: 104234abc4 | P25: GsG5c0UhuhXUPj4XlY8G1kcjKioiFrqI | Q25: 924fdda7-26f7-414b-ac56-9214ff796881 | R25: application/json | T25: PESONET | U25: send-funds.initiate | W25: Lorence Ecle | X25: CUOBPHM2XXX | Y25: 001080000029 | Z25: Pao Casipe | AA25: 1 | AB25: 203.0.113.42 | AC25: 14.599500 | AD25: 120.984200 | AE25: device-abc123 | AF25: AcmePayrollApp/2.1 | AG25: Philippines | AH25: Desktop | AI25: Mandaluyong
A26: 25 | B26: =C26 -> Y | C26: Y | D26: TS-EB-SB-PRODUCTS-0026 | E26: TS-EB-SB-PRODUCTS-0026: Send Funds via Local Fund Transfer v1.0_Initiate Local Funds Transfer API_Verify Initiation of Local Funds Transfer via EWB to EWB with Blank Beneficiary Account Number | F26: Send POST Request of Send Funds via Local Fund Transfer via EWB to EWB using Blank Beneficiary Account Number | G26: Status: FAILED responseCode: 400 Bad Request responseDescription | H26: 400 | I26: Missing required parameter: targetAccountNumber | J26: /auth/token/v1/generate | K26: /send-funds/localft/v1/initiate | L26: application/json | M26: cnfKqb1Q53rmlS8HifRZf7zvtGZOSlUQ | N26: 1VjIqTcMCJ8tIv8bMpv9l9x01ebYQd88 | O26: 104234abc4 | P26: GsG5c0UhuhXUPj4XlY8G1kcjKioiFrqI | Q26: 924fdda7-26f7-414b-ac56-9214ff796881 | R26: application/json | T26: INTRABANK | U26: send-funds.initiate | V26: 200061777902 | W26: Lorence Ecle | X26: EWBCPHMMXXX | Z26: Pao Casipe | AA26: 1 | AB26: 203.0.113.42 | AC26: 14.599500 | AD26: 120.984200 | AE26: device-abc123 | AF26: AcmePayrollApp/2.1 | AG26: Philippines | AH26: Desktop | AI26: Mandaluyong
A27: 26 | B27: =C27 -> Y | C27: Y | D27: TS-EB-SB-PRODUCTS-0027 | E27: TS-EB-SB-PRODUCTS-0027: Send Funds via Local Fund Transfer v1.0_Initiate Local Funds Transfer API_Verify Initiation of Local Funds Transfer via EWB to EWRB with Blank Beneficiary Account Number | F27: Send POST Request of Send Funds via Local Fund Transfer EWB to EWRB using Blank Beneficiary Account Number | G27: Status: FAILED responseCode: 400 Bad Request responseDescription | H27: 400 | I27: Missing required parameter: targetAccountNumber | J27: /auth/token/v1/generate | K27: /send-funds/localft/v1/initiate | L27: application/json | M27: cnfKqb1Q53rmlS8HifRZf7zvtGZOSlUQ | N27: 1VjIqTcMCJ8tIv8bMpv9l9x01ebYQd88 | O27: 104234abc4 | P27: GsG5c0UhuhXUPj4XlY8G1kcjKioiFrqI | Q27: 924fdda7-26f7-414b-ac56-9214ff796881 | R27: application/json | T27: INTRABANK | U27: send-funds.initiate | V27: 200061777902 | W27: Lorence Ecle | X27: EAWRPHM2XXX | Z27: Pao Casipe | AA27: 1 | AB27: 203.0.113.42 | AC27: 14.599500 | AD27: 120.984200 | AE27: device-abc123 | AF27: AcmePayrollApp/2.1 | AG27: Philippines | AH27: Desktop | AI27: Mandaluyong
A28: 27 | B28: =C28 -> Y | C28: Y | D28: TS-EB-SB-PRODUCTS-0028 | E28: TS-EB-SB-PRODUCTS-0028: Send Funds via Local Fund Transfer v1.0_Initiate Local Funds Transfer API_Verify Initiation of Local Funds Transfer via EWB to InstaPay with Blank Beneficiary Account Number | F28: Send POST Request of Send Funds via Local Fund Transfer via EWB to InstaPay using Blank Beneficiary Account Number | G28: Status: FAILED responseCode: 400 Bad Request responseDescription | H28: 400 | I28: Missing required parameter: targetAccountNumber | J28: /auth/token/v1/generate | K28: /send-funds/localft/v1/initiate | L28: application/json | M28: cnfKqb1Q53rmlS8HifRZf7zvtGZOSlUQ | N28: 1VjIqTcMCJ8tIv8bMpv9l9x01ebYQd88 | O28: 104234abc4 | P28: GsG5c0UhuhXUPj4XlY8G1kcjKioiFrqI | Q28: 924fdda7-26f7-414b-ac56-9214ff796881 | R28: application/json | T28: INSTAPAY | U28: send-funds.initiate | V28: 200061777902 | W28: Lorence Ecle | X28: CUOBPHM2XXX | Z28: Pao Casipe | AA28: 1 | AB28: 203.0.113.42 | AC28: 14.599500 | AD28: 120.984200 | AE28: device-abc123 | AF28: AcmePayrollApp/2.1 | AG28: Philippines | AH28: Desktop | AI28: Mandaluyong
A29: 28 | B29: =C29 -> Y | C29: Y | D29: TS-EB-SB-PRODUCTS-0029 | E29: TS-EB-SB-PRODUCTS-0029: Send Funds via Local Fund Transfer v1.0_Initiate Local Funds Transfer API_Verify Initiation of Local Funds Transfervia EWB to PESONet with Blank Beneficiary Account Number | F29: Send POST Request of Send Funds via Local Fund Transfer via EWB to PESONet using Blank Beneficiary Account Number | G29: Status: FAILED responseCode: 400 Bad Request responseDescription | H29: 400 | I29: Missing required parameter: targetAccountNumber | J29: /auth/token/v1/generate | K29: /send-funds/localft/v1/initiate | L29: application/json | M29: cnfKqb1Q53rmlS8HifRZf7zvtGZOSlUQ | N29: 1VjIqTcMCJ8tIv8bMpv9l9x01ebYQd88 | O29: 104234abc4 | P29: GsG5c0UhuhXUPj4XlY8G1kcjKioiFrqI | Q29: 924fdda7-26f7-414b-ac56-9214ff796881 | R29: application/json | T29: PESONET | U29: send-funds.initiate | V29: 200061777902 | W29: Lorence Ecle | X29: CUOBPHM2XXX | Z29: Pao Casipe | AA29: 1 | AB29: 203.0.113.42 | AC29: 14.599500 | AD29: 120.984200 | AE29: device-abc123 | AF29: AcmePayrollApp/2.1 | AG29: Philippines | AH29: Desktop | AI29: Mandaluyong
A30: 29 | B30: =C30 -> N | C30: N | D30: TS-EB-SB-PRODUCTS-0030 | E30: TS-EB-SB-PRODUCTS-0030: Send Funds via Local Fund Transfer v1.0_Initiate Local Funds Transfer API_Verify Initiation of Local Funds Transfer via EWB to EWB with Blank Both Source Account and Beneficiary Account Number | F30: Send POST Request of Send Funds via Local Fund Transfer via EWB to EWB using Blank Source Account and Beneficiary Account Number | G30: Status: FAILED responseCode: 400 Bad Request responseDescription | H30: 400 | I30: Missing required parameter: sourceAccountNumber | J30: /auth/token/v1/generate | K30: /send-funds/localft/v1/initiate | L30: application/json | M30: cnfKqb1Q53rmlS8HifRZf7zvtGZOSlUQ | N30: 1VjIqTcMCJ8tIv8bMpv9l9x01ebYQd88 | O30: 104234abc4 | P30: GsG5c0UhuhXUPj4XlY8G1kcjKioiFrqI | Q30: 924fdda7-26f7-414b-ac56-9214ff796881 | R30: application/json | T30: INTRABANK | U30: send-funds.initiate | W30: Lorence Ecle | X30: EWBCPHMMXXX | Z30: Pao Casipe | AA30: 1 | AB30: 203.0.113.42 | AC30: 14.599500 | AD30: 120.984200 | AE30: device-abc123 | AF30: AcmePayrollApp/2.1 | AG30: Philippines | AH30: Desktop | AI30: Mandaluyong
A31: 30 | B31: =C31 -> N | C31: N | D31: TS-EB-SB-PRODUCTS-0031 | E31: TS-EB-SB-PRODUCTS-0031: Send Funds via Local Fund Transfer v1.0_Initiate Local Funds Transfer API_Verify Initiation of Local Funds Transfer via EWB to EWRB with Blank Both Source Account and Beneficiary Account Number | F31: Send POST Request of Send Funds via Local Fund Transfer via EWB to EWRB using Blank Source Account and Beneficiary Account Number | G31: Status: FAILED responseCode: 400 Bad Request responseDescription | H31: 400 | I31: Missing required parameter: sourceAccountNumber | J31: /auth/token/v1/generate | K31: /send-funds/localft/v1/initiate | L31: application/json | M31: cnfKqb1Q53rmlS8HifRZf7zvtGZOSlUQ | N31: 1VjIqTcMCJ8tIv8bMpv9l9x01ebYQd88 | O31: 104234abc4 | P31: GsG5c0UhuhXUPj4XlY8G1kcjKioiFrqI | Q31: 924fdda7-26f7-414b-ac56-9214ff796881 | R31: application/json | T31: INTRABANK | U31: send-funds.initiate | W31: Lorence Ecle | X31: EAWRPHM2XXX | Z31: Pao Casipe | AA31: 1 | AB31: 203.0.113.42 | AC31: 14.599500 | AD31: 120.984200 | AE31: device-abc123 | AF31: AcmePayrollApp/2.1 | AG31: Philippines | AH31: Desktop | AI31: Mandaluyong
A32: 31 | B32: =C32 -> N | C32: N | D32: TS-EB-SB-PRODUCTS-0032 | E32: TS-EB-SB-PRODUCTS-0032: Send Funds via Local Fund Transfer v1.0_Initiate Local Funds Transfer API_Verify Initiation of Local Funds Transfer via EWB to InstaPay with Blank Both Source Account and Beneficiary Account Number | F32: Send POST Request of Send Funds via Local Fund Transfer via EWB to InstaPay using Blank Source Account and Beneficiary Account Number | G32: Status: FAILED responseCode: 400 Bad Request responseDescription | H32: 400 | I32: Missing required parameter: sourceAccountNumber | J32: /auth/token/v1/generate | K32: /send-funds/localft/v1/initiate | L32: application/json | M32: cnfKqb1Q53rmlS8HifRZf7zvtGZOSlUQ | N32: 1VjIqTcMCJ8tIv8bMpv9l9x01ebYQd88 | O32: 104234abc4 | P32: GsG5c0UhuhXUPj4XlY8G1kcjKioiFrqI | Q32: 924fdda7-26f7-414b-ac56-9214ff796881 | R32: application/json | T32: INSTAPAY | U32: send-funds.initiate | W32: Lorence Ecle | X32: CUOBPHM2XXX | Z32: Pao Casipe | AA32: 1 | AB32: 203.0.113.42 | AC32: 14.599500 | AD32: 120.984200 | AE32: device-abc123 | AF32: AcmePayrollApp/2.1 | AG32: Philippines | AH32: Desktop | AI32: Mandaluyong
A33: 32 | B33: =C33 -> N | C33: N | D33: TS-EB-SB-PRODUCTS-0033 | E33: TS-EB-SB-PRODUCTS-0033: Send Funds via Local Fund Transfer v1.0_Initiate Local Funds Transfer API_Verify Initiation of Local Funds Transfer via EWB to PESONet with Blank Both Source Account and Beneficiary Account Number | F33: Send POST Request of Send Funds via Local Fund Transfer via EWB to PESONet using Blank Source Account and Beneficiary Account Number | G33: Status: FAILED responseCode: 400 Bad Request responseDescription | H33: 400 | I33: Missing required parameter: sourceAccountNumber | J33: /auth/token/v1/generate | K33: /send-funds/localft/v1/initiate | L33: application/json | M33: cnfKqb1Q53rmlS8HifRZf7zvtGZOSlUQ | N33: 1VjIqTcMCJ8tIv8bMpv9l9x01ebYQd88 | O33: 104234abc4 | P33: GsG5c0UhuhXUPj4XlY8G1kcjKioiFrqI | Q33: 924fdda7-26f7-414b-ac56-9214ff796881 | R33: application/json | T33: PESONET | U33: send-funds.initiate | W33: Lorence Ecle | X33: CUOBPHM2XXX | Z33: Pao Casipe | AA33: 1 | AB33: 203.0.113.42 | AC33: 14.599500 | AD33: 120.984200 | AE33: device-abc123 | AF33: AcmePayrollApp/2.1 | AG33: Philippines | AH33: Desktop | AI33: Mandaluyong
A34: 33 | B34: =C34 -> N | C34: N | D34: TS-EB-SB-PRODUCTS-0034 | E34: TS-EB-SB-PRODUCTS-0034-Verify Initiation of Local Funds Transfer via EWB to EWB with Source Account with Exceeding to 20 characters | F34: Send POST Request of Send Funds via Local Fund Transfer via EWB to EWB using Source Account Number with Exceeding to 20 characters | G34: Status: FAILED responseCode: 400 Bad Request responseDescription | H34: 400 | I34: Account not found for accountNumber=2000617779028765923451 and partnerId=104234abc4 | J34: /auth/token/v1/generate | K34: /send-funds/localft/v1/initiate | L34: application/json | M34: cnfKqb1Q53rmlS8HifRZf7zvtGZOSlUQ | N34: 1VjIqTcMCJ8tIv8bMpv9l9x01ebYQd88 | O34: 104234abc4 | P34: GsG5c0UhuhXUPj4XlY8G1kcjKioiFrqI | Q34: 924fdda7-26f7-414b-ac56-9214ff796881 | R34: application/json | T34: INTRABANK | U34: send-funds.initiate | V34: 2000617779028765923451 | W34: Lorence Ecle | X34: EWBCPHMMXXX | Y34: 200061812368 | Z34: Pao Casipe | AA34: 1 | AB34: 203.0.113.42 | AC34: 14.599500 | AD34: 120.984200 | AE34: device-abc123 | AF34: AcmePayrollApp/2.1 | AG34: Philippines | AH34: Desktop | AI34: Mandaluyong
A35: 34 | B35: =C35 -> N | C35: N | D35: TS-EB-SB-PRODUCTS-0035 | E35: TS-EB-SB-PRODUCTS-0035-Verify Initiation of Local Funds Transfer via EWB to EWRB with Source Account with Exceeding to 20 characters | F35: Send POST Request of Send Funds via Local Fund Transfer via EWB to EWRB using Source Account Number with Exceeding to 20 characters | G35: Status: FAILED responseCode: 400 Bad Request responseDescription | H35: 400 | I35: Account not found for accountNumber=2000617779028765923451 and partnerId=104234abc4 | J35: /auth/token/v1/generate | K35: /send-funds/localft/v1/initiate | L35: application/json | M35: cnfKqb1Q53rmlS8HifRZf7zvtGZOSlUQ | N35: 1VjIqTcMCJ8tIv8bMpv9l9x01ebYQd88 | O35: 104234abc4 | P35: GsG5c0UhuhXUPj4XlY8G1kcjKioiFrqI | Q35: 924fdda7-26f7-414b-ac56-9214ff796881 | R35: application/json | T35: INTRABANK | U35: send-funds.initiate | V35: 2000617779028765923451 | W35: Lorence Ecle | X35: EAWRPHM2XXX | Y35: 500027172598 | Z35: Pao Casipe | AA35: 1 | AB35: 203.0.113.42 | AC35: 14.599500 | AD35: 120.984200 | AE35: device-abc123 | AF35: AcmePayrollApp/2.1 | AG35: Philippines | AH35: Desktop | AI35: Mandaluyong
A36: 35 | B36: =C36 -> N | C36: N | D36: TS-EB-SB-PRODUCTS-0036 | E36: TS-EB-SB-PRODUCTS-0036-Verify Initiation of Local Funds Transfer via EWB to InstaPaywith Source Account with Exceeding to 20 characters | F36: Send POST Request of Send Funds via Local Fund Transfer via EWB to Instapay using Source Account Number with Exceeding to 20 characters | G36: Status: FAILED responseCode: 400 Bad Request responseDescription | H36: 400 | I36: Account not found for accountNumber=2000617779028765923451 and partnerId=104234abc4 | J36: /auth/token/v1/generate | K36: /send-funds/localft/v1/initiate | L36: application/json | M36: cnfKqb1Q53rmlS8HifRZf7zvtGZOSlUQ | N36: 1VjIqTcMCJ8tIv8bMpv9l9x01ebYQd88 | O36: 104234abc4 | P36: GsG5c0UhuhXUPj4XlY8G1kcjKioiFrqI | Q36: 924fdda7-26f7-414b-ac56-9214ff796881 | R36: application/json | T36: INSTAPAY | U36: send-funds.initiate | V36: 2000617779028765923451 | W36: Lorence Ecle | X36: CUOBPHM2XXX | Y36: 001080000029 | Z36: Pao Casipe | AA36: 1 | AB36: 203.0.113.42 | AC36: 14.599500 | AD36: 120.984200 | AE36: device-abc123 | AF36: AcmePayrollApp/2.1 | AG36: Philippines | AH36: Desktop | AI36: Mandaluyong
A37: 36 | B37: =C37 -> N | C37: N | D37: TS-EB-SB-PRODUCTS-0037 | E37: TS-EB-SB-PRODUCTS-0037-Verify Initiation of Local Funds Transfer via EWB to PESONet with Source Account with Exceeding to 20 characters | F37: Send POST Request of Send Funds via Local Fund Transfer via EWB to PESONet using Source Account Number with Exceeding to 20 characters | G37: Status: FAILED responseCode: 400 Bad Request responseDescription | H37: 400 | I37: Account not found for accountNumber=2000617779028765923451 and partnerId=104234abc4 | J37: /auth/token/v1/generate | K37: /send-funds/localft/v1/initiate | L37: application/json | M37: cnfKqb1Q53rmlS8HifRZf7zvtGZOSlUQ | N37: 1VjIqTcMCJ8tIv8bMpv9l9x01ebYQd88 | O37: 104234abc4 | P37: GsG5c0UhuhXUPj4XlY8G1kcjKioiFrqI | Q37: 924fdda7-26f7-414b-ac56-9214ff796881 | R37: application/json | T37: PESONET | U37: send-funds.initiate | V37: 2000617779028765923451 | W37: Lorence Ecle | X37: CUOBPHM2XXX | Y37: 001080000029 | Z37: Pao Casipe | AA37: 1 | AB37: 203.0.113.42 | AC37: 14.599500 | AD37: 120.984200 | AE37: device-abc123 | AF37: AcmePayrollApp/2.1 | AG37: Philippines | AH37: Desktop | AI37: Mandaluyong
A38: 37 | B38: =C38 -> N | C38: N | D38: TS-EB-SB-PRODUCTS-0038 | E38: TS-EB-SB-PRODUCTS-0038-Verify Initiation of Local Funds Transfer via EWB to EWB with Source Account Fewer than 10 characters | F38: Send POST Request of Send Funds via Local Fund Transfer via EWB to EWB using Source Account Number Fewer than 10 characters | G38: Status: FAILED responseCode: 400 Bad Request responseDescription | H38: 400 | I38: Account not found for accountNumber=200 and partnerId=104234abc4 | J38: /auth/token/v1/generate | K38: /send-funds/localft/v1/initiate | L38: application/json | M38: cnfKqb1Q53rmlS8HifRZf7zvtGZOSlUQ | N38: 1VjIqTcMCJ8tIv8bMpv9l9x01ebYQd88 | O38: 104234abc4 | P38: GsG5c0UhuhXUPj4XlY8G1kcjKioiFrqI | Q38: 924fdda7-26f7-414b-ac56-9214ff796881 | R38: application/json | T38: INTRABANK | U38: send-funds.initiate | V38: 200 | W38: Lorence Ecle | X38: EWBCPHMMXXX | Y38: 200061812368 | Z38: Pao Casipe | AA38: 1 | AB38: 203.0.113.42 | AC38: 14.599500 | AD38: 120.984200 | AE38: device-abc123 | AF38: AcmePayrollApp/2.1 | AG38: Philippines | AH38: Desktop | AI38: Mandaluyong
A39: 38 | B39: =C39 -> N | C39: N | D39: TS-EB-SB-PRODUCTS-0039 | E39: TS-EB-SB-PRODUCTS-0039-Verify Initiation of Local Funds Transfer via EWB to EWRB with Source Account Fewer than 10 characters | F39: Send POST Request of Send Funds via Local Fund Transfer via EWB to EWRB using Source Account Number Fewer than 10 characters | G39: Status: FAILED responseCode: 400 Bad Request responseDescription | H39: 400 | I39: Account not found for accountNumber=200 and partnerId=104234abc4 | J39: /auth/token/v1/generate | K39: /send-funds/localft/v1/initiate | L39: application/json | M39: cnfKqb1Q53rmlS8HifRZf7zvtGZOSlUQ | N39: 1VjIqTcMCJ8tIv8bMpv9l9x01ebYQd88 | O39: 104234abc4 | P39: GsG5c0UhuhXUPj4XlY8G1kcjKioiFrqI | Q39: 924fdda7-26f7-414b-ac56-9214ff796881 | R39: application/json | T39: INTRABANK | U39: send-funds.initiate | V39: 200 | W39: Lorence Ecle | X39: EAWRPHM2XXX | Y39: 500027172598 | Z39: Pao Casipe | AA39: 1 | AB39: 203.0.113.42 | AC39: 14.599500 | AD39: 120.984200 | AE39: device-abc123 | AF39: AcmePayrollApp/2.1 | AG39: Philippines | AH39: Desktop | AI39: Mandaluyong
A40: 39 | B40: =C40 -> N | C40: N | D40: TS-EB-SB-PRODUCTS-0040 | E40: TS-EB-SB-PRODUCTS-0040-Verify Initiation of Local Funds Transfer via EWB to InstaPay with Source Account Fewer than 10 characters | F40: Send POST Request of Send Funds via Local Fund Transfer via EWB to InstaPay using Source Account Number Fewer than 10 characters | G40: Status: FAILED responseCode: 400 Bad Request responseDescription | H40: 400 | I40: Account not found for accountNumber=200 and partnerId=104234abc4 | J40: /auth/token/v1/generate | K40: /send-funds/localft/v1/initiate | L40: application/json | M40: cnfKqb1Q53rmlS8HifRZf7zvtGZOSlUQ | N40: 1VjIqTcMCJ8tIv8bMpv9l9x01ebYQd88 | O40: 104234abc4 | P40: GsG5c0UhuhXUPj4XlY8G1kcjKioiFrqI | Q40: 924fdda7-26f7-414b-ac56-9214ff796881 | R40: application/json | T40: INSTAPAY | U40: send-funds.initiate | V40: 200 | W40: Lorence Ecle | X40: CUOBPHM2XXX | Y40: 001080000029 | Z40: Pao Casipe | AA40: 1 | AB40: 203.0.113.42 | AC40: 14.599500 | AD40: 120.984200 | AE40: device-abc123 | AF40: AcmePayrollApp/2.1 | AG40: Philippines | AH40: Desktop | AI40: Mandaluyong
A41: 40 | B41: =C41 -> N | C41: N | D41: TS-EB-SB-PRODUCTS-0041 | E41: TS-EB-SB-PRODUCTS-0041-Verify Initiation of Local Funds Transfer via EWB to PESONet with Source Account Fewer than 10 characters | F41: Send POST Request of Send Funds via Local Fund Transfer via EWB to PESONet using Source Account Number Fewer than 10 characters | G41: Status: FAILED responseCode: 400 Bad Request responseDescription | H41: 400 | I41: Account not found for accountNumber=200 and partnerId=104234abc4 | J41: /auth/token/v1/generate | K41: /send-funds/localft/v1/initiate | L41: application/json | M41: cnfKqb1Q53rmlS8HifRZf7zvtGZOSlUQ | N41: 1VjIqTcMCJ8tIv8bMpv9l9x01ebYQd88 | O41: 104234abc4 | P41: GsG5c0UhuhXUPj4XlY8G1kcjKioiFrqI | Q41: 924fdda7-26f7-414b-ac56-9214ff796881 | R41: application/json | T41: PESONET | U41: send-funds.initiate | V41: 200 | W41: Lorence Ecle | X41: CUOBPHM2XXX | Y41: 001080000029 | Z41: Pao Casipe | AA41: 1 | AB41: 203.0.113.42 | AC41: 14.599500 | AD41: 120.984200 | AE41: device-abc123 | AF41: AcmePayrollApp/2.1 | AG41: Philippines | AH41: Desktop | AI41: Mandaluyong
A42: 41 | B42: =C42 -> Y | C42: Y | D42: TS-EB-SB-PRODUCTS-0042 | E42: TS-EB-SB-PRODUCTS-0042-Verify Initiation of Local Funds Transfer via EWB to EWB with Source Account not linked to provided access token | F42: Send POST Request of Send Funds via Local Fund Transfer via EWB to EWB using Source Account not linked to the provided to access token | G42: Status: FAILED responseCode: 400 Bad Request responseDescription | H42: 403 | I42: The access token is not valid for this environment | J42: /auth/token/v1/generate | K42: /send-funds/localft/v1/initiate | L42: application/json | M42: cnfKqb1Q53rmlS8HifRZf7zvtGZOSlUQ | N42: 1VjIqTcMCJ8tIv8bMpv9l9x01ebYQd88 | O42: 104234abc4 | P42: GsG5c0UhuhXUPj4XlY8G1kcjKioiFrqI | Q42: 924fdda7-26f7-414b-ac56-9214ff796881 | R42: application/json | S42: 8TUw0J7mzxBXHFnFtx3Q3UC2Dcb7wB9v | T42: INTRABANK | U42: send-funds.initiate | V42: 200061777902 | W42: Lorence Ecle | X42: EWBCPHMMXXX | Y42: 200061812368 | Z42: Pao Casipe | AA42: 1 | AB42: 203.0.113.42 | AC42: 14.599500 | AD42: 120.984200 | AE42: device-abc123 | AF42: AcmePayrollApp/2.1 | AG42: Philippines | AH42: Desktop | AI42: Mandaluyong
A43: 42 | B43: =C43 -> Y | C43: Y | D43: TS-EB-SB-PRODUCTS-0043 | E43: TS-EB-SB-PRODUCTS-0043-Verify Initiation of Local Funds Transfer via EWB to EWRB with Source Account not linked to provided access token | F43: Send POST Request of Send Funds via Local Fund Transfer via EWB to EWRB using Source Account not linked to the provided to access token | G43: Status: FAILED responseCode: 400 Bad Request responseDescription | H43: 403 | I43: The access token is not valid for this environment | J43: /auth/token/v1/generate | K43: /send-funds/localft/v1/initiate | L43: application/json | M43: cnfKqb1Q53rmlS8HifRZf7zvtGZOSlUQ | N43: 1VjIqTcMCJ8tIv8bMpv9l9x01ebYQd88 | O43: 104234abc4 | P43: GsG5c0UhuhXUPj4XlY8G1kcjKioiFrqI | Q43: 924fdda7-26f7-414b-ac56-9214ff796881 | R43: application/json | S43: 8TUw0J7mzxBXHFnFtx3Q3UC2Dcb7wB9v | T43: INTRABANK | U43: send-funds.initiate | V43: 200061777902 | W43: Lorence Ecle | X43: EAWRPHM2XXX | Y43: 500027172598 | Z43: Pao Casipe | AA43: 1 | AB43: 203.0.113.42 | AC43: 14.599500 | AD43: 120.984200 | AE43: device-abc123 | AF43: AcmePayrollApp/2.1 | AG43: Philippines | AH43: Desktop | AI43: Mandaluyong
A44: 43 | B44: =C44 -> Y | C44: Y | D44: TS-EB-SB-PRODUCTS-0044 | E44: TS-EB-SB-PRODUCTS-0044-Verify Initiation of Local Funds Transfer via EWB to InstaPay with Source Account not linked to provided access token | F44: Send POST Request of Send Funds via Local Fund Transfer via EWB to InstaPay using Source Account not linked to the provided to access token | G44: Status: FAILED responseCode: 400 Bad Request responseDescription | H44: 403 | I44: The access token is not valid for this environment | J44: /auth/token/v1/generate | K44: /send-funds/localft/v1/initiate | L44: application/json | M44: cnfKqb1Q53rmlS8HifRZf7zvtGZOSlUQ | N44: 1VjIqTcMCJ8tIv8bMpv9l9x01ebYQd88 | O44: 104234abc4 | P44: GsG5c0UhuhXUPj4XlY8G1kcjKioiFrqI | Q44: 924fdda7-26f7-414b-ac56-9214ff796881 | R44: application/json | S44: 8TUw0J7mzxBXHFnFtx3Q3UC2Dcb7wB9v | T44: INSTAPAY | U44: send-funds.initiate | V44: 200061777902 | W44: Lorence Ecle | X44: CUOBPHM2XXX | Y44: 001080000029 | Z44: Pao Casipe | AA44: 1 | AB44: 203.0.113.42 | AC44: 14.599500 | AD44: 120.984200 | AE44: device-abc123 | AF44: AcmePayrollApp/2.1 | AG44: Philippines | AH44: Desktop | AI44: Mandaluyong
A45: 44 | B45: =C45 -> Y | C45: Y | D45: TS-EB-SB-PRODUCTS-0045 | E45: TS-EB-SB-PRODUCTS-0045-Verify Initiation of Local Funds Transfer via EWB to PESONet with Source Account not linked to provided access token | F45: Send POST Request of Send Funds via Local Fund Transfer via EWB to PESONet using Source Account not linked to the provided to access token | G45: Status: FAILED responseCode: 400 Bad Request responseDescription | H45: 403 | I45: The access token is not valid for this environment | J45: /auth/token/v1/generate | K45: /send-funds/localft/v1/initiate | L45: application/json | M45: cnfKqb1Q53rmlS8HifRZf7zvtGZOSlUQ | N45: 1VjIqTcMCJ8tIv8bMpv9l9x01ebYQd88 | O45: 104234abc4 | P45: GsG5c0UhuhXUPj4XlY8G1kcjKioiFrqI | Q45: 924fdda7-26f7-414b-ac56-9214ff796881 | R45: application/json | S45: 8TUw0J7mzxBXHFnFtx3Q3UC2Dcb7wB9v | T45: PESONET | U45: send-funds.initiate | V45: 200061777902 | W45: Lorence Ecle | X45: CUOBPHM2XXX | Y45: 001080000029 | Z45: Pao Casipe | AA45: 1 | AB45: 203.0.113.42 | AC45: 14.599500 | AD45: 120.984200 | AE45: device-abc123 | AF45: AcmePayrollApp/2.1 | AG45: Philippines | AH45: Desktop | AI45: Mandaluyong
A46: 45 | B46: =C46 -> N | C46: N | D46: TS-EB-SB-PRODUCTS-0046 | E46: TS-EB-SB-PRODUCTS-0046-Verify Initiation of Local Funds Transfer via EWB to EWB with FDS Receiver Beneficiary Account | F46: Send POST Request of Send Funds via Local Fund Transfer via EWB to EWB using FDS Receiver Beneficiary Account | G46: DB Initial Status = RECEIVED with (full 13-digit idempotency-key stored (with 48-hour TTL for duplicate checks) apiTxnId, apiTxnRef, ewbCoreReference, externalRailReference (if available, Instapay/PESONet applicable), status(PENDING), statusDescription, and createdTimestamp. apiTxnRef is correctly constructed (Application-ID + Product-ID + Idempotency-Key + wildcard) and propagated to EWB Core Banking System, payment rails, logs, reconciliation files, and audit trails. | H46: 200 | J46: /auth/token/v1/generate | K46: /send-funds/localft/v1/initiate | O46: 1042346967 | P46: GsG5c0UhuhXUPj4XlY8G1kcjKioiFrqI | Q46: 7902f971-6452-469f-85c5-b0d8379edf39 | R46: application/json | T46: INTRABANK | V46: 200061812538 | W46: Lorence Ecle | X46: EWBCPHMMXXX | Y46: 200061812368 | Z46: Pao Casipe | AA46: 1 | AB46: 203.0.113.42 | AC46: 14.599500 | AD46: 120.984200 | AE46: device-abc123 | AF46: AcmePayrollApp/2.1 | AG46: Philippines | AH46: Desktop | AI46: Mandaluyong
A47: 46 | B47: =C47 -> N | C47: N | D47: TS-EB-SB-PRODUCTS-0047 | E47: TS-EB-SB-PRODUCTS-0047-Verify Initiation of Local Funds Transfer via EWB to EWRB with FDS Receiver Beneficiary Account | F47: Send POST Request of Send Funds via Local Fund Transfer via EWB to EWrB using FDS Receiver Beneficiary Account | G47: DB Initial Status = RECEIVED with (full 13-digit idempotency-key stored (with 48-hour TTL for duplicate checks) apiTxnId, apiTxnRef, ewbCoreReference, externalRailReference (if available, Instapay/PESONet applicable), status(PENDING), statusDescription, and createdTimestamp. apiTxnRef is correctly constructed (Application-ID + Product-ID + Idempotency-Key + wildcard) and propagated to EWB Core Banking System, payment rails, logs, reconciliation files, and audit trails. | H47: 200 | J47: /auth/token/v1/generate | K47: /send-funds/localft/v1/initiate | O47: 1042346968 | P47: GsG5c0UhuhXUPj4XlY8G1kcjKioiFrqI | Q47: 7902f971-6452-469f-85c5-b0d8379edf39 | R47: application/json | T47: INTRABANK | V47: 200061812538 | W47: Lorence Ecle | X47: EAWRPHM2XXX | Y47: 500027172598 | Z47: Pao Casipe | AA47: 1 | AB47: 203.0.113.42 | AC47: 14.599500 | AD47: 120.984200 | AE47: device-abc123 | AF47: AcmePayrollApp/2.1 | AG47: Philippines | AH47: Desktop | AI47: Mandaluyong
A48: 47 | B48: =C48 -> N | C48: N | D48: TS-EB-SB-PRODUCTS-0048 | E48: TS-EB-SB-PRODUCTS-0048-Verify Initiation of Local Funds Transfer via EWB to InstaPay with FDS Receiver Beneficiary Account | F48: Send POST Request of Send Funds via Local Fund Transfer via EWB to InstaPay using FDS Receiver Beneficiary Account | G48: DB Initial Status = RECEIVED with (full 13-digit idempotency-key stored (with 48-hour TTL for duplicate checks) apiTxnId, apiTxnRef, ewbCoreReference, externalRailReference (if available, Instapay/PESONet applicable), status(PENDING), statusDescription, and createdTimestamp. apiTxnRef is correctly constructed (Application-ID + Product-ID + Idempotency-Key + wildcard) and propagated to EWB Core Banking System, payment rails, logs, reconciliation files, and audit trails. | H48: 200 | J48: /auth/token/v1/generate | K48: /send-funds/localft/v1/initiate | O48: 1042346969 | P48: GsG5c0UhuhXUPj4XlY8G1kcjKioiFrqI | Q48: 7902f971-6452-469f-85c5-b0d8379edf39 | R48: application/json | T48: INSTAPAY | V48: 200061812538 | W48: Lorence Ecle | X48: CUOBPHM2XXX | Y48: 001080000029 | Z48: Pao Casipe | AA48: 1 | AB48: 203.0.113.42 | AC48: 14.599500 | AD48: 120.984200 | AE48: device-abc123 | AF48: AcmePayrollApp/2.1 | AG48: Philippines | AH48: Desktop | AI48: Mandaluyong
A49: 48 | B49: =C49 -> N | C49: N | D49: TS-EB-SB-PRODUCTS-0049 | E49: TS-EB-SB-PRODUCTS-0049-Verify Initiation of Local Funds Transfer via EWB to PESONet with FDS Receiver Beneficiary Account | F49: Send POST Request of Send Funds via Local Fund Transfer via EWB to PESONet using FDS Receiver Beneficiary Account | G49: Success Status 200 OK DB Initial Status = RECEIVED with (full 13-digit idempotency-key stored (with 48-hour TTL for duplicate checks) apiTxnId, apiTxnRef, ewbCoreReference, externalRailReference (if available, Instapay/PESONet applicable), status(PENDING), statusDescription, and createdTimestamp. apiTxnRef is correctly constructed (Application-ID + Product-ID + Idempotency-Key + wildcard) and propagated to EWB Core Banking System, payment rails, logs, reconciliation files, and audit trails. | H49: 200 | J49: /auth/token/v1/generate | K49: /send-funds/localft/v1/initiate | O49: 1042346970 | P49: GsG5c0UhuhXUPj4XlY8G1kcjKioiFrqI | Q49: 7902f971-6452-469f-85c5-b0d8379edf39 | R49: application/json | T49: PESONET | V49: 200061812538 | W49: Lorence Ecle | X49: CUOBPHM2XXX | Y49: 001080000029 | Z49: Pao Casipe | AA49: 1 | AB49: 203.0.113.42 | AC49: 14.599500 | AD49: 120.984200 | AE49: device-abc123 | AF49: AcmePayrollApp/2.1 | AG49: Philippines | AH49: Desktop | AI49: Mandaluyong
A50: 49 | B50: =C50 -> N | C50: N | D50: TS-EB-SB-PRODUCTS-0050 | E50: TS-EB-SB-PRODUCTS-0050-Validate that all required body parameters are present and correctly formatted as per API specification via EWB to EWB | F50: Send POST Request of Send Funds via Local Fund Transfer via EWB to EWB using proper Required Body Parameters | G50: API returns HTTP 200 OK | H50: 200 | J50: /auth/token/v1/generate | K50: /send-funds/localft/v1/initiate | O50: 1042346971 | P50: GsG5c0UhuhXUPj4XlY8G1kcjKioiFrqI | Q50: 7902f971-6452-469f-85c5-b0d8379edf39 | R50: application/json | T50: INTRABANK | V50: 200061777902 | W50: Lorence Ecle | X50: EWBCPHMMXXX | Y50: 200061812368 | Z50: Pao Casipe | AA50: 1 | AB50: 203.0.113.42 | AC50: 14.599500 | AD50: 120.984200 | AE50: device-abc123 | AF50: AcmePayrollApp/2.1 | AG50: Philippines | AH50: Desktop | AI50: Mandaluyong
A51: 50 | B51: =C51 -> N | C51: N | D51: TS-EB-SB-PRODUCTS-0051 | E51: TS-EB-SB-PRODUCTS-0051-Validate that all required body parameters are present and correctly formatted as per API specification via EWB to EWRB | F51: Send POST Request of Send Funds via Local Fund Transfer via EWB to EWRB using proper Required Body Parameters | G51: API returns HTTP 200 OK | H51: 200 | J51: /auth/token/v1/generate | K51: /send-funds/localft/v1/initiate | O51: 1042346972 | P51: GsG5c0UhuhXUPj4XlY8G1kcjKioiFrqI | Q51: 7902f971-6452-469f-85c5-b0d8379edf39 | R51: application/json | T51: INTRABANK | V51: 200061777902 | W51: Lorence Ecle | X51: EAWRPHM2XXX | Y51: 500027172598 | Z51: Pao Casipe | AA51: 1 | AB51: 203.0.113.42 | AC51: 14.599500 | AD51: 120.984200 | AE51: device-abc123 | AF51: AcmePayrollApp/2.1 | AG51: Philippines | AH51: Desktop | AI51: Mandaluyong
A52: 51 | B52: =C52 -> N | C52: N | D52: TS-EB-SB-PRODUCTS-0052 | E52: TS-EB-SB-PRODUCTS-0052-Validate that all required body parameters are present and correctly formatted as per API specification via EWB to InstaPay | F52: Send POST Request of Send Funds via Local Fund Transfer via EWB to InstaPay using proper Required Body Parameters | G52: API returns HTTP 200 OK | H52: 200 | J52: /auth/token/v1/generate | K52: /send-funds/localft/v1/initiate | O52: 1042346973 | P52: GsG5c0UhuhXUPj4XlY8G1kcjKioiFrqI | Q52: 7902f971-6452-469f-85c5-b0d8379edf39 | R52: application/json | T52: INSTAPAY | V52: 200061777902 | W52: Lorence Ecle | X52: CUOBPHM2XXX | Y52: 001080000029 | Z52: Pao Casipe | AA52: 1 | AB52: 203.0.113.42 | AC52: 14.599500 | AD52: 120.984200 | AE52: device-abc123 | AF52: AcmePayrollApp/2.1 | AG52: Philippines | AH52: Desktop | AI52: Mandaluyong
A53: 52 | B53: =C53 -> N | C53: N | D53: TS-EB-SB-PRODUCTS-0053 | E53: TS-EB-SB-PRODUCTS-0053-Validate that all required body parameters are present and correctly formatted as per API specification via EWB to PESONet | F53: Send POST Request of Send Funds via Local Fund Transfer via EWB to PESONet using proper Required Body Parameters | G53: API returns HTTP 200 OK | H53: 200 | J53: /auth/token/v1/generate | K53: /send-funds/localft/v1/initiate | O53: 1042346974 | P53: GsG5c0UhuhXUPj4XlY8G1kcjKioiFrqI | Q53: 7902f971-6452-469f-85c5-b0d8379edf39 | R53: application/json | T53: PESONET | V53: 200061777902 | W53: Lorence Ecle | X53: CUOBPHM2XXX | Y53: 001080000029 | Z53: Pao Casipe | AA53: 1 | AB53: 203.0.113.42 | AC53: 14.599500 | AD53: 120.984200 | AE53: device-abc123 | AF53: AcmePayrollApp/2.1 | AG53: Philippines | AH53: Desktop | AI53: Mandaluyong
A54: 53 | B54: =C54 -> N | C54: N | D54: TS-EB-SB-PRODUCTS-0054 | E54: TS-EB-SB-PRODUCTS-0054-Verify if required body parameters validation/notes are enforced as per API specification via EWB to EWB upon using invalid values | F54: Send POST Request of Send Funds via Local Fund Transfer via EWB to EWB using invalid values on Required Body Parameters | G54: Status: FAILED responseCode: 400 Bad Request responseDescription | H54: 400 | J54: /auth/token/v1/generate | K54: /send-funds/localft/v1/initiate | O54: 1042346975 | P54: GsG5c0UhuhXUPj4XlY8G1kcjKioiFrqI | Q54: 7902f971-6452-469f-85c5-b0d8379edf39 | R54: application/json | T54: INTRABANK | V54: 200061777902 | W54: Lorence Ecle | X54: EWBCPHMMXXX | Y54: 200061812368 | Z54: Pao Casipe | AA54: 1 | AB54: 203.0.113.42 | AC54: 14.599500 | AD54: 120.984200 | AE54: device-abc123 | AF54: AcmePayrollApp/2.1 | AG54: Philippines | AH54: Desktop | AI54: Mandaluyong
A55: 54 | B55: =C55 -> N | C55: N | D55: TS-EB-SB-PRODUCTS-0055 | E55: TS-EB-SB-PRODUCTS-0055-Verify if required body parameters validation/notes are enforced as per API specification via EWB to EWRB upon using invalid values | F55: Send POST Request of Send Funds via Local Fund Transfer via EWB to EWRB using invalid values on Required Body Parameters | G55: Status: FAILED responseCode: 400 Bad Request responseDescription | H55: 400 | J55: /auth/token/v1/generate | K55: /send-funds/localft/v1/initiate | O55: 1042346976 | P55: GsG5c0UhuhXUPj4XlY8G1kcjKioiFrqI | Q55: 7902f971-6452-469f-85c5-b0d8379edf39 | R55: application/json | T55: INTRABANK | V55: 200061777902 | W55: Lorence Ecle | X55: EAWRPHM2XXX | Y55: 500027172598 | Z55: Pao Casipe | AA55: 1 | AB55: 203.0.113.42 | AC55: 14.599500 | AD55: 120.984200 | AE55: device-abc123 | AF55: AcmePayrollApp/2.1 | AG55: Philippines | AH55: Desktop | AI55: Mandaluyong
A56: 55 | B56: =C56 -> N | C56: N | D56: TS-EB-SB-PRODUCTS-0056 | E56: TS-EB-SB-PRODUCTS-0056-Verify if required body parameters validation/notes are enforced as per API specification via EWB to InstaPay upon using invalid values | F56: Send POST Request of Send Funds via Local Fund Transfer via EWB to InstaPay using invalid values on Required Body Parameters | G56: Status: FAILED responseCode: 400 Bad Request responseDescription | H56: 400 | J56: /auth/token/v1/generate | K56: /send-funds/localft/v1/initiate | O56: 1042346977 | P56: GsG5c0UhuhXUPj4XlY8G1kcjKioiFrqI | Q56: 7902f971-6452-469f-85c5-b0d8379edf39 | R56: application/json | T56: INSTAPAY | V56: 200061777902 | W56: Lorence Ecle | X56: CUOBPHM2XXX | Y56: 001080000029 | Z56: Pao Casipe | AA56: 1 | AB56: 203.0.113.42 | AC56: 14.599500 | AD56: 120.984200 | AE56: device-abc123 | AF56: AcmePayrollApp/2.1 | AG56: Philippines | AH56: Desktop | AI56: Mandaluyong
A57: 56 | B57: =C57 -> N | C57: N | D57: TS-EB-SB-PRODUCTS-0057 | E57: TS-EB-SB-PRODUCTS-0057-Verify if required body parameters validation/notes are enforced as per API specification via EWB to PESONet upon using invalid values | F57: Send POST Request of Send Funds via Local Fund Transfer via EWB to PESONet using invalid values on Required Body Parameters | G57: Status: FAILED responseCode: 400 Bad Request responseDescription | H57: 400 | J57: /auth/token/v1/generate | K57: /send-funds/localft/v1/initiate | O57: 1042346978 | P57: GsG5c0UhuhXUPj4XlY8G1kcjKioiFrqI | Q57: 7902f971-6452-469f-85c5-b0d8379edf39 | R57: application/json | T57: PESONET | V57: 200061777902 | W57: Lorence Ecle | X57: CUOBPHM2XXX | Y57: 001080000029 | Z57: Pao Casipe | AA57: 1 | AB57: 203.0.113.42 | AC57: 14.599500 | AD57: 120.984200 | AE57: device-abc123 | AF57: AcmePayrollApp/2.1 | AG57: Philippines | AH57: Desktop | AI57: Mandaluyong
A58: 57 | B58: =C58 -> N | C58: N | D58: TS-EB-SB-PRODUCTS-0058 | E58: TS-EB-SB-PRODUCTS-0058-Validate that all Not Required body parameters are present and correctly formatted as per API specification via EWB to EWB | F58: Send POST Request of Send Funds via Local Fund Transfer via EWB to EWB using valid values on Not Required Body Parameters | G58: API returns HTTP 200 OK | H58: 200 | J58: /auth/token/v1/generate | K58: /send-funds/localft/v1/initiate | O58: 1042346979 | P58: GsG5c0UhuhXUPj4XlY8G1kcjKioiFrqI | Q58: 7902f971-6452-469f-85c5-b0d8379edf39 | R58: application/json | T58: INTRABANK | V58: 200061777902 | W58: Lorence Ecle | X58: EWBCPHMMXXX | Y58: 200061812368 | Z58: Pao Casipe | AA58: 1 | AB58: 203.0.113.42 | AC58: 14.599500 | AD58: 120.984200 | AE58: device-abc123 | AF58: AcmePayrollApp/2.1 | AG58: Philippines | AH58: Desktop | AI58: Mandaluyong
A59: 58 | B59: =C59 -> N | C59: N | D59: TS-EB-SB-PRODUCTS-0059 | E59: TS-EB-SB-PRODUCTS-0059-Validate that all optional body parameters are present and correctly formatted as per API specification via EWB to EWRB | F59: Send POST Request of Send Funds via Local Fund Transfer via EWB to EWRB using valid values on Not Required Body Parameters | G59: API returns HTTP 200 OK | H59: 200 | J59: /auth/token/v1/generate | K59: /send-funds/localft/v1/initiate | O59: 1042346980 | P59: GsG5c0UhuhXUPj4XlY8G1kcjKioiFrqI | Q59: 7902f971-6452-469f-85c5-b0d8379edf39 | R59: application/json | T59: INTRABANK | V59: 200061777902 | W59: Lorence Ecle | X59: EAWRPHM2XXX | Y59: 500027172598 | Z59: Pao Casipe | AA59: 1 | AB59: 203.0.113.42 | AC59: 14.599500 | AD59: 120.984200 | AE59: device-abc123 | AF59: AcmePayrollApp/2.1 | AG59: Philippines | AH59: Desktop | AI59: Mandaluyong
A60: 59 | B60: =C60 -> N | C60: N | D60: TS-EB-SB-PRODUCTS-0060 | E60: TS-EB-SB-PRODUCTS-0060-Validate that all optional body parameters are present and correctly formatted as per API specification via EWB to InstaPay | F60: Send POST Request of Send Funds via Local Fund Transfer via EWB to InstaPay using valid values on Not Required Body Parameters | G60: API returns HTTP 200 OK | H60: 200 | J60: /auth/token/v1/generate | K60: /send-funds/localft/v1/initiate | O60: 1042346981 | P60: GsG5c0UhuhXUPj4XlY8G1kcjKioiFrqI | Q60: 7902f971-6452-469f-85c5-b0d8379edf39 | R60: application/json | T60: INSTAPAY | V60: 200061777902 | W60: Lorence Ecle | X60: CUOBPHM2XXX | Y60: 001080000029 | Z60: Pao Casipe | AA60: 1 | AB60: 203.0.113.42 | AC60: 14.599500 | AD60: 120.984200 | AE60: device-abc123 | AF60: AcmePayrollApp/2.1 | AG60: Philippines | AH60: Desktop | AI60: Mandaluyong
A61: 60 | B61: =C61 -> N | C61: N | D61: TS-EB-SB-PRODUCTS-0061 | E61: TS-EB-SB-PRODUCTS-0061-Validate that all optional body parameters are present and correctly formatted as per API specification via EWB to PESONet | F61: Send POST Request of Send Funds via Local Fund Transfer via EWB to PESONet using valid values on Not Required Body Parameters | G61: API returns HTTP 200 OK | H61: 200 | J61: /auth/token/v1/generate | K61: /send-funds/localft/v1/initiate | O61: 1042346982 | P61: GsG5c0UhuhXUPj4XlY8G1kcjKioiFrqI | Q61: 7902f971-6452-469f-85c5-b0d8379edf39 | R61: application/json | T61: PESONET | V61: 200061777902 | W61: Lorence Ecle | X61: CUOBPHM2XXX | Y61: 001080000029 | Z61: Pao Casipe | AA61: 1 | AB61: 203.0.113.42 | AC61: 14.599500 | AD61: 120.984200 | AE61: device-abc123 | AF61: AcmePayrollApp/2.1 | AG61: Philippines | AH61: Desktop | AI61: Mandaluyong
A62: 61 | B62: =C62 -> N | C62: N | D62: TS-EB-SB-PRODUCTS-0062 | E62: TS-EB-SB-PRODUCTS-0062-Validate that all optional body parameters are present and correctly formatted as per API specification via EWB to EWB | F62: Send POST Request of Send Funds via Local Fund Transfer via EWB to EWB using invalid values on Not Required Body Parameters | G62: Status: FAILED responseCode: 400 Bad Request responseDescription | H62: 400 | J62: /auth/token/v1/generate | K62: /send-funds/localft/v1/initiate | O62: 1042346983 | P62: GsG5c0UhuhXUPj4XlY8G1kcjKioiFrqI | Q62: 7902f971-6452-469f-85c5-b0d8379edf39 | R62: application/json | T62: INTRABANK | V62: 200061777902 | W62: Lorence Ecle | X62: EAWRPHM2XXX | Y62: 500027172598 | Z62: Pao Casipe | AA62: 1 | AB62: 203.0.113.42 | AC62: 14.599500 | AD62: 120.984200 | AE62: device-abc123 | AF62: AcmePayrollApp/2.1 | AG62: Philippines | AH62: Desktop | AI62: Mandaluyong
A63: 62 | B63: =C63 -> N | C63: N | D63: TS-EB-SB-PRODUCTS-0063 | E63: TS-EB-SB-PRODUCTS-0063-Verify if not required body parameters validation/notes are enforced as per API specification via EWB to EWRB upon using invalid values | F63: Send POST Request of Send Funds via Local Fund Transfer via EWB to EWRB using invalid values on Not Required Body Parameters | G63: Status: FAILED responseCode: 400 Bad Request responseDescription | H63: 400 | J63: /auth/token/v1/generate | K63: /send-funds/localft/v1/initiate | O63: 1042346984 | P63: GsG5c0UhuhXUPj4XlY8G1kcjKioiFrqI
A64: 63 | B64: =C64 -> N | C64: N | D64: TS-EB-SB-PRODUCTS-0064 | E64: TS-EB-SB-PRODUCTS-0064-Verify if not required body parameters validation/notes are enforced as per API specification via EWB to InstaPay upon using invalid values | F64: Send POST Request of Send Funds via Local Fund Transfer via EWB to InstaPay using invalid values on Not Required Body Parameters | G64: Status: FAILED responseCode: 400 Bad Request responseDescription | H64: 200 | J64: /auth/token/v1/generate | K64: /send-funds/localft/v1/initiate | O64: 1042346985 | P64: GsG5c0UhuhXUPj4XlY8G1kcjKioiFrqI
A65: 64 | B65: =C65 -> N | C65: N | D65: TS-EB-SB-PRODUCTS-0065 | E65: TS-EB-SB-PRODUCTS-0065-Verify if not required body parameters validation/notes are enforced as per API specification via EWB to PESONet upon using invalid values | F65: Send POST Request of Send Funds via Local Fund Transfer via EWB to PESONet using invalid values on Not Required Body Parameters | G65: Status: FAILED responseCode: 400 Bad Request responseDescription | H65: 400 | J65: /auth/token/v1/generate | K65: /send-funds/localft/v1/initiate | O65: 1042346986 | P65: GsG5c0UhuhXUPj4XlY8G1kcjKioiFrqI
A66: 65 | B66: =C66 -> N | C66: N | D66: TS-EB-SB-PRODUCTS-0066_1 | E66: TS-EB-SB-PRODUCTS-0066_1-Verify that resending the same request with the same 13‑digit idempotency key returns the original response | F66: Resend POST Request of Send Funds via Local Fund Transfer using the same request with same 13‑digit idempotency key | G66: The API Portal detects the existing record and skips re‑processing, returning the original response within ≤ 500 ms. The API returns the original successful response with the same apiTxnRef, status, and references. Sample Response Body: 200 OK { "apiTxnId": 20, "apiTxnRef": "60000000000010156580823", "ewbCoreReference": null, "externalRailReference": null, "responseCode": "ACCEPTED", "status": "PENDING", "responseDescription": null, "createdTimestamp": "2026-06-01T14:50:41.0068888" } | H66: 200 | J66: /auth/token/v1/generate | K66: /send-funds/localft/v1/initiate | O66: 1042346987 | P66: GsG5c0UhuhXUPj4XlY8G1kcjKioiFrqI
A67: 66 | B67: =C67 -> N | C67: N | D67: TS-EB-SB-PRODUCTS-0066_2 | E67: TS-EB-SB-PRODUCTS-0066_2-Verify that resending the same request with the same 13‑digit idempotency key returns the original response | F67: Resend POST Request of Send Funds via Local Fund Transfer using the same request with same 13‑digit idempotency key | G67: The API Portal detects the existing record and skips re‑processing, returning the original response within ≤ 500 ms. The API returns the original successful response with the same apiTxnRef, status, and references. Sample Response Body: 200 OK { "apiTxnId": 20, "apiTxnRef": "60000000000010156580823", "ewbCoreReference": null, "externalRailReference": null, "responseCode": "ACCEPTED", "status": "PENDING", "responseDescription": null, "createdTimestamp": "2026-06-01T14:50:41.0068888" } | H67: 200 | J67: /auth/token/v1/generate | K67: /send-funds/localft/v1/initiate | O67: 1042346987 | P67: GsG5c0UhuhXUPj4XlY8G1kcjKioiFrqI
A68: 67 | B68: =C68 -> N | C68: N | D68: TS-EB-SB-PRODUCTS-0066_3 | E68: TS-EB-SB-PRODUCTS-0066_3-Verify that resending the same request with the same 13‑digit idempotency key returns the original response | F68: Resend POST Request of Send Funds via Local Fund Transfer using the same request with same 13‑digit idempotency key | G68: The API Portal detects the existing record and skips re‑processing, returning the original response within ≤ 500 ms. The API returns the original successful response with the same apiTxnRef, status, and references. Sample Response Body: 200 OK { "apiTxnId": 20, "apiTxnRef": "60000000000010156580823", "ewbCoreReference": null, "externalRailReference": null, "responseCode": "ACCEPTED", "status": "PENDING", "responseDescription": null, "createdTimestamp": "2026-06-01T14:50:41.0068888" } | H68: 200 | J68: /auth/token/v1/generate | K68: /send-funds/localft/v1/initiate | O68: 1042346987 | P68: GsG5c0UhuhXUPj4XlY8G1kcjKioiFrqI
A69: 68 | B69: =C69 -> N | C69: N | D69: TS-EB-SB-PRODUCTS-0066_4 | E69: TS-EB-SB-PRODUCTS-0066_4-Verify that resending the same request with the same 13‑digit idempotency key returns the original response | F69: Resend POST Request of Send Funds via Local Fund Transfer using the same request with same 13‑digit idempotency key | G69: The API Portal detects the existing record and skips re‑processing, returning the original response within ≤ 500 ms. The API returns the original successful response with the same apiTxnRef, status, and references. Sample Response Body: 200 OK { "apiTxnId": 20, "apiTxnRef": "60000000000010156580823", "ewbCoreReference": null, "externalRailReference": null, "responseCode": "ACCEPTED", "status": "PENDING", "responseDescription": null, "createdTimestamp": "2026-06-01T14:50:41.0068888" } | H69: 200 | J69: /auth/token/v1/generate | K69: /send-funds/localft/v1/initiate | O69: 1042346987 | P69: GsG5c0UhuhXUPj4XlY8G1kcjKioiFrqI
A70: 69 | B70: =C70 -> N | C70: N | D70: TS-EB-SB-PRODUCTS-0067_1 | E70: TS-EB-SB-PRODUCTS-0067_1-Verify Different payload with the same idempotency-key response | F70: Send POST Request of Send Funds via Local Fund Transfer using the different payload with same 13‑digit idempotency key | G70: Different payload with same idempotency-key returns HTTP 409 Conflict with clear error message. Sample Response Body: 409 Conflict { "status": "FAILED", "authId": null, "errors": null, "responseCode": "409", "responseDescription": "Idempotency key already used with a different request payload" } | H70: 409 | J70: /auth/token/v1/generate | K70: /send-funds/localft/v1/initiate | O70: 1042346988 | P70: GsG5c0UhuhXUPj4XlY8G1kcjKioiFrqI
A71: 70 | B71: =C71 -> N | C71: N | D71: TS-EB-SB-PRODUCTS-0067_2 | E71: TS-EB-SB-PRODUCTS-0067_2-Verify Different payload with the same idempotency-key response | F71: Send POST Request of Send Funds via Local Fund Transfer using the different payload with same 13‑digit idempotency key | G71: Different payload with same idempotency-key returns HTTP 409 Conflict with clear error message. Sample Response Body: 409 Conflict { "status": "FAILED", "authId": null, "errors": null, "responseCode": "409", "responseDescription": "Idempotency key already used with a different request payload" } | H71: 409 | J71: /auth/token/v1/generate | K71: /send-funds/localft/v1/initiate | O71: 1042346993 | P71: GsG5c0UhuhXUPj4XlY8G1kcjKioiFrqI
A72: 71 | B72: =C72 -> N | C72: N | D72: TS-EB-SB-PRODUCTS-0067_3 | E72: TS-EB-SB-PRODUCTS-0067_3-Verify Different payload with the same idempotency-key response | F72: Send POST Request of Send Funds via Local Fund Transfer using the different payload with same 13‑digit idempotency key | G72: Different payload with same idempotency-key returns HTTP 409 Conflict with clear error message. Sample Response Body: 409 Conflict { "status": "FAILED", "authId": null, "errors": null, "responseCode": "409", "responseDescription": "Idempotency key already used with a different request payload" } | H72: 409 | J72: /auth/token/v1/generate | K72: /send-funds/localft/v1/initiate | O72: 1042346993 | P72: GsG5c0UhuhXUPj4XlY8G1kcjKioiFrqI
A73: 72 | B73: =C73 -> N | C73: N | D73: TS-EB-SB-PRODUCTS-0067_4 | E73: TS-EB-SB-PRODUCTS-0067_4-Verify Different payload with the same idempotency-key response | F73: Send POST Request of Send Funds via Local Fund Transfer using the different payload with same 13‑digit idempotency key | G73: Different payload with same idempotency-key returns HTTP 409 Conflict with clear error message. Sample Response Body: 409 Conflict { "status": "FAILED", "authId": null, "errors": null, "responseCode": "409", "responseDescription": "Idempotency key already used with a different request payload" } | H73: 409 | J73: /auth/token/v1/generate | K73: /send-funds/localft/v1/initiate | O73: 1042346993 | P73: GsG5c0UhuhXUPj4XlY8G1kcjKioiFrqI
A74: 73 | B74: =C74 -> N | C74: N | D74: TS-EB-SB-PRODUCTS-0034 | E74: TS-EB-SB-PRODUCTS-0068: Send Funds via Local Fund Transfer v1.0_Initiate Local Funds Transfer API_Verify Different payload with the same idempotency-key response time / processing time | F74: Send POST Request of Send Funds via Local Fund Transfer using the different payload with same 13‑digit idempotency key. Observe response/processing time. | G74: Different payload with same idempotency-key returns HTTP 409 Conflict with clear error message is processed within ≤ 1 second. | H74: 409 | J74: /auth/token/v1/generate | K74: /send-funds/localft/v1/initiate
A75: 74 | B75: =C75 -> N | C75: N | D75: TS-EB-SB-PRODUCTS-0069_1 | E75: TS-EB-SB-PRODUCTS-0069_1-Verify that Transaction ID is generated on successful Intrabank transaction | F75: Send POST Request of valid Send Funds Local Fund Transfer via Intrabank | G75: apitxnID and apitxnRef are visible with correct formats in the Response Body | H75: 200 | J75: /auth/token/v1/generate | K75: /send-funds/localft/v1/initiate | O75: 1042346990 | P75: GsG5c0UhuhXUPj4XlY8G1kcjKioiFrqI
A76: 75 | B76: =C76 -> N | C76: N | D76: TS-EB-SB-PRODUCTS-0069_2 | E76: TS-EB-SB-PRODUCTS-0069_2-Verify that Transaction ID is generated on successful Intrabank transaction | F76: Send POST Request of valid Send Funds Local Fund Transfer via Intrabank | G76: apitxnID and apitxnRef are visible with correct formats in the Response Body | H76: 200 | J76: /auth/token/v1/generate | K76: /send-funds/localft/v1/initiate | O76: 1042346990 | P76: GsG5c0UhuhXUPj4XlY8G1kcjKioiFrqI
A77: 76 | B77: =C77 -> N | C77: N | D77: TS-EB-SB-PRODUCTS-0070 | E77: TS-EB-SB-PRODUCTS-0070-Verify that Transaction ID is generated on successful Instapay transaction | F77: Send POST Request of valid Send Funds Local Fund Transfer via InstaPay | G77: apitxnID and apitxnRef are visible with correct formats in the Response Body | H77: 200 | J77: /auth/token/v1/generate | K77: /send-funds/localft/v1/initiate | O77: 1042346991 | P77: GsG5c0UhuhXUPj4XlY8G1kcjKioiFrqI
A78: 77 | B78: =C78 -> N | C78: N | D78: TS-EB-SB-PRODUCTS-0071 | E78: TS-EB-SB-PRODUCTS-0071-Verify that Transaction ID is generated on successful PESONet transaction | F78: Send POST Request of valid Send Funds Local Fund Transfer via PESONet | G78: apitxnID and apitxnRef are visible with correct formats in the Response Body | H78: 200 | J78: /auth/token/v1/generate | K78: /send-funds/localft/v1/initiate | O78: 1042346992 | P78: GsG5c0UhuhXUPj4XlY8G1kcjKioiFrqI
A79: 78 | B79: =C79 -> N | C79: N | D79: TS-EB-SB-PRODUCTS-0072_1 | E79: TS-EB-SB-PRODUCTS-0072_1-Verify that apiTxnId format containts 36 BIGINT auto-increment primary key of Intrabank transaction | J79: /auth/token/v1/generate | K79: /send-funds/localft/v1/initiate | O79: 1042346993 | P79: GsG5c0UhuhXUPj4XlY8G1kcjKioiFrqI
A80: 79 | B80: =C80 -> N | C80: N | D80: TS-EB-SB-PRODUCTS-0072_2 | E80: TS-EB-SB-PRODUCTS-0072_2-Verify that apiTxnId format containts 36 BIGINT auto-increment primary key of Intrabank transaction | F80: Send POST Request of valid Send Funds Local Fund Transfer via Intrabank | G80: API Portal generates internal apiTxnId (Up to 36 digits (BIGINT) auto-increment primary key). | H80: 200 | J80: /auth/token/v1/generate | K80: /send-funds/localft/v1/initiate | O80: 1042346993 | P80: GsG5c0UhuhXUPj4XlY8G1kcjKioiFrqI
A81: 80 | B81: =C81 -> N | C81: N | D81: TS-EB-SB-PRODUCTS-0073 | E81: TS-EB-SB-PRODUCTS-0073-Verify that apiTxnId format containts 36 BIGINT auto-increment primary key of Instapay transaction | F81: Send POST Request of valid Send Funds Local Fund Transfer via InstaPay | G81: API Portal generates internal apiTxnId (Up to 36 digits (BIGINT) auto-increment primary key). | H81: 200 | J81: /auth/token/v1/generate | K81: /send-funds/localft/v1/initiate | O81: 1042346994 | P81: GsG5c0UhuhXUPj4XlY8G1kcjKioiFrqI
A82: 81 | B82: =C82 -> N | C82: N | D82: TS-EB-SB-PRODUCTS-0074 | E82: TS-EB-SB-PRODUCTS-0074-Verify that apiTxnId format containts 36 BIGINT auto-increment primary key of PESONet transaction | F82: Send POST Request of valid Send Funds Local Fund Transfer via PESONet | G82: API Portal generates internal apiTxnId (Up to 36 digits (BIGINT) auto-increment primary key). | H82: 200 | J82: /auth/token/v1/generate | K82: /send-funds/localft/v1/initiate | O82: 1042346995 | P82: GsG5c0UhuhXUPj4XlY8G1kcjKioiFrqI
A83: 82 | B83: =C83 -> N | C83: N | D83: TS-EB-SB-PRODUCTS-0075_1 | E83: TS-EB-SB-PRODUCTS-0075_1-Verify that apiTxnRef has correct format of Intrabank transaction | F83: Send POST Request of valid Send Funds Local Fund Transfer via Intrabank | G83: apiTxnRef is correctly constructed 23 digits (Application-ID + Product-ID + Idempotency-Key + wildcard) | H83: 200 | J83: /auth/token/v1/generate | K83: /send-funds/localft/v1/initiate | O83: 1042346996 | P83: GsG5c0UhuhXUPj4XlY8G1kcjKioiFrqI
A84: 83 | B84: =C84 -> N | C84: N | D84: TS-EB-SB-PRODUCTS-0075_2 | E84: TS-EB-SB-PRODUCTS-0075_2-Verify that apiTxnRef has correct format of Intrabank transaction | F84: Send POST Request of valid Send Funds Local Fund Transfer via Intrabank | G84: apiTxnRef is correctly constructed 23 digits (Application-ID + Product-ID + Idempotency-Key + wildcard) | H84: 200 | J84: /auth/token/v1/generate | K84: /send-funds/localft/v1/initiate | O84: 1042346996 | P84: GsG5c0UhuhXUPj4XlY8G1kcjKioiFrqI
A85: 84 | B85: =C85 -> N | C85: N | D85: TS-EB-SB-PRODUCTS-0076 | E85: TS-EB-SB-PRODUCTS-0076-Verify that apiTxnRef has correct format of Instapay transaction | F85: Send POST Request of valid Send Funds Local Fund Transfer via InstaPay | G85: apiTxnRef is correctly constructed 23 digits (Application-ID + Product-ID + Idempotency-Key + wildcard) | H85: 200 | J85: /auth/token/v1/generate | K85: /send-funds/localft/v1/initiate | O85: 1042346997 | P85: GsG5c0UhuhXUPj4XlY8G1kcjKioiFrqI
A86: 85 | B86: =C86 -> N | C86: N | D86: TS-EB-SB-PRODUCTS-0077 | E86: TS-EB-SB-PRODUCTS-0077-Verify that apiTxnRef has correct format of PESONet transaction | F86: Send POST Request of valid Send Funds Local Fund Transfer via PESONet | G86: apiTxnRef is correctly constructed 23 digits (Application-ID + Product-ID + Idempotency-Key + wildcard) | H86: 200 | J86: /auth/token/v1/generate | K86: /send-funds/localft/v1/initiate | O86: 1042346998 | P86: GsG5c0UhuhXUPj4XlY8G1kcjKioiFrqI
A87: 86 | B87: =C87 -> N | C87: N | D87: TS-EB-SB-PRODUCTS-0078_1 | E87: TS-EB-SB-PRODUCTS-0078_1-Verify that apiTxnRef has propagated to downstream system upon doing Intrabank transaction | F87: Send POST Request of valid Send Funds Local Fund Transfer via Intrabank | G87: apiTxnRef is propagated to downstream systems, payment rails, logs, reconciliation files, and audit trails. | H87: 200 | J87: /auth/token/v1/generate | K87: /send-funds/localft/v1/initiate | O87: 1042346999 | P87: GsG5c0UhuhXUPj4XlY8G1kcjKioiFrqI
A88: 87 | B88: =C88 -> N | C88: N | D88: TS-EB-SB-PRODUCTS-0078_2 | E88: TS-EB-SB-PRODUCTS-0078_2-Verify that apiTxnRef has propagated to downstream system upon doing Intrabank transaction | F88: Send POST Request of valid Send Funds Local Fund Transfer via Intrabank | G88: apiTxnRef is propagated to downstream systems, payment rails, logs, reconciliation files, and audit trails. | H88: 200 | J88: /auth/token/v1/generate | K88: /send-funds/localft/v1/initiate | O88: 1042346999 | P88: GsG5c0UhuhXUPj4XlY8G1kcjKioiFrqI
A89: 88 | B89: =C89 -> N | C89: N | D89: TS-EB-SB-PRODUCTS-0079 | E89: TS-EB-SB-PRODUCTS-0079-Verify that apiTxnRef has propagated to downstream system Instapay transaction | F89: Send POST Request of valid Send Funds Local Fund Transfer via InstaPay | G89: apiTxnRef is propagated to downstream systems, payment rails, logs, reconciliation files, and audit trails. | H89: 200 | J89: /auth/token/v1/generate | K89: /send-funds/localft/v1/initiate | O89: 1042347000 | P89: GsG5c0UhuhXUPj4XlY8G1kcjKioiFrqI
A90: 89 | B90: =C90 -> N | C90: N | D90: TS-EB-SB-PRODUCTS-0080 | E90: TS-EB-SB-PRODUCTS-0080-Verify that apiTxnRef has propagated to downstream system PESONet transaction | F90: Send POST Request of valid Send Funds Local Fund Transfer via PESONet | G90: apiTxnRef is propagated to downstream systems, payment rails, logs, reconciliation files, and audit trails. | H90: 200 | J90: /auth/token/v1/generate | K90: /send-funds/localft/v1/initiate | O90: 1042347001 | P90: GsG5c0UhuhXUPj4XlY8G1kcjKioiFrqI
A91: 90 | B91: =C91 -> N | C91: N | D91: TS-EB-SB-PRODUCTS-0081_1 | E91: TS-EB-SB-PRODUCTS-0081_1-Verify Intrabank/InstaPay/PESONETrail Initial Status | F91: Send POST Request of valid Send Funds Local Fund Transfer via Intrabank/InstaPay/PESONet | G91: apiTxnRef is propagated to downstream systems, payment rails, logs, reconciliation files, and audit trails. | H91: 200 | J91: /auth/token/v1/generate | K91: /send-funds/localft/v1/initiate | O91: 1042347002 | P91: GsG5c0UhuhXUPj4XlY8G1kcjKioiFrqI
... A94: 93 | B94: =C94 -> N | C94: N | D94: TS-EB-SB-PRODUCTS-0081_4 | E94: TS-EB-SB-PRODUCTS-0081_4-Verify Intrabank/InstaPay/PESONETrail Initial Status | F94: Send POST Request of valid Send Funds Local Fund Transfer via Intrabank/InstaPay/PESONet | G94: apiTxnRef is propagated to downstream systems, payment rails, logs, reconciliation files, and audit trails. | H94: 200 | J94: /auth/token/v1/generate | K94: /send-funds/localft/v1/initiate | O94: 1042347002 | P94: GsG5c0UhuhXUPj4XlY8G1kcjKioiFrqI
A95: 94 | B95: =C95 -> N | C95: N | D95: TS-EB-SB-PRODUCTS-0035 | E95: TS-EB-SB-PRODUCTS-0082: Send Funds via Local Fund Transfer v1.0_Initiate Local Funds Transfer API_Verify Intrabank/InstaPay/PESONET rail Initial Status processing time | F95: Send POST Request of valid Send Funds Local Fund Transfer via Intrabank/InstaPay/PESONet | G95: Status "RECEIVE" in response and database within ≤ 1 second upon successful validation of the API call | H95: 200 | J95: /auth/token/v1/generate | K95: /send-funds/localft/v1/initiate
A96: 95 | B96: =C96 -> N | C96: N | D96: TS-EB-SB-PRODUCTS-0083_1 | E96: TS-EB-SB-PRODUCTS-0083_1-Verify strict reconciliation between API Portal, Core Banking, and payment rails | F96: Send POST Request of valid Send Funds Local Fund Transfer via Intrabank/InstaPay/PESONet | G96: apiTxnRef is propagated to downstream systems, payment rails, logs, reconciliation files, and audit trails. | H96: 200 | J96: /auth/token/v1/generate | K96: /send-funds/localft/v1/initiate | O96: 1042347003 | P96: GsG5c0UhuhXUPj4XlY8G1kcjKioiFrqI
A97: 96 | B97: =C97 -> N | C97: N | D97: TS-EB-SB-PRODUCTS-0083_2 | E97: TS-EB-SB-PRODUCTS-0083_2-Verify strict reconciliation between API Portal, Core Banking, and payment rails | F97: Send POST Request of valid Send Funds Local Fund Transfer via Intrabank/InstaPay/PESONet | G97: apiTxnRef is propagated to downstream systems, payment rails, logs, reconciliation files, and audit trails. | H97: 200 | J97: /auth/token/v1/generate | K97: /send-funds/localft/v1/initiate | O97: 1042347003 | P97: GsG5c0UhuhXUPj4XlY8G1kcjKioiFrqI
A98: 97 | B98: =C98 -> N | C98: N | D98: TS-EB-SB-PRODUCTS-0083_3 | E98: TS-EB-SB-PRODUCTS-0083_3-Verify strict reconciliation between API Portal, Core Banking, and payment rails | F98: Send POST Request of valid Send Funds Local Fund Transfer via Intrabank/InstaPay/PESONet | G98: apiTxnRef is propagated to downstream systems, payment rails, logs, reconciliation files, and audit trails. | H98: 200 | J98: /auth/token/v1/generate | K98: /send-funds/localft/v1/initiate | O98: 1042347003 | P98: GsG5c0UhuhXUPj4XlY8G1kcjKioiFrqI
A99: 98 | B99: =C99 -> N | C99: N | D99: TS-EB-SB-PRODUCTS-0083_4 | E99: TS-EB-SB-PRODUCTS-0083_4-Verify strict reconciliation between API Portal, Core Banking, and payment rails | F99: Send POST Request of valid Send Funds Local Fund Transfer via Intrabank/InstaPay/PESONet | G99: apiTxnRef is propagated to downstream systems, payment rails, logs, reconciliation files, and audit trails. | H99: 200 | J99: /auth/token/v1/generate | K99: /send-funds/localft/v1/initiate | O99: 1042347003 | P99: GsG5c0UhuhXUPj4XlY8G1kcjKioiFrqI
A100: 99 | B100: =C100 -> N | C100: N | D100: TS-EB-SB-PRODUCTS-0084_1 | E100: TS-EB-SB-PRODUCTS-0084_1-Verify all transaction status transitions are logged and auditable in the Dedicated External API Portal Database | F100: Send POST Request of valid Send Funds Local Fund Transfer via Intrabank/Instapay/PESONet | G100: apiTxnRef is propagated to downstream systems, payment rails, logs, reconciliation files, and audit trails. | H100: 200 | J100: /auth/token/v1/generate | K100: /send-funds/localft/v1/initiate | O100: 1042347003 | P100: GsG5c0UhuhXUPj4XlY8G1kcjKioiFrqI
A101: 100 | B101: =C101 -> N | C101: N | D101: TS-EB-SB-PRODUCTS-0084_2 | E101: TS-EB-SB-PRODUCTS-0084_2-Verify all transaction status transitions are logged and auditable in the Dedicated External API Portal Database | F101: Send POST Request of valid Send Funds Local Fund Transfer via Intrabank/Instapay/PESONet | G101: apiTxnRef is propagated to downstream systems, payment rails, logs, reconciliation files, and audit trails. | H101: 200 | J101: /auth/token/v1/generate | K101: /send-funds/localft/v1/initiate | O101: 1042347003 | P101: GsG5c0UhuhXUPj4XlY8G1kcjKioiFrqI
A102: 101 | B102: =C102 -> N | C102: N | D102: TS-EB-SB-PRODUCTS-0084_3 | E102: TS-EB-SB-PRODUCTS-0084_3-Verify all transaction status transitions are logged and auditable in the Dedicated External API Portal Database | F102: Send POST Request of valid Send Funds Local Fund Transfer via Intrabank/Instapay/PESONet | G102: apiTxnRef is propagated to downstream systems, payment rails, logs, reconciliation files, and audit trails. | H102: 200 | J102: /auth/token/v1/generate | K102: /send-funds/localft/v1/initiate | O102: 1042347003 | P102: GsG5c0UhuhXUPj4XlY8G1kcjKioiFrqI
...

Sheet PTTAuthAPI
A1: # | B1: ExecutionFlag | C1: Core | D1: TC_ID | E1: Description | F1: StepAction | G1: ExpectedResult | H1: ExpectedStatus | I1: ExpectedResponseDescription | J1: IN_EndPoint | K1: IN_HeadAccept | L1: IN_HeadClientID | M1: IN_HeadClientSecret | N1: IN_HeadPartnerID | O1: IN_HeadAPIKey | P1: IN_HeadContentType | Q1: IN_AccountNumber | R1: IN_Scope | S1: OUT_RequestHeaders | T1: OUT_RequestBody | U1: OUT_ResponseHeaders | V1: OUT_ResponseBody
A2: 1 | B2: Y | C2: Y | D2: TS-EB-PRODUCTS-0296 | E2: TS-EB-PRODUCTS-0296: Account Authentication via Access Token v1.0_Generate Account Access Token API_Verify Token generation for Client-Owned Account | F2: Send POST Request using Client-Owned Account | G2: Successful Request Status 200 OK Response Body contains: - access_token [Token is valid and usable] - token_type - expires_in -authId Request logged in API Portal DB | H2: 200 | J2: /auth/token/v1/generate | K2: application/json | L2: 3TaenF9h5d9FCEEIZRVPc4AxdFggPaxA | M2: wE4n0CYiVOdJ9m8EfKuMhxm0m4kOaUOr | N2: 263677df68 | O2: K6y28Ks1TyrwjONU0PatZ6BhOWfTAuHo | P2: application/json | Q2: 200061817815 | R2: send-funds.initiate
A3: 2 | B3: Y | C3: Y | D3: TS-EB-PRODUCTS-0006_1 | E3: TS-EB-PRODUCTS-0006_1: Account Authentication via Access Token v1.0_Generate Account Access Token API_Verify API Call using Token used with different client credentials | F3: Send POST Request using Valid Account Access Token but different client credentials | G3: Failed/Rejected Status 401 Unauthorized - clear error message. Error: Token does not match client credentials - Token validation executes in p99 latency < 30 ms. | H3: 401 | I3: Invalid OAuth2 request parameters | J3: /auth/token/v1/generate | K3: application/json | L3: 3TaenF9h5d9FCEEIZRVPc4AxdFggPaxA | M3: wE4n0CYiVOdJ9m8EfILMhxm0m4kOaUOr | N3: 263677df68 | O3: K6y28Ks1TyrwjONU0PatZ6BhOWfTAuHo | P3: application/json | Q3: 200061817815 | R3: send-funds.initiate
A4: 3 | B4: Y | C4: Y | D4: TS-EB-PRODUCTS-0006_2 | E4: TS-EB-PRODUCTS-0006_2: Account Authentication via Access Token v1.0_Generate Account Access Token API_Verify API Call using Token used with different client credentials | F4: Send POST Request using Valid Account Access Token but different client credentials | G4: Failed/Rejected Status 401 Unauthorized - clear error message. Error: Token does not match client credentials - Token validation executes in p99 latency < 30 ms. | H4: 401 | I4: Invalid OAuth2 request parameters | J4: /auth/token/v1/generate | K4: application/json | L4: 3TaenF9h5d9FCEEUYZRVPc4AxdFggPaxA | M4: wE4n0CYiVOdJ9m8EfKuMhxm0m4kOaUOr | N4: 263677df68 | O4: K6y28Ks1TyrwjONU0PatZ6BhOWfTAuHo | P4: application/json | Q4: 200061817815 | R4: send-funds.initiate
A5: 4 | B5: Y | C5: Y | D5: TS-EB-PRODUCTS-0007 | E5: TS-EB-PRODUCTS-0007: Account Authentication via Access Token v1.0_Generate Account Access Token API_Token used with different Partner-ID | F5: Send POST Request using Valid Account Access Token but different Partner-ID | G5: Failed/Rejected Status 401 Unauthorized - clear error message. Enforcement failure due to Partner-ID mismatch - Token validation executes in p99 latency < 30 ms. | H5: 401 | I5: The partner ID provided is invalid, not recognized, or not registered in Client Hub. | J5: /auth/token/v1/generate | K5: application/json | L5: 3TaenF9h5d9FCEEIZRVPc4AxdFggPaxA | M5: wE4n0CYiVOdJ9m8EfKuMhxm0m4kOaUOr | N5: 263847df68 | O5: K6y28Ks1TyrwjONU0PatZ6BhOWfTAuHo | P5: application/json | Q5: 200061817815 | R5: send-funds.initiate
A6: 5 | B6: Y | C6: Y | D6: TS-EB-PRODUCTS-0297_1 | E6: TS-EB-PRODUCTS-0297_1: Account Authentication via Access Token v1.0_Generate Account Access Token API_Verify send request with missing mandatory parameters. | F6: Send POST Request with missing mandatory parameters | G6: Failed 400 (Bad Request) Error details for missing fields | H6: 400 | I6: The accountNumber provided is invalid, not recognized, or not registered in Client Hub. | J6: /auth/token/v1/generate | K6: application/json | L6: 3TaenF9h5d9FCEEIZRVPc4AxdFggPaxA | M6: wE4n0CYiVOdJ9m8EfKuMhxm0m4kOaUOr | N6: 263677df68 | O6: K6y28Ks1TyrwjONU0PatZ6BhOWfTAuHo | P6: application/json | R6: send-funds.initiate
A7: 6 | B7: Y | C7: Y | D7: TS-EB-PRODUCTS-0297_2 | E7: TS-EB-PRODUCTS-0297_2: Account Authentication via Access Token v1.0_Generate Account Access Token API_Verify send request with missing mandatory parameters. | F7: Send POST Request with missing mandatory parameters | G7: Failed 400 (Bad Request) Error details for missing fields | H7: 400 | I7: The scope provided The scope provided is invalid or not recognized | J7: /auth/token/v1/generate | K7: application/json | L7: 3TaenF9h5d9FCEEIZRVPc4AxdFggPaxA | M7: wE4n0CYiVOdJ9m8EfKuMhxm0m4kOaUOr | N7: 263677df68 | O7: K6y28Ks1TyrwjONU0PatZ6BhOWfTAuHo | P7: application/json | Q7: 200061817815
A8: 7 | B8: Y | C8: Y | D8: TS-EB-PRODUCTS-0299 | E8: TS-EB-PRODUCTS-0299: Account Authentication via Access Token v1.0_Generate Account Access Token API_Verify successful POST Authentication using Client Owned Account with ACTIVE status and with valid client-id, client-secret, and partner-id | F8: Send POST Request using valid ACTIVE Client Owned Account wiht valid client-credentials | G8: Successful Status 200 OK Response Body: within 300 ms. accessToken, tokenType: Bearer, expiresIn, authId Token is bound to the exact account, | H8: 200 | J8: /auth/token/v1/generate | K8: application/json | L8: 3TaenF9h5d9FCEEIZRVPc4AxdFggPaxA | M8: wE4n0CYiVOdJ9m8EfKuMhxm0m4kOaUOr | N8: 263677df68 | O8: K6y28Ks1TyrwjONU0PatZ6BhOWfTAuHo | P8: application/json | Q8: 200061817815 | R8: send-funds.initiate
A9: 8 | B9: Y | C9: Y | D9: TS-EB-PRODUCTS-0300_1 | E9: TS-EB-PRODUCTS-0300_1: Account Authentication via Access Token v1.0_Generate Account Access Token API_Verify authentication token is usable in the next account-based API call within the expiry window | F9: Send POST Request using valid ACTIVE Client Owned Account with valid client-credentials using same authentication token | G9: Token generated is usable in the nexy account-based transactional API call within expiry (3600s) | H9: 200 | J9: /auth/token/v1/generate | K9: application/json | L9: 3TaenF9h5d9FCEEIZRVPc4AxdFggPaxA | M9: wE4n0CYiVOdJ9m8EfKuMhxm0m4kOaUOr | N9: 263677df68 | O9: K6y28Ks1TyrwjONU0PatZ6BhOWfTAuHo | P9: application/json | Q9: 200061817815 | R9: send-funds.initiate
A10: 9 | B10: Y | C10: Y | D10: TS-EB-PRODUCTS-0301_1 | E10: TS-EB-PRODUCTS-0301_1: Account Authentication via Access Token v1.0_Generate Account Access Token API_Verify POST request using Invalid client credentials | F10: Send POST Request using valid ACTIVE Client Owned Account with invalid client-credentials | G10: Failed/ Rejected Request 401 Unauthorized No token generated, authid, redirectUrl are returned Invalid credential attempts are rejected within 300 ms. | H10: 401 | I10: Invalid OAuth2 request parameters | J10: /auth/token/v1/generate | K10: application/json | L10: 3TaenF9h5d9FCEEIZRVPc4AxdFggPaxA | M10: wE4n0CYiVOdJ9m8EfILMhxm0m4kOaUOr | N10: 263677df68 | O10: K6y28Ks1TyrwjONU0PatZ6BhOWfTAuHo | P10: application/json | Q10: 200061817815 | R10: send-funds.initiate
A11: 10 | B11: Y | C11: Y | D11: TS-EB-PRODUCTS-0301_2 | E11: TS-EB-PRODUCTS-0301_2: Account Authentication via Access Token v1.0_Generate Account Access Token API_Verify POST request using Invalid client credentials | F11: Send POST Request using valid ACTIVE Client Owned Account with invalid client-credentials | G11: Failed/ Rejected Request 401 Unauthorized No token generated, authid, redirectUrl are returned Invalid credential attempts are rejected within 300 ms. | H11: 401 | I11: Invalid OAuth2 request parameters | J11: /auth/token/v1/generate | K11: application/json | L11: 3TaenF9h5d9FCEEUYZRVPc4AxdFggPaxA | M11: wE4n0CYiVOdJ9m8EfKuMhxm0m4kOaUOr | N11: 263677df68 | O11: K6y28Ks1TyrwjONU0PatZ6BhOWfTAuHo | P11: application/json | Q11: 200061817815 | R11: send-funds.initiate
A12: 11 | B12: Y | C12: Y | D12: TS-EB-PRODUCTS-0301_3 | E12: TS-EB-PRODUCTS-0301_3: Account Authentication via Access Token v1.0_Generate Account Access Token API_Verify POST request using Invalid client credentials | F12: Send POST Request using valid ACTIVE Client Owned Account with invalid client-credentials | G12: Failed/ Rejected Request 401 Unauthorized No token generated, authid, redirectUrl are returned Invalid credential attempts are rejected within 300 ms. | H12: 401 | I12: Invalid OAuth2 request parameters | J12: /auth/token/v1/generate | K12: application/json | L12: 3TaenF9h5d9FCEEIZRVPc4AxdFggPaxA | N12: 263677df68 | O12: K6y28Ks1TyrwjONU0PatZ6BhOWfTAuHo | P12: application/json | Q12: 200061817815 | R12: send-funds.initiate
A13: 12 | B13: Y | C13: Y | D13: TS-EB-PRODUCTS-0301_4 | E13: TS-EB-PRODUCTS-0301_4: Account Authentication via Access Token v1.0_Generate Account Access Token API_Verify POST request using Invalid client credentials | F13: Send POST Request using valid ACTIVE Client Owned Account with invalid client-credentials | G13: Failed/ Rejected Request 401 Unauthorized No token generated, authid, redirectUrl are returned Invalid credential attempts are rejected within 300 ms. | H13: 401 | I13: Invalid OAuth2 request parameters | J13: /auth/token/v1/generate | K13: application/json | M13: wE4n0CYiVOdJ9m8EfKuMhxm0m4kOaUOr | N13: 263677df68 | O13: K6y28Ks1TyrwjONU0PatZ6BhOWfTAuHo | P13: application/json | Q13: 200061817815 | R13: send-funds.initiate
A14: 13 | B14: Y | C14: Y | D14: TS-EB-PRODUCTS-0302_1 | E14: TS-EB-PRODUCTS-0302_1: Account Authentication via Access Token v1.0_Generate Account Access Token API_Verify Send Request using Invalid Account Number | F14: Send POST Request using valid ACTIVE Client Owned Account with invalid client-credentials | G14: Failed / Rejected Request 400 Bad Request - error code invalid_account - clear errorDescription. No token or redirectUrl is issued. Core banking validation completes and rejects within 300 ms. | H14: 400 | I14: The accountNumber provided is invalid, not recognized, or not registered in Client Hub. | J14: /auth/token/v1/generate | K14: application/json | L14: 3TaenF9h5d9FCEEIZRVPc4AxdFggPaxA | M14: wE4n0CYiVOdJ9m8EfKuMhxm0m4kOaUOr | N14: 263677df68 | O14: K6y28Ks1TyrwjONU0PatZ6BhOWfTAuHo | P14: application/json | R14: send-funds.initiate
A15: 14 | B15: Y | C15: Y | D15: TS-EB-PRODUCTS-0302_2 | E15: TS-EB-PRODUCTS-0302_2: Account Authentication via Access Token v1.0_Generate Account Access Token API_Verify Send Request using Invalid Account Number | F15: Send POST Request using Invalid Client Owned Account with valid client-credentials. | G15: Failed / Rejected Request 400 Bad Request - error code invalid_account - clear errorDescription. No token or redirectUrl is issued. Core banking validation completes and rejects within 300 ms. | H15: 400 | I15: The accountNumber provided is invalid, not recognized, or not registered in Client Hub. | J15: /auth/token/v1/generate | K15: application/json | L15: 3TaenF9h5d9FCEEIZRVPc4AxdFggPaxA | M15: wE4n0CYiVOdJ9m8EfKuMhxm0m4kOaUOr | N15: 263677df68 | O15: K6y28Ks1TyrwjONU0PatZ6BhOWfTAuHo | P15: application/json | Q15: 200061817716 | R15: send-funds.initiate
A16: 15 | B16: Y | C16: Y | D16: TS-EB-PRODUCTS-0304 | E16: TS-EB-PRODUCTS-0304: Account Authentication via Access Token v1.0_Generate Account Access Token API_Verify Send Request using Not Existing Account Number | F16: Send POST Request using NOT EXISTING Client Owned Account with valid client-credentials. | G16: Failed / Rejected Request 400 Bad Request - error code invalid_account - clear errorDescription. No token or redirectUrl is issued. Core banking validation completes and rejects within 300 ms. | H16: 400 | I16: The accountNumber provided is invalid, not recognized, or not registered in Client Hub. | J16: /auth/token/v1/generate | K16: application/json | L16: 3TaenF9h5d9FCEEIZRVPc4AxdFggPaxA | M16: wE4n0CYiVOdJ9m8EfKuMhxm0m4kOaUOr | N16: 263677df68 | O16: K6y28Ks1TyrwjONU0PatZ6BhOWfTAuHo | P16: application/json | Q16: 999999999999 | R16: send-funds.initiate
A17: 16 | B17: Y | C17: Y | D17: TS-EB-PRODUCTS-0305 | E17: TS-EB-PRODUCTS-0305: Account Authentication via Access Token v1.0_Generate Account Access Token API_Verify Send Request using Malformed Account Number | F17: Send POST Request using MALFORMED Client Owned Account with valid client-credentials. | G17: Failed / Rejected Request 400 Bad Request - error code invalid_account - clear errorDescription. No token or redirectUrl is issued. Core banking validation completes and rejects within 300 ms. | H17: 400 | I17: The accountNumber provided is invalid, not recognized, or not registered in Client Hub. | J17: /auth/token/v1/generate | K17: application/json | L17: 3TaenF9h5d9FCEEIZRVPc4AxdFggPaxA | M17: wE4n0CYiVOdJ9m8EfKuMhxm0m4kOaUOr | N17: 263677df68 | O17: K6y28Ks1TyrwjONU0PatZ6BhOWfTAuHo | P17: application/json | Q17: 200P6181781S | R17: send-funds.initiate
A18: 17 | B18: Y | C18: Y | D18: TS-EB-PRODUCTS-0306 | E18: TS-EB-PRODUCTS-0306: Account Authentication via Access Token v1.0_Generate Account Access Token API_Validate POST Request using Valid values in Scope | F18: Send POST Request using Valid Scope value with valid client-credentials. | G18: Successful Status 200 OK - Valid scope indicated in Request Body Parameters contains [send-funds.initiate, receive-funds.generate, manage-funds.balance] (subscribed capabilities) | H18: 200 | J18: /auth/token/v1/generate | K18: application/json | L18: 3TaenF9h5d9FCEEIZRVPc4AxdFggPaxA | M18: wE4n0CYiVOdJ9m8EfKuMhxm0m4kOaUOr | N18: 263677df68 | O18: K6y28Ks1TyrwjONU0PatZ6BhOWfTAuHo | P18: application/json | Q18: 200061817815 | R18: send-funds.initiate
A19: 18 | B19: Y | C19: Y | D19: TS-EB-PRODUCTS-0307 | E19: TS-EB-PRODUCTS-0307: Account Authentication via Access Token v1.0_Generate Account Access Token API_Validate POST Request using Invalid values in Scope | F19: Send POST Request using Invalid Scope value with valid client-credentials. | G19: Failed / Rejected Request 400 Bad Request -invalid_scope with clear errorDescription. contains unknown or disallowed values [send-funds.initiate, , manage-funds.balance] (not subscribed capabilities) | H19: 400 | I19: The scope provided is invalid or not recognized | J19: /auth/token/v1/generate | K19: application/json | L19: 3TaenF9h5d9FCEEIZRVPc4AxdFggPaxA | M19: wE4n0CYiVOdJ9m8EfKuMhxm0m4kOaUOr | N19: 263677df68 | O19: K6y28Ks1TyrwjONU0PatZ6BhOWfTAuHo | P19: application/json | Q19: 200061817815 | R19: send-funds.invalid
A20: 19 | B20: N | C20: N | D20: TS-EB-PRODUCTS-0001 | E20: TS-EB-PRODUCTS-0001: Account Authentication via Access Token v1.0_Generate Account Access Token API_Send POST Request using Valid Account Access Token | F20: Valid Account Access Token issued by Account Authentication API Token not expired or revoked Token matches client credentials and Partner-ID | G20: Successful Status 200 OK API request successfully processed Ownership and consent verified Token validation executes in p99 latency < 30 ms. | H20: 200 | J20: /auth/token/v1/generate | K20: application/json | P20: application/json | Q20: 200061817815 | R20: send-funds.initiate
A21: 20 | B21: N | C21: N | D21: TS-EB-PRODUCTS-0002 | E21: TS-EB-PRODUCTS-0002: Account Authentication via Access Token v1.0_Generate Account Access Token API_Verify API Call using Expired Account Access Token | F21: Send POST Request using Expired Account Access Token | G21: Failed/Rejected Status 401 Unauthorized - clear error message. -Token validation executes in p99 latency < 30 ms. | H21: 401 | J21: /auth/token/v1/generate | K21: application/json | P21: application/json | R21: send-funds.initiate
A22: 21 | B22: N | C22: N | D22: TS-EB-PRODUCTS-0003 | E22: TS-EB-PRODUCTS-0003: Account Authentication via Access Token v1.0_Generate Account Access Token API_Verify API Call using Revoked Account Access Token | F22: Send POST Request using Exceeding / Fewer Account Access Token | G22: Failed/Rejected Status 401 Unauthorized - clear error message. - Token validation executes in p99 latency < 30 ms. | H22: 401 | J22: /auth/token/v1/generate | K22: application/json | P22: application/json | R22: send-funds.initiate
A23: 22 | B23: N | C23: N | D23: TS-EB-PRODUCTS-0004 | E23: TS-EB-SB-PRODUCTS-0005: Account Authentication via Access Token v1.0_Generate Account Access Token API_Verify API Call using malformed Account Access Token | F23: Send POST Request without VALID Account Access Token | G23: Failed/Rejected Status 401 Unauthorized - clear error message. - Token validation executes in p99 latency < 30 ms. | H23: 401 | J23: /auth/token/v1/generate | K23: application/json | P23: application/json | R23: send-funds.initiate
A24: 23 | B24: N | C24: N | D24: TS-EB-PRODUCTS-0005 | E24: TS-EB-PRODUCTS-0005: Account Authentication via Access Token v1.0_Generate Account Access Token API_Verify API Call using malformed Account Access Token | F24: Send POST Request using Malformed Account Access Token | G24: Failed/Rejected Status 401 Unauthorized - clear error message. - Token validation executes in p99 latency < 30 ms. | H24: 401 | J24: /auth/token/v1/generate | K24: application/json | P24: application/json | R24: send-funds.initiate
A25: 24 | B25: N | C25: N | D25: TS-EB-TEST-S7-PRODUCTS-0001 | E25: TS-EB-TEST-S7-PRODUCTS-0001: Account Authentication via Access Token v1.0_Generate Account Access Token API_Verify if access token generated by specific client partner (A) can also be used by the other partner client (B) | F25: 1. Generate Access Token using Auth API 2. Use the generated access token against an API request containing a different PartnerId/Application than the one associated with the token. | G25: 1. Access Token should be generated: Sample Response: { "accessToken": "52N8qO9rbr7veEWcEbPWqZ4FSd2YyE2i", "tokenType": "bearer", "expiresIn": 3600, "authId": "auth-18bcfcea-4478-4bba-8810-8bd2a1bd3165" } 2. The API validates the PartnerId/Application against the claims contained in the access token and rejects the request. 403 Forbidden – Token is valid but does not belong to the requested PartnerId/Application. | H25: 403 | J25: /auth/token/v1/generate | K25: application/json | P25: application/json | Q25: 200061817815 | R25: send-funds.initiate
A26: 25 | B26: N | C26: N | D26: TS-EB-TEST-S7-PRODUCTS-0003 | E26: TS-EB-TEST-S7-PRODUCTS-0003: Account Authentication via Access Token v1.0_Generate Account Access Token API_Verify if access token generated by Test can be used on other environments | F26: 1. Generate Access Token using Auth API via Test environment 2. Use the Access Token to other API's with different environments | G26: 1. Access token is generated: { "accessToken": "52N8qO9rbr7veEWcEbPWqZ4FSd2YyE2i", "tokenType": "bearer", "expiresIn": 3600, "authId": "auth-18bcfcea-4478-4bba-8810-8bd2a1bd3165" } 2. Request Action should be restricted. Access token should only be accessible per Environment Sample: Auth API [Test] -> LFT/Check Status [Test] 403 Forbidden | H26: 403 | J26: /auth/token/v1/generate | K26: application/json | L26: 3TaenF9h5d9FCEEIZRVPc4AxdFggPaxA | M26: wE4n0CYiVOdJ9m8EfKuMhxm0m4kOaUOr | N26: 263677df68 | O26: K6y28Ks1TyrwjONU0PatZ6BhOWfTAuHo | P26: application/json | Q26: 200061817815 | R26: send-funds.initiate
A27: 26 | B27: N | C27: N | D27: TS-EB-PRODUCTS-0298 | E27: TS-EB-PRODUCTS-0298: Account Authentication via Access Token v1.0_Generate Account Access Token API_Verify send request from an IP not whitelisted for the application. | F27: Send POST Request using Not Whitelisted IP | G27: Failed Request 403 (Forbidden) No token generated | H27: 403 | J27: /auth/token/v1/generate | K27: application/json | L27: 3TaenF9h5d9FCEEIZRVPc4AxdFggPaxA | M27: wE4n0CYiVOdJ9m8EfKuMhxm0m4kOaUOr | N27: 263677df68 | O27: K6y28Ks1TyrwjONU0PatZ6BhOWfTAuHo | P27: application/json | Q27: 200061817815 | R27: send-funds.initiate
A28: 27 | B28: N | C28: N | D28: TS-EB-PRODUCTS-0300 | E28: TS-EB-PRODUCTS-0300: Account Authentication via Access Token v1.0_Generate Account Access Token API_Verify status in Database of successful Client Owned Account Authentication | F28: Send POST Request using valid ACTIVE Client Owned Account with valid client-credentials. Validate DB | G28: Status in DB is COMPLETED | H28: 200 | J28: /auth/token/v1/generate | K28: application/json | L28: 3TaenF9h5d9FCEEIZRVPc4AxdFggPaxA | M28: wE4n0CYiVOdJ9m8EfKuMhxm0m4kOaUOr | N28: 263677df68 | O28: K6y28Ks1TyrwjONU0PatZ6BhOWfTAuHo | P28: application/json | Q28: 200061817815 | R28: send-funds.initiate

Sheet PTTBankList
A1: # | B1: ExecutionFlag | C1: CORE | D1: TC_ID | E1: Description | F1: StepAction | G1: ExpectedResult | H1: ExpectedStatus | I1: ExpectedResponseDescription | J1: IN_EndPoint | K1: IN_ParamChannel | L1: IN_HeadPartnerID | M1: IN_HeadAPIKey | N1: IN_HeadCorrelationID | O1: OUT_RequestHeaders | P1: OUT_RequestBody | Q1: OUT_ResponseHeaders | R1: OUT_ResponseBody
A2: 1 | B2: =C2 -> Y | C2: Y | D2: TS-EB-PRODUCTS-0320 | E2: TS-EB-PRODUCTS-0320: Send Funds via Local Fund Transfer v1.0 _Get Supported Banks and Wallets API_Verify successful GET request of Get Supported Banks and Wallets API | F2: Send GET Request of Get Supported Banks and Wallets API | G2: Status HTTP 200 OK Response Body: Complete and accurate list of Supported Receiving Financial Institutions (banks and e‑wallets) available for disbursements under the Send Funds via Local Fund Transfer product. { "data": [ { "bankName": "Alipay / Lazada Wallet", "pesonet": { "status": false, "brstn": "" }, "instapay": { "status": true, "brstn": "7021" }, "enable": true }, { "bankName": "Zybi Tech Inc. / JuanCash", "pesonet": { "status": true, "brstn": "18080012" }, "instapay": { "status": true, "brstn": "7012" }, "enable": true } ] } Institutioin Entries: Institution name, enablement flag, and supported settlement rails with corresponding Bank Identification Codes (BICs) where applicable. | H2: 200 | J2: /send-funds/localft/v1/list/institutions | L2: 263677df68 | M2: K6y28Ks1TyrwjONU0PatZ6BhOWfTAuHo | N2: 9a29f3f4-c0ca-478f-b7b9-f6d25dcad73a
A3: 2 | B3: Y | C3: Y | D3: TS-EB-PRODUCTS-0321 | E3: TS-EB-PRODUCTS-0321: Send Funds via Local Fund Transfer v1.0 _Get Supported Banks and Wallets API_Verify when Optional field "Transfer Network" (channel) is not provided to filter Financial Institutions | F3: Send GET Request of Get Supported Banks and Wallets API when channel is empty | G3: When list channel parameter is not provided, the API returns institutions across all supported transfer networks channel: Intrabank, Instapay, PESONet) Sample Response Body: "data": [ { "bankName": "Alipay / Lazada Wallet", "pesonet": { "status": false, "brstn": "" }, "instapay": { "status": true, "brstn": "7021" }, "enable": true }, { "bankName": "Zybi Tech Inc. / JuanCash", "pesonet": { "status": true, "brstn": "18080012" }, "instapay": { "status": true, "brstn": "7012" }, "enable": true } ] } | H3: 200 | J3: /send-funds/localft/v1/list/institutions | L3: 263677df68 | M3: K6y28Ks1TyrwjONU0PatZ6BhOWfTAuHo | N3: e6f1bb53-631b-4f25-8c70-c4c4d4d0f9fa
